Workbook

Sheet info
B4: Vestas Sales Data — Data Ownership & Use Notice
B6: Copyright (c) Thomas Buhl. All rights reserved.
B8: I, Thomas Buhl, generated the dataset contained in this repository (“Data”) and I own the Data.
B10: Permission is granted to use the Data for personal, academic, and internal evaluation purposes, provided that you give appropriate credit to Thomas Buhl.
B12: Commercial use is not permitted without prior written permission. If you would like to use the Data for commercial purposes, please contact:
B13: thomasbuhldk@gmail.com
B16: DISCLAIMER
B17: THE DATA IS PROVIDED “AS IS”, WITHOUT WARRANTY OF ANY KIND, EXPRESS OR IMPLIED, INCLUDING BUT NOT LIMITED TO THE WARRANTIES OF ACCURACY, COMPLETENESS, NON-INFRINGEMENT, MERCHANTABILITY, OR FITNESS FOR A PARTICULAR PURPOSE.
B19: LIMITATION OF LIABILITY
B20: IN NO EVENT SHALL THOMAS BUHL BE LIABLE FOR ANY CLAIM, DAMAGES, OR OTHER LIABILITY, WHETHER IN AN ACTION OF CONTRACT, TORT, OR OTHERWISE, ARISING FROM, OUT OF, OR IN CONNECTION WITH THE DATA OR THE USE OR OTHER DEALINGS IN THE DATA. USE THE DATA AT YOUR OWN RISK.
B22: Unofficial dashboard — not affiliated with or endorsed by Vestas. Data compiled manually from public Vestas reports/announcements; verify against original sources. Provided “as is” without warranty.
B24: ## Sources and attribution
... B36: The data and dashboard are provided “as is” without warranties of any kind. I make no guarantees of accuracy, completeness, or fitness for a particular purpose. Use at your own risk. I am not responsible or liable for any losses or damages arising from use of the data or dashboard.

Sheet Vestas Economy
B1: 1995 | C1: 1996 | D1: 1997 | E1: 1998 | F1: 1999 | G1: 2000 | H1: 2001 | I1: 2002 | J1: 2003 | K1: 2004 | L1: 2005 | M1: 2006 | N1: 2007 | O1: 2008 | P1: 2009 | Q1: 2010 | R1: 2011 | S1: 2012 | T1: 2013 | U1: 2014 | V1: 2015 | W1: 2016 | X1: 2017 | Y1: 2018 | Z1: 2019 | AA1: 2020 | AB1: 2021 | AC1: 2022 | AD1: 2023 | AE1: 2024 | AF1: 2025
A2: revenue (mEUR) | C2: 252 | D2: 262 | E2: 379 | F2: 634 | G2: 896 | H2: 1282 | I2: 1395 | J2: 1653 | K2: 2363 | L2: 3583 | M2: 3854 | N2: 4861 | O2: 6035 | P2: 5079 | Q2: 6920 | R2: 5836 | S2: 7216 | T2: 6084 | U2: 6910 | V2: 8423 | W2: 10237 | X2: 9953 | Y2: 10134 | Z2: 12147 | AA2: 14819 | AB2: 15587 | AC2: 14486 | AD2: 15382 | AE2: 17295 | AF2: 18822
A3: gross profit | C3: 27 | D3: 32 | E3: 50 | F3: 69 | G3: 136 | H3: 192 | I3: 142 | J3: 150 | K3: 120 | L3: 84 | M3: 461 | N3: 825 | O3: 1125 | P3: 836 | Q3: 1175 | R3: 725 | S3: 796 | T3: 896 | U3: 1178 | V3: 1505 | W3: 2126 | X3: 1963 | Y3: 1631 | Z3: 1761 | AA3: 1538 | AB3: 1556 | AC3: 118 | AD3: 1283 | AE3: 2057 | AF3: 2497
A4: EBIT | C4: 15 | D4: 19 | E4: 32 | F4: 69 | G4: 100 | H4: 143 | I4: 74 | J4: 74 | K4: -49 | L4: -116 | M4: 201 | N4: 202 | O4: 614 | P4: 251 | Q4: 310 | R4: -60 | S4: -697 | T4: 102 | U4: 607 | V4: 906 | W4: 1421 | X4: 1230 | Y4: 921 | Z4: 1004 | AA4: 698 | AB4: 289 | AC4: -1596 | AD4: 292 | AE4: 794 | AF4: 1015
A5: sales of projects | K5: 2161 | L5: 3340 | M5: 3577 | N5: 4497 | O5: =5566+73 -> 5639 | P5: =6126+6 -> 6132 | Q5: =6283+14 -> 6297 | R5: =5115+16 -> 5131 | S5: =6298+32 -> 6330 | T5: =5082+48 -> 5130 | U5: 5946 | V5: 7285 | W5: 8928 | X5: =X2-X6 -> 8431 | Y5: 8465 | Z5: 10276 | AA5: 12764 | AB5: 13103 | AC5: 11331 | AD5: 11814 | AE5: 13598 | AF5: 15052
A6: sales of service | K6: 115 | L6: 172 | M6: 214 | N6: 298 | O6: 396 | P6: 504 | Q6: 623 | R6: 705 | S6: 886 | T6: 954 | U6: 964 | V6: 1138 | W6: 1309 | X6: 1522 | Y6: 1669 | Z6: 1871 | AA6: 2055 | AB6: 2484 | AC6: 3155 | AD6: 3568 | AE6: 3697 | AF6: 3770
A7: Order intake (bnEUR) | N7: 5.5 | O7: 6.4 | P7: 3.2 | Q7: 8.6 | R7: 7.3 | S7: 3.8 | T7: 5.8 | U7: 5.8 | V7: 8.2 | W7: 9.5 | X7: 8.9 | Y7: 10.6 | Z7: 13.8 | AA7: 12.7 | AB7: 11.6 | AC7: 11.9 | AD7: 18.5 | AE7: 19.2 | AF7: 17.4
A8: Order inkake (MW) | E8: 556 | F8: 1147 | G8: 1434 | H8: 2520 | I8: 2670 | J8: 2667 | K8: 2784 | L8: 3185 | M8: 4239 | N8: 5613 | O8: 6019 | P8: 3072 | Q8: 8673 | R8: 7397 | S8: 3738 | T8: 5964 | U8: 6544 | V8: 8943 | W8: 10494 | X8: 11237 | Y8: 14214 | Z8: 17877 | AA8: 17249 | AB8: 13896 | AC8: 11189 | AD8: 18286 | AE8: 16844 | AF8: 16292
A9: Order backlog – wind turbines (bnEUR) | N9: 4.8 | O9: 5.2 | P9: 2.2 | Q9: 7.7 | R9: 9.6 | S9: 7.1 | T9: 6.8 | U9: 6.7 | V9: 7.9 | W9: 8.5 | X9: 8.8 | Y9: 11.9 | Z9: 16 | AA9: 19 | AB9: 18.1 | AC9: 19.1 | AD9: 26 | AE9: 31.6 | AF9: 33.2
A10: Order backlog – service (bnEUR) | P10: 1.9 | Q10: 2.8 | R10: 3.9 | S10: 5.3 | T10: 6.7 | U10: 7 | V10: 8.9 | W10: 10.7 | X10: 12.1 | Y10: 14.3 | Z10: 17.8 | AA10: 23.9 | AB10: 27.8 | AC10: 30.4 | AD10: 34.1 | AE10: 36.8 | AF10: 38.7
A11: Order backlog - windturbines (MW) | X11: 11492 | Y11: 15646 | Z11: 20974 | AA11: 24630 | AB11: 21984 | AC11: 19623 | AD11: 25315 | AE11: 29241 | AF11: 31026
A13: WT order backlog/sold GW | N13: =1000*N9/N8 -> 0.85515767 | O13: =1000*O9/O8 -> 0.86393089 | P13: =1000*P9/P8 -> 0.71614583 | Q13: =1000*Q9/Q8 -> 0.88781275 | R13: =1000*R9/R8 -> 1.2978234 | S13: =1000*S9/S8 -> 1.8994114 | T13: =1000*T9/T8 -> 1.1401744 | U13: =1000*U9/U8 -> 1.0238386 | ... AF13: =1000*AF9/AF8 -> 2.03781
A14: Service order backlog/sold GW | P14: =1000*P10/P8 -> 0.61848958 | Q14: =1000*Q10/Q8 -> 0.322841 | R14: =1000*R10/R8 -> 0.52724077 | S14: =1000*S10/S8 -> 1.4178705 | T14: =1000*T10/T8 -> 1.1234071 | U14: =1000*U10/U8 -> 1.0696822 | V14: =1000*V10/V8 -> 0.99519177 | W14: =1000*W10/W8 -> 1.0196303 | ... AF14: =1000*AF10/AF8 -> 2.375399
A15: Produced and shipped wind turbine (MW) | F15: 653 | G15: 805 | H15: 1645 | I15: 1640 | J15: 1812 | L15: 3900 | M15: 4313 | N15: 4974 | O15: 6160 | P15: 6131 | Q15: 4057 | R15: 5054 | S15: 6171 | T15: 4513 | U15: 6125 | V15: 7948 | W15: 11237 | X15: 11237 | Y15: 10676 | Z15: 12618 | AA15: 17055 | AB15: 17845 | AC15: 13106 | AD15: 11666 | AE15: 13198 | AF15: 13374
A16: Produced and shipped wind turbine (#) | F16: 843 | G16: 1014 | H16: 1970 | I16: 1453 | J16: 1369 | M16: 2553 | N16: 2752 | O16: 3250 | P16: 3320 | Q16: 2025 | R16: 2571 | S16: 2765 | T16: 2025 | U16: 2527 | V16: 3330 | W16: 4264 | X16: 4241 | Y16: 3729 | Z16: 4185 | AA16: 5239 | AB16: 4456 | AC16: 3126 | AD16: 2554 | AE16: 2837 | AF16: 2737
A17: deliveries [MW] | Z17: 12884 | AA17: 17212 | AB17: 16594 | AC17: 13328 | AD17: 12685 | AE17: 12900 | AF17: 14537
A19: employees:
A20: Manufacturing and sourcing | L20: 6338 | O20: 11166 | R20: 11000 | S20: 7528 | T20: 6430 | U20: 10092 | V20: 10282 | W20: 10112
A21: sales | L21: 3341 | O21: 7143 | R21: 7681 | S21: 6187 | T21: 5869 | U21: 6214 | V21: 7682 | W21: 8956
A22: Technology and Service (R&D) | O22: 1345 | R22: 2037 | S22: 2142 | T22: 1797 | U22: 1265 | V22: 1292 | W22: 1414
A23: Others | L23: 939 | O23: 1175 | R23: 2003 | S23: 1921 | T23: 1401 | U23: 2098 | V23: 1251 | W23: 1342
A25: Material comsumption
A26: Metals | I26: 61113 | J26: 66093 | K26: 90732 | L26: 143170 | M26: 164413 | N26: 170505 | O26: 187478 | P26: 202624 | Q26: 171000 | R26: 212000 | S26: 192000 | T26: 119000
A27: Other raw materials | I27: 15428 | J27: 15731 | K27: 20080 | L27: 82592 | M27: 93983 | N27: 111541 | O27: 129207 | P27: 126600 | Q27: 107000 | R27: 105000 | S27: 121000 | T27: 91000
A28: Waste of on operation [kt] | Z28: 85 | AA28: 89 | AB28: 70 | AC28: 47 | AD28: 44 | AE28: 44 | AF28: 54
A29: of which recycled [kt] | Z29: 43 | AA29: 46 | AB29: 35 | AC29: 26 | AD29: 30 | AE29: 30 | AF29: =0.69*AF28 -> 37.26
A30: Material effeciency - t waste pr MW shipped | Z30: 3.3 | AA30: 2.5 | AB30: 2 | AC30: 1.6 | AD30: 1.2 | AE30: 1 | AF30: 1.3
A31: Consumption of energy (GWh) | AA31: 621 | AB31: 738 | AC31: 641 | AD31: 658 | AE31: 640 | AF31: 677
A33: average # employees | C33: 1108 | D33: 1206 | E33: 1477 | F33: 2261 | G33: 3282 | H33: 4582 | I33: 5974 | J33: 6394 | K33: 9449 | L33: 10300 | M33: 11334 | N33: 13820 | O33: 17924 | P33: 20832 | Q33: 22216 | R33: 22926 | S33: 21033 | T33: 17051 | U33: 17905 | V33: 18986 | W33: 21625 | X33: 22504 | Y33: 24221 | Z33: 24964 | AA33: 26121 | AB33: 29164 | AC33: 28779 | AD33: 29463 | AE33: 32729
A34: EOY employees | E34: 1813 | F34: 2626 | G34: 3852 | H34: 5240 | I34: 5999 | J34: 6525 | K34: 9594 | L34: 10618 | M34: 12309 | N34: 15305 | O34: 20829 | P34: 20730 | Q34: 23252 | R34: 22721 | S34: 17778 | T34: 15497 | U34: 19669 | V34: 20507 | W34: 21824 | X34: 23303 | Y34: 24648 | Z34: 25542 | AA34: 29378 | AB34: 29427 | AC34: 28438 | AD34: 30586 | AE34: 35100 | AF34: 36973
A36: Turbine sale index | O36: 100 | P36: =P5/$O5*100 -> 108.74268 | Q36: =Q5/$O5*100 -> 111.66874 | R36: =R5/$O5*100 -> 90.991311 | S36: =S5/$O5*100 -> 112.25395 | T36: =T5/$O5*100 -> 90.973577 | U36: =U5/$O5*100 -> 105.44423 | V36: =V5/$O5*100 -> 129.18957 | W36: =W5/$O5*100 -> 158.32594 | ... AF36: =AF5/$O5*100 -> 266.92676
A37: Service sale index | O37: 100 | P37: =P6/$O6*100 -> 127.27273 | Q37: =Q6/$O6*100 -> 157.32323 | R37: =R6/$O6*100 -> 178.0303 | S37: =S6/$O6*100 -> 223.73737 | T37: =T6/$O6*100 -> 240.90909 | U37: =U6/$O6*100 -> 243.43434 | V37: =V6/$O6*100 -> 287.37374 | W37: =W6/$O6*100 -> 330.55556 | ... AF37: =AF6/$O6*100 -> 952.0202
A39: average MW price [mEUR/MW] | N39: =1000*N7/N8 -> 0.97986816 | O39: =1000*O7/O8 -> 1.0632996 | P39: =1000*P7/P8 -> 1.0416667 | Q39: =1000*Q7/Q8 -> 0.99158307 | R39: =1000*R7/R8 -> 0.98688658 | S39: =1000*S7/S8 -> 1.0165864 | T39: =1000*T7/T8 -> 0.97250168 | U39: =1000*U7/U8 -> 0.88630807 | ... AF39: =1000*AF7/AF8 -> 1.0680088
A40: In % | O40: =O39/$O$39 -> 1 | P40: =P39/$O$39 -> 0.97965495 | Q40: =Q39/$O$39 -> 0.93255289 | R40: =R39/$O$39 -> 0.92813598 | S40: =S39/$O$39 -> 0.95606775 | T40: =T39/$O$39 -> 0.91460744 | U40: =U39/$O$39 -> 0.83354504 | V40: =V39/$O$39 -> 0.86233297 | ... AF40: =AF39/$O$39 -> 1.0044289
A42: Weighted average service contract lenght | W42: ='OI 2016'!E125 -> 5.6366513 | X42: ='OI 2017'!E155 -> 2.3568755 | Y42: ='OI 2018'!E155 -> 10.306983 | Z42: ='OI 2019'!E156 -> 12.122227 | AA42: ='OI 2020'!E187 -> 14.699832 | AB42: ='OI 2021'!E189 -> 5.3373273
C45: Servicemargin | D45: Samlet margin | E45: Margin eksl. service
A46: 16Q1 | C46: 17.4 | D46: 5.8 | E46: 2.83
A47: 16Q2 | C47: 17.8 | D47: 15.6 | E47: 15.28
A48: 16Q3 | C48: 14.1 | D48: 14.9 | E48: 15.01
A49: 16Q4 | C49: 19.1 | D49: 15.2 | E49: 14.72
A50: 17Q1 | C50: 19.2 | D50: 11.2 | E50: 10.58
A51: 17Q2 | C51: 19.4 | D51: 12.6 | E51: 11.28
A52: 17Q3 | C52: 17.9 | D52: 12.9 | E52: 12.17
A53: 17Q4 | C53: 23.4 | D53: 12.3 | E53: 10.65
A54: 18Q1 | C54: 26.8 | D54: 7.4 | E54: 2.1
A55: 18Q2 | C55: 25.2 | D55: 11.5 | E55: 8.39
A56: 18Q3 | C56: 24.4 | D56: 8.4 | E56: 5.67
C58: Order backlog – service (bnEUR) | D58: Order backlog – wind turbines (bnEUR)
A60: 2009 | C60: =P10 -> 1.9 | D60: =P9 -> 2.2 | M60: sales pr quater | O60: for public orders
A61: 2010 | C61: =Q10 -> 2.8 | D61: =Q9 -> 7.7 | N61: q1 | O61: q2 | P61: q3 | Q61: q4 | R61: total
A62: 2011 | C62: =R10 -> 3.9 | D62: =R9 -> 9.6 | M62: 2025 | N62: ='OI 2025'!A16 -> 2398 | O62: ='OI 2025'!A32 -> 1112 | P62: ='OI 2025'!A66 -> 4003 | Q62: ='OI 2025'!A108 -> 5476 | R62: =SUM(N62:Q62) -> 12989
A63: 2012 | C63: =S10 -> 5.3 | D63: =S9 -> 7.1 | M63: 2024 | N63: ='OI 2024'!A12 -> 1503 | O63: ='OI 2024'!A31 -> 2902 | P63: ='OI 2024'!A54 -> 3742 | Q63: ='OI 2024'!A95 -> 6028 | R63: =SUM(N63:Q63) -> 14175
A64: 2013 | C64: =T10 -> 6.7 | D64: =T9 -> 6.8 | M64: 2023 | N64: ='OI 2023'!A14 -> 3022 | O64: ='OI 2023'!A28 -> 1802 | P64: ='OI 2023'!A49 -> 4044 | Q64: ='OI 2023'!A79 -> 6945 | R64: =SUM(N64:Q64) -> 15813
A65: 2014 | C65: =U10 -> 7 | D65: =U9 -> 6.7 | M65: 2022 | N65: ='OI 2022'!A25 -> 2179 | O65: ='OI 2022'!A41 -> 1783 | P65: ='OI 2022'!A50 -> 1240 | Q65: ='OI 2022'!A72 -> 3366 | R65: =SUM(N65:Q65) -> 8568
A66: 15Q1 | C66: 7.5 | D66: 7.5 | M66: 2021 | N66: ='OI 2021'!A19 -> 1060 | O66: ='OI 2021'!A48 -> 4127 | P66: ='OI 2021'!A70 -> 3167 | Q66: ='OI 2021'!A85 -> 2011 | R66: =SUM(N66:Q66) -> 10365
A67: 15Q2 | C67: 8.1 | D67: 8.8 | M67: 2020 | N67: ='OI 2020'!A24 -> 2064 | O67: ='OI 2020'!A55 -> 3076 | P67: ='OI 2020'!A86 -> 3535 | Q67: ='OI 2020'!A121 -> 3818 | R67: =SUM(N67:Q67) -> 12493
A68: 15Q3 | C68: 8.2 | D68: 8.2 | M68: 2019 | N68: ='OI 2019'!A18 -> 2233 | O68: ='OI 2019'!A43 -> 4601 | P68: ='OI 2019'!A63 -> 3748 | Q68: ='OI 2019'!A93 -> 2996 | R68: =SUM(N68:Q68) -> 13578
A69: 15Q4 | C69: 8.9 | D69: 7.9 | M69: 2018 | N69: ='OI 2018'!L134 -> 1176 | O69: ='OI 2018'!L135 -> 2695.2 | P69: ='OI 2018'!L136 -> 2672 | Q69: ='OI 2018'!L137 -> 4174 | R69: =SUM(N69:Q69) -> 10717.2
A70: 16Q1 | C70: 9.4 | D70: 8.6 | M70: 2017 | N70: ='OI 2017'!L131 -> 1353 | O70: ='OI 2017'!L132 -> 1956 | P70: ='OI 2017'!L133 -> 1739 | Q70: ='OI 2017'!L134 -> 3361 | R70: =SUM(N70:Q70) -> 8409
A71: 16Q2 | C71: 9.9 | D71: 8.2 | M71: 2016 | N71: ='OI 2016'!L103 -> 1806 | O71: ='OI 2016'!L104 -> 1124 | P71: ='OI 2016'!L105 -> 1350 | Q71: ='OI 2016'!L106 -> 3305 | R71: =SUM(N71:Q71) -> 7585
A72: 16Q3 | C72: 9.9 | D72: 7.2 | M72: 2015 | N72: ='OI 2015'!L106 -> 1332 | O72: ='OI 2015'!L107 -> 2467 | P72: ='OI 2015'!L108 -> 1131 | Q72: ='OI 2015'!L109 -> 1823 | R72: =SUM(N72:Q72) -> 6753
A73: 16Q4 | C73: 10.7 | D73: 8.5 | M73: 2014 | N73: ='OI 2014'!L103 -> 390 | O73: ='OI 2014'!L104 -> 1544 | P73: ='OI 2014'!L105 -> 604 | Q73: ='OI 2014'!L106 -> 1574 | R73: =SUM(N73:Q73) -> 4112
A74: 17Q1 | C74: 11 | D74: 9 | M74: 2013 | N74: ='OI 2013'!L99 -> 271 | O74: ='OI 2013'!L100 -> 1295 | P74: ='OI 2013'!L101 -> 1250 | Q74: ='OI 2013'!L102 -> 1509 | R74: =SUM(N74:Q74) -> 4325
A75: 17Q2 | C75: 11.1 | D75: 9.1 | M75: 2013 | N75: 271 | O75: 1295 | P75: 1250 | Q75: 1509 | R75: =SUM(N75:Q75) -> 4325
A76: 17Q3 | C76: 11.4 | D76: 8.8 | M76: 2012 | N76: 915 | O76: 704 | P76: 158 | Q76: 505 | R76: =SUM(N76:Q76) -> 2282
A77: 17Q4 | C77: 12.1 | D77: 8.8 | M77: 2011 | N77: 338 | O77: 1479 | P77: 737 | Q77: 2035 | R77: =SUM(N77:Q77) -> 4589
A78: 18Q1 | C78: 12.3 | D78: 9.3 | M78: 2010 | N78: 783 | O78: 2603 | P78: 2089 | Q78: 1524 | R78: =SUM(N78:Q78) -> 6999
A79: 18Q2 | C79: 12.8 | D79: 10.2
A80: 18Q3 | C80: 13.2 | D80: 10.5
C83: Pris/MW | D83: €/MW
A84: 2007 | C84: =D84*7.45 -> 7.3000178 | D84: =N39 -> 0.97986816
A85: 2008 | C85: =D85*7.45 -> 7.9215817 | D85: 1.0632996
A86: 2009 | C86: =D86*7.45 -> 7.7604167 | D86: 1.0416667
A87: 2010 | C87: =D87*7.45 -> 7.3872939 | D87: 0.99158307
A88: 2011 | C88: =D88*7.45 -> 7.352305 | D88: 0.98688658
A89: 2012 | C89: =D89*7.45 -> 7.5735688 | D89: 1.0165864
A90: 13Q1 | C90: 7.7491959 | D90: =C90/7.6 -> 1.019631
A91: 13Q2 | C91: 7.9087314 | D91: =C91/7.45 -> 1.0615747
A92: 13Q3 | C92: 6.8268128 | D92: =C92/7.45 -> 0.9163507
A93: 13Q4 | C93: 6.8513204 | D93: =C93/7.45 -> 0.91964032
A94: 14Q1 | C94: 6.5233586 | D94: =C94/7.45 -> 0.8756186
A95: 14Q2 | C95: 6.4672868 | D95: =C95/7.45 -> 0.86809219
A96: 14Q3 | C96: 6.477513 | D96: =C96/7.45 -> 0.86946483
A97: 14Q4 | C97: 6.7939499 | D97: =C97/7.45 -> 0.91193959
A98: 15Q1 | C98: 6.7998924 | D98: =C98/7.45 -> 0.91273724
A99: 15Q2 | C99: 6.6537181 | D99: =C99/7.45 -> 0.89311653
A100: 15Q3 | C100: 7.3979247 | D100: =C100/7.45 -> 0.99301003
A101: 15Q4 | C101: 6.6902952 | D101: =C101/7.45 -> 0.8980262
A102: 16Q1 | C102: 6.1900793 | D102: =C102/7.45 -> 0.83088313
... A108: 17Q3 | C108: 5.968024 | D108: =C108/7.45 -> 0.80107705
A109: 17Q4 | C109: 5.5204222 | D109: 0.74
A110: 18Q1 | C110: 5.4458219 | D110: 0.73
A111: 18Q2 | C111: 5.2966213 | D111: 0.71
A112: 18Q3 | C112: 5.8188234 | D112: 0.78
A113: 18Q4 | C113: 5.67 | D113: 0.76
A114: 19Q1 | C114: 6.04 | D114: 0.81
A115: 19q2 | D115: 0.75
A116: 19q3 | D116: 0.75
A117: 19q4 | D117: 0.79
A118: 20q1 | D118: 0.72
...

Sheet Order and Service summary
E1: If model is specified | V1: Size | AG1: MW of each service
C2: Turbine model of platform | D2: 2014 | E2: 2015 | F2: 2016 | G2: 2017 | H2: 2018 | I2: 2019 | J2: 2020 | K2: 2021 | L2: 2022 | M2: 2023 | N2: 2024 | O2: 2025 | R2: 2012 | S2: 2013 | T2: 2014 | U2: 2015 | V2: 2016 | W2: 2017 | X2: 2018 | Y2: 2019 | Z2: 2020 | AA2: 2021 | AB2: 2022 | AC2: 2023 | AF2: 2014 | AG2: 2015 | AH2: 2016 | AI2: 2017 | AJ2: 2018 | AK2: 2019 | AL2: 2020
C3: 2MW | D3: =SUMIF('OI 2014'!$I$87:$I$101,C3,'OI 2014'!$L$87:$L$101) -> 30 | E3: =SUMIF('OI 2015'!$I$87:$I$101,C3,'OI 2015'!$L$87:$L$101) -> 75 | F3: =SUMIF('OI 2016'!$I$87:$I$101,C3,'OI 2016'!$L$87:$L$101) -> 184.6 | G3: =SUMIF('OI 2017'!$I$112:$I$128,C3,'OI 2017'!$L$112:$L$128) -> 175 | H3: =SUMIF('OI 2018'!$I$112:$I$131,C3,'OI 2018'!$L$112:$L$131) -> 100 | I3: =SUMIF('OI 2019'!$I$113:$I$132,C3,'OI 2019'!$L$113:$L$132) -> 0 | J3: =SUMIF('OI 2020'!$I$144:$I$165,C3,'OI 2020'!$K$144:$K$165) -> 0 | K3: =SUMIF('OI 2021'!$I$145:$I$166,C3,'OI 2021'!$K$145:$K$166) -> 0 | L3: =SUMIF('OI 2022'!$I$158:$I$175,$C3,'OI 2022'!$K$158:$K$175) -> 0 | M3: =SUMIF('OI 2023'!$I$158:$I$173,$C3,'OI 2023'!$J$158:$J$173) -> 0 | Q3: >2MW | R3: ='OI 2012'!M78+'OI 2012'!T78 -> 163 | S3: ='OI 2013'!M78+'OI 2013'!T78 -> 229.91111 | T3: ='OI 2014'!M78+'OI 2014'!T78 -> 364.70588 | U3: ='OI 2015'!M78+'OI 2015'!T78 -> 70 | V3: ='OI 2016'!M78+'OI 2016'!T78 -> 15 | W3: 0 | X3: 0 | Y3: 0 | Z3: 0 | AA3: 0 | AB3: 0 | AC3: 0 | AE3: AOM4000 | AF3: ='OI 2014'!E81 -> 1234 | AG3: ='OI 2015'!E81 -> 2363 | AH3: ='OI 2016'!E81 -> 1849 | AI3: ='OI 2017'!E106 -> 1785 | AJ3: ='OI 2018'!E106 -> 1202.8 | AK3: ='OI 2019'!E107 -> 2214 | AL3: ='OI 2020'!E138 -> 2087
C4: 3MW | D4: =SUMIF('OI 2014'!$I$87:$I$101,C4,'OI 2014'!$L$87:$L$101) -> 0 | E4: =SUMIF('OI 2015'!$I$87:$I$101,C4,'OI 2015'!$L$87:$L$101) -> 0 | F4: =SUMIF('OI 2016'!$I$87:$I$101,C4,'OI 2016'!$L$87:$L$101) -> 26 | G4: =SUMIF('OI 2017'!$I$112:$I$128,C4,'OI 2017'!$L$112:$L$128) -> 0 | H4: =SUMIF('OI 2018'!$I$112:$I$131,C4,'OI 2018'!$L$112:$L$131) -> 0 | I4: =SUMIF('OI 2019'!$I$113:$I$132,C4,'OI 2019'!$L$113:$L$132) -> 0 | J4: =SUMIF('OI 2020'!$I$144:$I$165,C4,'OI 2020'!$K$144:$K$165) -> 0 | K4: =SUMIF('OI 2021'!$I$145:$I$166,C4,'OI 2021'!$K$145:$K$166) -> 0 | L4: =SUMIF('OI 2022'!$I$158:$I$175,$C4,'OI 2022'!$K$158:$K$175) -> 0 | M4: =SUMIF('OI 2023'!$I$158:$I$173,$C4,'OI 2023'!$J$158:$J$173) -> 0 | Q4: 2-2.99MW | R4: ='OI 2012'!M79+'OI 2012'!T79 -> 237 | S4: ='OI 2013'!M79+'OI 2013'!T79 -> 1123.7 | T4: ='OI 2014'!M79+'OI 2014'!T79 -> 1080 | U4: ='OI 2015'!M79+'OI 2015'!T79 -> 1470 | V4: ='OI 2016'!M79+'OI 2016'!T79 -> 1642.9636 | W4: ='OI 2017'!M103+'OI 2017'!T103 -> 1729.8636 | X4: ='OI 2018'!M103+'OI 2018'!T103 -> 1460 | Y4: ='OI 2019'!N104+'OI 2019'!V104 -> 1590.8182 | Z4: ='OI 2020'!M135 -> 723 | AA4: ='OI 2021'!N137 -> 1008 | AB4: ='OI 2022'!N149 -> 224 | AC4: ='OI 2023'!N149 -> 806 | AE4: AOM5000 | AF4: ='OI 2014'!E80 -> 2559 | AG4: ='OI 2015'!E80 -> 3421 | AH4: ='OI 2016'!E80 -> 3190 | AI4: ='OI 2017'!E105 -> 4551 | AJ4: ='OI 2018'!E105 -> 7360.4 | AK4: ='OI 2019'!E106 -> 6601 | AL4: ='OI 2020'!E137 -> 9504
C5: 4MW | D5: =SUMIF('OI 2014'!$I$87:$I$101,C5,'OI 2014'!$L$87:$L$101) -> 0 | E5: =SUMIF('OI 2015'!$I$87:$I$101,C5,'OI 2015'!$L$87:$L$101) -> 0 | F5: =SUMIF('OI 2016'!$I$87:$I$101,C5,'OI 2016'!$L$87:$L$101) -> 0 | G5: =SUMIF('OI 2017'!$I$112:$I$128,C5,'OI 2017'!$L$112:$L$128) -> 79.5 | H5: =SUMIF('OI 2018'!$I$112:$I$131,C5,'OI 2018'!$L$112:$L$131) -> 20.25 | I5: =SUMIF('OI 2019'!$I$113:$I$132,C5,'OI 2019'!$L$113:$L$132) -> 0 | J5: =SUMIF('OI 2020'!$I$144:$I$165,C5,'OI 2020'!$K$144:$K$165) -> 0 | K5: =SUMIF('OI 2021'!$I$145:$I$166,C5,'OI 2021'!$K$145:$K$166) -> 12 | L5: =SUMIF('OI 2022'!$I$158:$I$175,$C5,'OI 2022'!$K$158:$K$175) -> 0 | M5: =SUMIF('OI 2023'!$I$158:$I$173,$C5,'OI 2023'!$J$158:$J$173) -> 0 | Q5: 3-3.99MW | R5: ='OI 2012'!M80+'OI 2012'!T80 -> 323 | S5: ='OI 2013'!M80+'OI 2013'!T80 -> 511.89091 | T5: ='OI 2014'!M80+'OI 2014'!T80 -> 481.48485 | U5: ='OI 2015'!M80+'OI 2015'!T80 -> 1081.9379 | V5: ='OI 2016'!M80+'OI 2016'!T80 -> 1136.6096 | W5: ='OI 2017'!M104+'OI 2017'!T104 -> 1261.2067 | X5: ='OI 2018'!M104+'OI 2018'!T104 -> 1311.9335 | Y5: ='OI 2019'!N105+'OI 2019'!V105 -> 429.33816 | Z5: ='OI 2020'!N136 -> 2485 | AA5: ='OI 2021'!N138 -> 811 | AB5: ='OI 2022'!N150 -> 123 | AC5: ='OI 2023'!N150 -> 130
C6: V52-850kW | D6: =SUMIF('OI 2014'!$I$87:$I$101,C6,'OI 2014'!$L$87:$L$101) -> 364.70588 | E6: =SUMIF('OI 2015'!$I$87:$I$101,C6,'OI 2015'!$L$87:$L$101) -> 0 | F6: =SUMIF('OI 2016'!$I$87:$I$101,C6,'OI 2016'!$L$87:$L$101) -> 0 | G6: =SUMIF('OI 2017'!$I$112:$I$128,C6,'OI 2017'!$L$112:$L$128) -> 0 | H6: =SUMIF('OI 2018'!$I$112:$I$131,C6,'OI 2018'!$L$112:$L$131) -> 0 | I6: =SUMIF('OI 2019'!$I$113:$I$132,C6,'OI 2019'!$L$113:$L$132) -> 0 | J6: =SUMIF('OI 2020'!$I$144:$I$165,C6,'OI 2020'!$K$144:$K$165) -> 0 | K6: =SUMIF('OI 2021'!$I$145:$I$166,C6,'OI 2021'!$K$145:$K$166) -> 0 | L6: =SUMIF('OI 2022'!$I$158:$I$175,$C6,'OI 2022'!$K$158:$K$175) -> 0 | M6: =SUMIF('OI 2023'!$I$158:$I$173,$C6,'OI 2023'!$J$158:$J$173) -> 0 | Q6: 4-5.99MW | R6: 0 | S6: 0 | T6: ='OI 2014'!M81+'OI 2014'!T81 -> 0 | U6: ='OI 2015'!M81+'OI 2015'!T81 -> 0 | V6: ='OI 2016'!M81+'OI 2016'!T81 -> 0 | W6: ='OI 2017'!M105+'OI 2017'!T105 -> 164.5 | X6: ='OI 2018'!M105+'OI 2018'!T105 -> 725.05952 | Y6: ='OI 2019'!N106+'OI 2019'!V106 -> 1435.7674 | Z6: ='OI 2020'!N137 -> 7134 | AA6: ='OI 2021'!N139 -> 4446 | AB6: ='OI 2022'!N151 -> 4962 | AC6: ='OI 2023'!N151 -> 9281
C7: V80-2.0MW | D7: =SUMIF('OI 2014'!$I$87:$I$101,C7,'OI 2014'!$L$87:$L$101) -> 34 | E7: =SUMIF('OI 2015'!$I$87:$I$101,C7,'OI 2015'!$L$87:$L$101) -> 0 | F7: =SUMIF('OI 2016'!$I$87:$I$101,C7,'OI 2016'!$L$87:$L$101) -> 0 | G7: =SUMIF('OI 2017'!$I$112:$I$128,C7,'OI 2017'!$L$112:$L$128) -> 0 | H7: =SUMIF('OI 2018'!$I$112:$I$131,C7,'OI 2018'!$L$112:$L$131) -> 0 | I7: =SUMIF('OI 2019'!$I$113:$I$132,C7,'OI 2019'!$L$113:$L$132) -> 0 | J7: =SUMIF('OI 2020'!$I$144:$I$165,C7,'OI 2020'!$K$144:$K$165) -> 0 | K7: =SUMIF('OI 2021'!$I$145:$I$166,C7,'OI 2021'!$K$145:$K$166) -> 0 | L7: =SUMIF('OI 2022'!$I$158:$I$175,$C7,'OI 2022'!$K$158:$K$175) -> 0 | M7: =SUMIF('OI 2023'!$I$158:$I$173,$C7,'OI 2023'!$J$158:$J$173) -> 0 | Q7: 6-7MW | Z7: ='OI 2020'!N138 -> 1313 | AA7: ='OI 2021'!N140 -> 3284 | AB7: ='OI 2022'!N152 -> 2588 | AC7: ='OI 2023'!N152 -> 1937 | AG7: MW of each service
C8: V90-2.0MW | D8: =SUMIF('OI 2014'!$I$87:$I$101,C8,'OI 2014'!$L$87:$L$101) -> 21 | E8: =SUMIF('OI 2015'!$I$87:$I$101,C8,'OI 2015'!$L$87:$L$101) -> 49 | F8: =SUMIF('OI 2016'!$I$87:$I$101,C8,'OI 2016'!$L$87:$L$101) -> 0 | G8: =SUMIF('OI 2017'!$I$112:$I$128,C8,'OI 2017'!$L$112:$L$128) -> 0 | H8: =SUMIF('OI 2018'!$I$112:$I$131,C8,'OI 2018'!$L$112:$L$131) -> 0 | I8: =SUMIF('OI 2019'!$I$113:$I$132,C8,'OI 2019'!$L$113:$L$132) -> 0 | J8: =SUMIF('OI 2020'!$I$144:$I$165,C8,'OI 2020'!$K$144:$K$165) -> 1 | K8: =SUMIF('OI 2021'!$I$145:$I$166,C8,'OI 2021'!$K$145:$K$166) -> 2 | L8: =SUMIF('OI 2022'!$I$158:$I$175,$C8,'OI 2022'!$K$158:$K$175) -> 0 | M8: =SUMIF('OI 2023'!$I$158:$I$173,$C8,'OI 2023'!$J$158:$J$173) -> 0 | Q8: 7+ | AA8: ='OI 2021'!N141 -> 733 | AB8: ='OI 2022'!N153 -> 650 | AC8: ='OI 2023'!N153 -> 3168 | AF8: 2014 | AG8: 2015 | AH8: 2016 | AI8: 2017 | AJ8: 2018 | AK8: 2019 | AL8: 2020
C9: V90-3.0MW | D9: =SUMIF('OI 2014'!$I$87:$I$101,C9,'OI 2014'!$L$87:$L$101) -> 61 | E9: =SUMIF('OI 2015'!$I$87:$I$101,C9,'OI 2015'!$L$87:$L$101) -> 29 | F9: =SUMIF('OI 2016'!$I$87:$I$101,C9,'OI 2016'!$L$87:$L$101) -> 40 | G9: =SUMIF('OI 2017'!$I$112:$I$128,C9,'OI 2017'!$L$112:$L$128) -> 0 | H9: =SUMIF('OI 2018'!$I$112:$I$131,C9,'OI 2018'!$L$112:$L$131) -> 0 | I9: =SUMIF('OI 2019'!$I$113:$I$132,C9,'OI 2019'!$L$113:$L$132) -> 0 | J9: =SUMIF('OI 2020'!$I$144:$I$165,C9,'OI 2020'!$K$144:$K$165) -> 0 | K9: =SUMIF('OI 2021'!$I$145:$I$166,C9,'OI 2021'!$K$145:$K$166) -> 0 | L9: =SUMIF('OI 2022'!$I$158:$I$175,$C9,'OI 2022'!$K$158:$K$175) -> 0 | M9: =SUMIF('OI 2023'!$I$158:$I$173,$C9,'OI 2023'!$J$158:$J$173) -> 0 | AE9: AOM2000 | AI9: 1.3 | AJ9: 0.7
C10: V100-1.8MW | D10: =SUMIF('OI 2014'!$I$87:$I$101,C10,'OI 2014'!$L$87:$L$101) -> 0 | E10: =SUMIF('OI 2015'!$I$87:$I$101,C10,'OI 2015'!$L$87:$L$101) -> 70 | F10: =SUMIF('OI 2016'!$I$87:$I$101,C10,'OI 2016'!$L$87:$L$101) -> 15 | G10: =SUMIF('OI 2017'!$I$112:$I$128,C10,'OI 2017'!$L$112:$L$128) -> 0 | H10: =SUMIF('OI 2018'!$I$112:$I$131,C10,'OI 2018'!$L$112:$L$131) -> 0 | I10: =SUMIF('OI 2019'!$I$113:$I$132,C10,'OI 2019'!$L$113:$L$132) -> 0 | J10: =SUMIF('OI 2020'!$I$144:$I$165,C10,'OI 2020'!$K$144:$K$165) -> 0 | K10: =SUMIF('OI 2021'!$I$145:$I$166,C10,'OI 2021'!$K$145:$K$166) -> 0 | L10: =SUMIF('OI 2022'!$I$158:$I$175,$C10,'OI 2022'!$K$158:$K$175) -> 0 | M10: =SUMIF('OI 2023'!$I$158:$I$173,$C10,'OI 2023'!$J$158:$J$173) -> 0 | Q10: sum #WTG | R10: =SUM(R3:R7) -> 723 | S10: =SUM(S3:S7) -> 1865.502 | T10: =SUM(T3:T7) -> 1926.1907 | U10: =SUM(U3:U7) -> 2621.9379 | V10: =SUM(V3:V7) -> 2794.5732 | W10: =SUM(W3:W7) -> 3155.5704 | X10: =SUM(X3:X7) -> 3496.993 | Y10: =SUM(Y3:Y7) -> 3455.9238 | AE10: AOM3000 | AI10: 3.4 | AJ10: 6.9
C11: V100-2.0MW | D11: =SUMIF('OI 2014'!$I$87:$I$101,C11,'OI 2014'!$L$87:$L$101) -> 659 | E11: =SUMIF('OI 2015'!$I$87:$I$101,C11,'OI 2015'!$L$87:$L$101) -> 486 | F11: =SUMIF('OI 2016'!$I$87:$I$101,C11,'OI 2016'!$L$87:$L$101) -> 104 | G11: =SUMIF('OI 2017'!$I$112:$I$128,C11,'OI 2017'!$L$112:$L$128) -> 72 | H11: =SUMIF('OI 2018'!$I$112:$I$131,C11,'OI 2018'!$L$112:$L$131) -> 141 | I11: =SUMIF('OI 2019'!$I$113:$I$132,C11,'OI 2019'!$L$113:$L$132) -> 0 | J11: =SUMIF('OI 2020'!$I$144:$I$165,C11,'OI 2020'!$K$144:$K$165) -> 124 | K11: =SUMIF('OI 2021'!$I$145:$I$166,C11,'OI 2021'!$K$145:$K$166) -> 86 | L11: =SUMIF('OI 2022'!$I$158:$I$175,$C11,'OI 2022'!$K$158:$K$175) -> 2 | M11: =SUMIF('OI 2023'!$I$158:$I$173,$C11,'OI 2023'!$J$158:$J$173) -> 40 | Q11: sum MW | R11: ='OI 2012'!E78 -> 2281.8 | S11: ='OI 2013'!E78 -> 4325 | T11: ='OI 2014'!E78 -> 4112 | U11: ='OI 2015'!E78 -> 6753 | V11: ='OI 2016'!E78 -> 7585 | W11: ='OI 2017'!E103 -> 13165 | X11: ='OI 2018'!E103 -> 15473.2 | Y11: ='OI 2019'!E104 -> 17862 | AE11: AOM4000 | AF11: =AF3/(AF3+AF4) -> 0.32533615 | AG11: =AG3/(AG3+AG4) -> 0.4085408 | AH11: =AH3/(AH3+AH4) -> 0.36693788 | AI11: 0.337 | AJ11: 0.328
C12: V105-3.45MW | D12: =SUMIF('OI 2014'!$I$87:$I$101,C12,'OI 2014'!$L$87:$L$101) -> 0 | E12: =SUMIF('OI 2015'!$I$87:$I$101,C12,'OI 2015'!$L$87:$L$101) -> 0 | F12: =SUMIF('OI 2016'!$I$87:$I$101,C12,'OI 2016'!$L$87:$L$101) -> 8.9855072 | G12: =SUMIF('OI 2017'!$I$112:$I$128,C12,'OI 2017'!$L$112:$L$128) -> 31.714976 | H12: =SUMIF('OI 2018'!$I$112:$I$131,C12,'OI 2018'!$L$112:$L$131) -> 0 | I12: =SUMIF('OI 2019'!$I$113:$I$132,C12,'OI 2019'!$L$113:$L$132) -> 17 | J12: =SUMIF('OI 2020'!$I$144:$I$165,C12,'OI 2020'!$K$144:$K$165) -> 127 | K12: =SUMIF('OI 2021'!$I$145:$I$166,C12,'OI 2021'!$K$145:$K$166) -> 25 | L12: =SUMIF('OI 2022'!$I$158:$I$175,$C12,'OI 2022'!$K$158:$K$175) -> 8 | M12: =SUMIF('OI 2023'!$I$158:$I$173,$C12,'OI 2023'!$J$158:$J$173) -> 0 | AE12: AOM5000 | AF12: =AF4/(AF4+AF3) -> 0.67466385 | AG12: =AG4/(AG4+AG3) -> 0.5914592 | AH12: =AH4/(AH4+AH3) -> 0.63306212 | AI12: 0.616 | AJ12: 0.616
C13: V105-3.6MW | D13: =SUMIF('OI 2014'!$I$87:$I$101,C13,'OI 2014'!$L$87:$L$101) -> 0 | E13: =SUMIF('OI 2015'!$I$87:$I$101,C13,'OI 2015'!$L$87:$L$101) -> 0 | F13: =SUMIF('OI 2016'!$I$87:$I$101,C13,'OI 2016'!$L$87:$L$101) -> 0 | G13: =SUMIF('OI 2017'!$I$112:$I$128,C13,'OI 2017'!$L$112:$L$128) -> 0 | H13: =SUMIF('OI 2018'!$I$112:$I$131,C13,'OI 2018'!$L$112:$L$131) -> 0 | I13: =SUMIF('OI 2019'!$I$113:$I$132,C13,'OI 2019'!$L$113:$L$132) -> 0 | J13: =SUMIF('OI 2020'!$I$144:$I$165,C13,'OI 2020'!$K$144:$K$165) -> 11 | K13: =SUMIF('OI 2021'!$I$145:$I$166,C13,'OI 2021'!$K$145:$K$166) -> 0 | L13: =SUMIF('OI 2022'!$I$158:$I$175,$C13,'OI 2022'!$K$158:$K$175) -> 0 | M13: =SUMIF('OI 2023'!$I$158:$I$173,$C13,'OI 2023'!$J$158:$J$173) -> 0
C14: V110-2.0MW | D14: =SUMIF('OI 2014'!$I$87:$I$101,C14,'OI 2014'!$L$87:$L$101) -> 336 | E14: =SUMIF('OI 2015'!$I$87:$I$101,C14,'OI 2015'!$L$87:$L$101) -> 860 | F14: =SUMIF('OI 2016'!$I$87:$I$101,C14,'OI 2016'!$L$87:$L$101) -> 1354.3636 | G14: =SUMIF('OI 2017'!$I$112:$I$128,C14,'OI 2017'!$L$112:$L$128) -> 1409.5 | H14: =SUMIF('OI 2018'!$I$112:$I$131,C14,'OI 2018'!$L$112:$L$131) -> 360.09091 | I14: =SUMIF('OI 2019'!$I$113:$I$132,C14,'OI 2019'!$L$113:$L$132) -> 255 | J14: =SUMIF('OI 2020'!$I$144:$I$165,C14,'OI 2020'!$K$144:$K$165) -> 215 | K14: =SUMIF('OI 2021'!$I$145:$I$166,C14,'OI 2021'!$K$145:$K$166) -> 59 | L14: =SUMIF('OI 2022'!$I$158:$I$175,$C14,'OI 2022'!$K$158:$K$175) -> 0 | M14: =SUMIF('OI 2023'!$I$158:$I$173,$C14,'OI 2023'!$J$158:$J$173) -> 259
C15: V110-2.2MW | D15: =SUMIF('OI 2014'!$I$87:$I$101,C15,'OI 2014'!$L$87:$L$101) -> 0 | E15: =SUMIF('OI 2015'!$I$87:$I$101,C15,'OI 2015'!$L$87:$L$101) -> 0 | F15: =SUMIF('OI 2016'!$I$87:$I$101,C15,'OI 2016'!$L$87:$L$101) -> 0 | G15: =SUMIF('OI 2017'!$I$112:$I$128,C15,'OI 2017'!$L$112:$L$128) -> 40.363636 | H15: =SUMIF('OI 2018'!$I$112:$I$131,C15,'OI 2018'!$L$112:$L$131) -> 183.18182 | I15: =SUMIF('OI 2019'!$I$113:$I$132,C15,'OI 2019'!$L$113:$L$132) -> 66 | J15: =SUMIF('OI 2020'!$I$144:$I$165,C15,'OI 2020'!$K$144:$K$165) -> 63 | K15: =SUMIF('OI 2021'!$I$145:$I$166,C15,'OI 2021'!$K$145:$K$166) -> 60.090909 | L15: =SUMIF('OI 2022'!$I$158:$I$175,$C15,'OI 2022'!$K$158:$K$175) -> 66 | M15: =SUMIF('OI 2023'!$I$158:$I$173,$C15,'OI 2023'!$J$158:$J$173) -> 0
C16: V112-3.075MW | D16: =SUMIF('OI 2014'!$I$87:$I$101,C16,'OI 2014'!$L$87:$L$101) -> 0 | E16: =SUMIF('OI 2015'!$I$87:$I$101,C16,'OI 2015'!$L$87:$L$101) -> 13.00813 | F16: =SUMIF('OI 2016'!$I$87:$I$101,C16,'OI 2016'!$L$87:$L$101) -> 0 | G16: =SUMIF('OI 2017'!$I$112:$I$128,C16,'OI 2017'!$L$112:$L$128) -> 0 | H16: =SUMIF('OI 2018'!$I$112:$I$131,C16,'OI 2018'!$L$112:$L$131) -> 0 | I16: =SUMIF('OI 2019'!$I$113:$I$132,C16,'OI 2019'!$L$113:$L$132) -> 0 | J16: =SUMIF('OI 2020'!$I$144:$I$165,C16,'OI 2020'!$K$144:$K$165) -> 0 | K16: =SUMIF('OI 2021'!$I$145:$I$166,C16,'OI 2021'!$K$145:$K$166) -> 0 | L16: =SUMIF('OI 2022'!$I$158:$I$175,$C16,'OI 2022'!$K$158:$K$175) -> 0 | M16: =SUMIF('OI 2023'!$I$158:$I$173,$C16,'OI 2023'!$J$158:$J$173) -> 0
C17: V112-3.0MW | D17: =SUMIF('OI 2014'!$I$87:$I$101,C17,'OI 2014'!$L$87:$L$101) -> 97.333333 | E17: =SUMIF('OI 2015'!$I$87:$I$101,C17,'OI 2015'!$L$87:$L$101) -> 12 | F17: =SUMIF('OI 2016'!$I$87:$I$101,C17,'OI 2016'!$L$87:$L$101) -> 0 | G17: =SUMIF('OI 2017'!$I$112:$I$128,C17,'OI 2017'!$L$112:$L$128) -> 0 | H17: =SUMIF('OI 2018'!$I$112:$I$131,C17,'OI 2018'!$L$112:$L$131) -> 19 | I17: =SUMIF('OI 2019'!$I$113:$I$132,C17,'OI 2019'!$L$113:$L$132) -> 0 | J17: =SUMIF('OI 2020'!$I$144:$I$165,C17,'OI 2020'!$K$144:$K$165) -> 0 | K17: =SUMIF('OI 2021'!$I$145:$I$166,C17,'OI 2021'!$K$145:$K$166) -> 0 | L17: =SUMIF('OI 2022'!$I$158:$I$175,$C17,'OI 2022'!$K$158:$K$175) -> 0 | M17: =SUMIF('OI 2023'!$I$158:$I$173,$C17,'OI 2023'!$J$158:$J$173) -> 0
C18: V112-3.3MW | D18: =SUMIF('OI 2014'!$I$87:$I$101,C18,'OI 2014'!$L$87:$L$101) -> 200.06061 | E18: =SUMIF('OI 2015'!$I$87:$I$101,C18,'OI 2015'!$L$87:$L$101) -> 212.12121 | F18: =SUMIF('OI 2016'!$I$87:$I$101,C18,'OI 2016'!$L$87:$L$101) -> 34.848485 | G18: =SUMIF('OI 2017'!$I$112:$I$128,C18,'OI 2017'!$L$112:$L$128) -> 26.060606 | H18: =SUMIF('OI 2018'!$I$112:$I$131,C18,'OI 2018'!$L$112:$L$131) -> 0 | I18: =SUMIF('OI 2019'!$I$113:$I$132,C18,'OI 2019'!$L$113:$L$132) -> 9 | J18: =SUMIF('OI 2020'!$I$144:$I$165,C18,'OI 2020'!$K$144:$K$165) -> 0 | K18: =SUMIF('OI 2021'!$I$145:$I$166,C18,'OI 2021'!$K$145:$K$166) -> 0 | L18: =SUMIF('OI 2022'!$I$158:$I$175,$C18,'OI 2022'!$K$158:$K$175) -> 0 | M18: =SUMIF('OI 2023'!$I$158:$I$173,$C18,'OI 2023'!$J$158:$J$173) -> 0
C19: V112-3.45MW | D19: =SUMIF('OI 2014'!$I$87:$I$101,C19,'OI 2014'!$L$87:$L$101) -> 0 | E19: =SUMIF('OI 2015'!$I$87:$I$101,C19,'OI 2015'!$L$87:$L$101) -> 140.69652 | F19: =SUMIF('OI 2016'!$I$87:$I$101,C19,'OI 2016'!$L$87:$L$101) -> 164.15942 | G19: =SUMIF('OI 2017'!$I$112:$I$128,C19,'OI 2017'!$L$112:$L$128) -> 40.125604 | H19: =SUMIF('OI 2018'!$I$112:$I$131,C19,'OI 2018'!$L$112:$L$131) -> 22.951252 | I19: =SUMIF('OI 2019'!$I$113:$I$132,C19,'OI 2019'!$L$113:$L$132) -> 72 | J19: =SUMIF('OI 2020'!$I$144:$I$165,C19,'OI 2020'!$K$144:$K$165) -> 34 | K19: =SUMIF('OI 2021'!$I$145:$I$166,C19,'OI 2021'!$K$145:$K$166) -> 10 | L19: =SUMIF('OI 2022'!$I$158:$I$175,$C19,'OI 2022'!$K$158:$K$175) -> 2 | M19: =SUMIF('OI 2023'!$I$158:$I$173,$C19,'OI 2023'!$J$158:$J$173) -> 0
C20: V116-2.0MW | D20: =SUMIF('OI 2014'!$I$87:$I$101,C20,'OI 2014'!$L$87:$L$101) -> 0 | E20: =SUMIF('OI 2015'!$I$87:$I$101,C20,'OI 2015'!$L$87:$L$101) -> 0 | F20: =SUMIF('OI 2016'!$I$87:$I$101,C20,'OI 2016'!$L$87:$L$101) -> 0 | G20: =SUMIF('OI 2017'!$I$112:$I$128,C20,'OI 2017'!$L$112:$L$128) -> 33 | H20: =SUMIF('OI 2018'!$I$112:$I$131,C20,'OI 2018'!$L$112:$L$131) -> 216 | I20: =SUMIF('OI 2019'!$I$113:$I$132,C20,'OI 2019'!$L$113:$L$132) -> 0 | J20: =SUMIF('OI 2020'!$I$144:$I$165,C20,'OI 2020'!$K$144:$K$165) -> 0 | K20: =SUMIF('OI 2021'!$I$145:$I$166,C20,'OI 2021'!$K$145:$K$166) -> 0 | L20: =SUMIF('OI 2022'!$I$158:$I$175,$C20,'OI 2022'!$K$158:$K$175) -> 0 | M20: =SUMIF('OI 2023'!$I$158:$I$173,$C20,'OI 2023'!$J$158:$J$173) -> 0
C21: V117-3.0MW | D21: =SUMIF('OI 2014'!$I$87:$I$101,C21,'OI 2014'!$L$87:$L$101) -> 6 | E21: =SUMIF('OI 2015'!$I$87:$I$101,C21,'OI 2015'!$L$87:$L$101) -> 0 | F21: =SUMIF('OI 2016'!$I$87:$I$101,C21,'OI 2016'!$L$87:$L$101) -> 0 | G21: =SUMIF('OI 2017'!$I$112:$I$128,C21,'OI 2017'!$L$112:$L$128) -> 0 | H21: =SUMIF('OI 2018'!$I$112:$I$131,C21,'OI 2018'!$L$112:$L$131) -> 0 | I21: =SUMIF('OI 2019'!$I$113:$I$132,C21,'OI 2019'!$L$113:$L$132) -> 0 | J21: =SUMIF('OI 2020'!$I$144:$I$165,C21,'OI 2020'!$K$144:$K$165) -> 0 | K21: =SUMIF('OI 2021'!$I$145:$I$166,C21,'OI 2021'!$K$145:$K$166) -> 0 | L21: =SUMIF('OI 2022'!$I$158:$I$175,$C21,'OI 2022'!$K$158:$K$175) -> 0 | M21: =SUMIF('OI 2023'!$I$158:$I$173,$C21,'OI 2023'!$J$158:$J$173) -> 0
C22: V117-3.3MW | D22: =SUMIF('OI 2014'!$I$87:$I$101,C22,'OI 2014'!$L$87:$L$101) -> 19 | E22: =SUMIF('OI 2015'!$I$87:$I$101,C22,'OI 2015'!$L$87:$L$101) -> 365.45455 | F22: =SUMIF('OI 2016'!$I$87:$I$101,C22,'OI 2016'!$L$87:$L$101) -> 53.939394 | G22: =SUMIF('OI 2017'!$I$112:$I$128,C22,'OI 2017'!$L$112:$L$128) -> 0 | H22: =SUMIF('OI 2018'!$I$112:$I$131,C22,'OI 2018'!$L$112:$L$131) -> 10 | I22: =SUMIF('OI 2019'!$I$113:$I$132,C22,'OI 2019'!$L$113:$L$132) -> 0 | J22: =SUMIF('OI 2020'!$I$144:$I$165,C22,'OI 2020'!$K$144:$K$165) -> 0 | K22: =SUMIF('OI 2021'!$I$145:$I$166,C22,'OI 2021'!$K$145:$K$166) -> 0 | L22: =SUMIF('OI 2022'!$I$158:$I$175,$C22,'OI 2022'!$K$158:$K$175) -> 0 | M22: =SUMIF('OI 2023'!$I$158:$I$173,$C22,'OI 2023'!$J$158:$J$173) -> 0
C23: V117-3.45MW | D23: =SUMIF('OI 2014'!$I$87:$I$101,C23,'OI 2014'!$L$87:$L$101) -> 0 | E23: =SUMIF('OI 2015'!$I$87:$I$101,C23,'OI 2015'!$L$87:$L$101) -> 30 | F23: =SUMIF('OI 2016'!$I$87:$I$101,C23,'OI 2016'!$L$87:$L$101) -> 398.97101 | G23: =SUMIF('OI 2017'!$I$112:$I$128,C23,'OI 2017'!$L$112:$L$128) -> 66.932367 | H23: =SUMIF('OI 2018'!$I$112:$I$131,C23,'OI 2018'!$L$112:$L$131) -> 178.15217 | I23: =SUMIF('OI 2019'!$I$113:$I$132,C23,'OI 2019'!$L$113:$L$132) -> 46 | J23: =SUMIF('OI 2020'!$I$144:$I$165,C23,'OI 2020'!$K$144:$K$165) -> 33 | K23: =SUMIF('OI 2021'!$I$145:$I$166,C23,'OI 2021'!$K$145:$K$166) -> 23 | L23: =SUMIF('OI 2022'!$I$158:$I$175,$C23,'OI 2022'!$K$158:$K$175) -> 13 | M23: =SUMIF('OI 2023'!$I$158:$I$173,$C23,'OI 2023'!$J$158:$J$173) -> 0
C24: V117-4.2MW | D24: =SUMIF('OI 2014'!$I$87:$I$101,C24,'OI 2014'!$L$87:$L$101) -> 0 | E24: =SUMIF('OI 2015'!$I$87:$I$101,C24,'OI 2015'!$L$87:$L$101) -> 0 | F24: =SUMIF('OI 2016'!$I$87:$I$101,C24,'OI 2016'!$L$87:$L$101) -> 0 | G24: =SUMIF('OI 2017'!$I$112:$I$128,C24,'OI 2017'!$L$112:$L$128) -> 0 | H24: =SUMIF('OI 2018'!$I$112:$I$131,C24,'OI 2018'!$L$112:$L$131) -> 31 | I24: =SUMIF('OI 2019'!$I$113:$I$132,C24,'OI 2019'!$L$113:$L$132) -> 107 | J24: =SUMIF('OI 2020'!$I$144:$I$165,C24,'OI 2020'!$K$144:$K$165) -> 166 | K24: =SUMIF('OI 2021'!$I$145:$I$166,C24,'OI 2021'!$K$145:$K$166) -> 97 | L24: =SUMIF('OI 2022'!$I$158:$I$175,$C24,'OI 2022'!$K$158:$K$175) -> 36 | M24: =SUMIF('OI 2023'!$I$158:$I$173,$C24,'OI 2023'!$J$158:$J$173) -> 44
... C31: V136-3.0MW | D31: =SUMIF('OI 2014'!$I$87:$I$101,C31,'OI 2014'!$L$87:$L$101) -> 0 | E31: =SUMIF('OI 2015'!$I$87:$I$101,C31,'OI 2015'!$L$87:$L$101) -> 0 | F31: =SUMIF('OI 2016'!$I$87:$I$101,C31,'OI 2016'!$L$87:$L$101) -> 0 | G31: =SUMIF('OI 2017'!$I$112:$I$128,C31,'OI 2017'!$L$112:$L$128) -> 60 | H31: =SUMIF('OI 2018'!$I$112:$I$131,C31,'OI 2018'!$L$112:$L$131) -> 0 | I31: =SUMIF('OI 2019'!$I$113:$I$132,C31,'OI 2019'!$L$113:$L$132) -> 0 | J31: =SUMIF('OI 2020'!$I$144:$I$165,C31,'OI 2020'!$K$144:$K$165) -> 0 | K31: =SUMIF('OI 2021'!$I$145:$I$166,C31,'OI 2021'!$K$145:$K$166) -> 0 | L31: =SUMIF('OI 2022'!$I$158:$I$175,$C31,'OI 2022'!$K$158:$K$175) -> 0 | M31: =SUMIF('OI 2023'!$I$158:$I$173,$C31,'OI 2023'!$J$158:$J$173) -> 0
C32: V136-3.45MW | D32: =SUMIF('OI 2014'!$I$87:$I$101,C32,'OI 2014'!$L$87:$L$101) -> 0 | E32: =SUMIF('OI 2015'!$I$87:$I$101,C32,'OI 2015'!$L$87:$L$101) -> 33.913043 | F32: =SUMIF('OI 2016'!$I$87:$I$101,C32,'OI 2016'!$L$87:$L$101) -> 0 | G32: =SUMIF('OI 2017'!$I$112:$I$128,C32,'OI 2017'!$L$112:$L$128) -> 634.8341 | H32: =SUMIF('OI 2018'!$I$112:$I$131,C32,'OI 2018'!$L$112:$L$131) -> 717.7179 | I32: =SUMIF('OI 2019'!$I$113:$I$132,C32,'OI 2019'!$L$113:$L$132) -> 114.88889 | J32: =SUMIF('OI 2020'!$I$144:$I$165,C32,'OI 2020'!$K$144:$K$165) -> 274 | K32: =SUMIF('OI 2021'!$I$145:$I$166,C32,'OI 2021'!$K$145:$K$166) -> 79 | L32: =SUMIF('OI 2022'!$I$158:$I$175,$C32,'OI 2022'!$K$158:$K$175) -> 11 | M32: =SUMIF('OI 2023'!$I$158:$I$173,$C32,'OI 2023'!$J$158:$J$173) -> 0 | Q32: Average length | R32: 2014 | S32: 2015 | T32: 2016 | U32: 2017 | V32: 2018 | W32: 2019 | X32: 2020 | Y32: 2021 | Z32: 2022 | AA32: 2023
C33: V136-3.6MW | D33: =SUMIF('OI 2014'!$I$87:$I$101,C33,'OI 2014'!$L$87:$L$101) -> 0 | E33: =SUMIF('OI 2015'!$I$87:$I$101,C33,'OI 2015'!$L$87:$L$101) -> 0 | F33: =SUMIF('OI 2016'!$I$87:$I$101,C33,'OI 2016'!$L$87:$L$101) -> 0 | G33: =SUMIF('OI 2017'!$I$112:$I$128,C33,'OI 2017'!$L$112:$L$128) -> 44.166667 | H33: =SUMIF('OI 2018'!$I$112:$I$131,C33,'OI 2018'!$L$112:$L$131) -> 103 | I33: =SUMIF('OI 2019'!$I$113:$I$132,C33,'OI 2019'!$L$113:$L$132) -> 12 | J33: =SUMIF('OI 2020'!$I$144:$I$165,C33,'OI 2020'!$K$144:$K$165) -> 1 | K33: =SUMIF('OI 2021'!$I$145:$I$166,C33,'OI 2021'!$K$145:$K$166) -> 0 | L33: =SUMIF('OI 2022'!$I$158:$I$175,$C33,'OI 2022'!$K$158:$K$175) -> 0 | M33: =SUMIF('OI 2023'!$I$158:$I$173,$C33,'OI 2023'!$J$158:$J$173) -> 0 | Q33: AOM4000 | R33: ='OI 2014'!G81 -> 7.7647059 | S33: ='OI 2015'!G81 -> 7.7931034 | T33: ='OI 2016'!G81 -> 10.24 | U33: ='OI 2017'!G106 -> 11.375 | V33: ='OI 2018'!G106 -> 10.214286 | W33: ='OI 2019'!G107 -> 13.571429 | X33: ='OI 2020'!G138 -> 12.75 | Y33: ='OI 2021'!G140 -> 18.125 | Z33: ='OI 2022'!G152 -> 14.5
C34: V136-4.2MW | D34: =SUMIF('OI 2014'!$I$87:$I$101,C34,'OI 2014'!$L$87:$L$101) -> 0 | E34: =SUMIF('OI 2015'!$I$87:$I$101,C34,'OI 2015'!$L$87:$L$101) -> 0 | F34: =SUMIF('OI 2016'!$I$87:$I$101,C34,'OI 2016'!$L$87:$L$101) -> 0 | G34: =SUMIF('OI 2017'!$I$112:$I$128,C34,'OI 2017'!$L$112:$L$128) -> 85 | H34: =SUMIF('OI 2018'!$I$112:$I$131,C34,'OI 2018'!$L$112:$L$131) -> 406.80952 | I34: =SUMIF('OI 2019'!$I$113:$I$132,C34,'OI 2019'!$L$113:$L$132) -> 237.9103 | J34: =SUMIF('OI 2020'!$I$144:$I$165,C34,'OI 2020'!$K$144:$K$165) -> 221 | K34: =SUMIF('OI 2021'!$I$145:$I$166,C34,'OI 2021'!$K$145:$K$166) -> 79 | L34: =SUMIF('OI 2022'!$I$158:$I$175,$C34,'OI 2022'!$K$158:$K$175) -> 63 | M34: =SUMIF('OI 2023'!$I$158:$I$173,$C34,'OI 2023'!$J$158:$J$173) -> 30 | Q34: AOM5000 | R34: ='OI 2014'!G80 -> 8.875 | S34: ='OI 2015'!G80 -> 10.029412 | T34: ='OI 2016'!G80 -> 10.2 | U34: ='OI 2017'!G105 -> 13.916667 | V34: ='OI 2018'!G105 -> 15.196078 | W34: ='OI 2019'!G106 -> 18.914894 | X34: ='OI 2020'!G137 -> 18.109589 | Y34: ='OI 2021'!G139 -> 18.886792 | Z34: ='OI 2022'!G151 -> 21.591837
C35: V136-4.5MW | D35: =SUMIF('OI 2014'!$I$87:$I$101,C35,'OI 2014'!$L$87:$L$101) -> 0 | E35: =SUMIF('OI 2015'!$I$87:$I$101,C35,'OI 2015'!$L$87:$L$101) -> 0 | F35: =SUMIF('OI 2016'!$I$87:$I$101,C35,'OI 2016'!$L$87:$L$101) -> 0 | G35: =SUMIF('OI 2017'!$I$112:$I$128,C35,'OI 2017'!$L$112:$L$128) -> 0 | H35: =SUMIF('OI 2018'!$I$112:$I$131,C35,'OI 2018'!$L$112:$L$131) -> 0 | I35: =SUMIF('OI 2019'!$I$113:$I$132,C35,'OI 2019'!$L$113:$L$132) -> 0 | J35: =SUMIF('OI 2020'!$I$144:$I$165,C35,'OI 2020'!$K$144:$K$165) -> 0 | K35: =SUMIF('OI 2021'!$I$145:$I$166,C35,'OI 2021'!$K$145:$K$166) -> 0 | L35: =SUMIF('OI 2022'!$I$158:$I$175,$C35,'OI 2022'!$K$158:$K$175) -> 116 | M35: =SUMIF('OI 2023'!$I$158:$I$173,$C35,'OI 2023'!$J$158:$J$173) -> 136
C36: V150-4.2MW | D36: =SUMIF('OI 2014'!$I$87:$I$101,C36,'OI 2014'!$L$87:$L$101) -> 0 | E36: =SUMIF('OI 2015'!$I$87:$I$101,C36,'OI 2015'!$L$87:$L$101) -> 0 | F36: =SUMIF('OI 2016'!$I$87:$I$101,C36,'OI 2016'!$L$87:$L$101) -> 0 | G36: =SUMIF('OI 2017'!$I$112:$I$128,C36,'OI 2017'!$L$112:$L$128) -> 0 | H36: =SUMIF('OI 2018'!$I$112:$I$131,C36,'OI 2018'!$L$112:$L$131) -> 267 | I36: =SUMIF('OI 2019'!$I$113:$I$132,C36,'OI 2019'!$L$113:$L$132) -> 1056.8571 | J36: =SUMIF('OI 2020'!$I$144:$I$165,C36,'OI 2020'!$K$144:$K$165) -> 1025.9048 | K36: =SUMIF('OI 2021'!$I$145:$I$166,C36,'OI 2021'!$K$145:$K$166) -> 520 | L36: =SUMIF('OI 2022'!$I$158:$I$175,$C36,'OI 2022'!$K$158:$K$175) -> 139 | M36: =SUMIF('OI 2023'!$I$158:$I$173,$C36,'OI 2023'!$J$158:$J$173) -> 223
C37: V150-4.3MW | D37: =SUMIF('OI 2014'!$I$87:$I$101,C37,'OI 2014'!$L$87:$L$101) -> 0 | E37: =SUMIF('OI 2015'!$I$87:$I$101,C37,'OI 2015'!$L$87:$L$101) -> 0 | F37: =SUMIF('OI 2016'!$I$87:$I$101,C37,'OI 2016'!$L$87:$L$101) -> 0 | G37: =SUMIF('OI 2017'!$I$112:$I$128,C37,'OI 2017'!$L$112:$L$128) -> 0 | H37: =SUMIF('OI 2018'!$I$112:$I$131,C37,'OI 2018'!$L$112:$L$131) -> 0 | I37: =SUMIF('OI 2019'!$I$113:$I$132,C37,'OI 2019'!$L$113:$L$132) -> 0 | J37: =SUMIF('OI 2020'!$I$144:$I$165,C37,'OI 2020'!$K$144:$K$165) -> 29 | K37: =SUMIF('OI 2021'!$I$145:$I$166,C37,'OI 2021'!$K$145:$K$166) -> 0 | L37: =SUMIF('OI 2022'!$I$158:$I$175,$C37,'OI 2022'!$K$158:$K$175) -> 0 | M37: =SUMIF('OI 2023'!$I$158:$I$173,$C37,'OI 2023'!$J$158:$J$173) -> 0
C38: V150-4.5MW | D38: =SUMIF('OI 2014'!$I$87:$I$101,C38,'OI 2014'!$L$87:$L$101) -> 0 | E38: =SUMIF('OI 2015'!$I$87:$I$101,C38,'OI 2015'!$L$87:$L$101) -> 0 | F38: =SUMIF('OI 2016'!$I$87:$I$101,C38,'OI 2016'!$L$87:$L$101) -> 0 | G38: =SUMIF('OI 2017'!$I$112:$I$128,C38,'OI 2017'!$L$112:$L$128) -> 0 | H38: =SUMIF('OI 2018'!$I$112:$I$131,C38,'OI 2018'!$L$112:$L$131) -> 0 | I38: =SUMIF('OI 2019'!$I$113:$I$132,C38,'OI 2019'!$L$113:$L$132) -> 0 | J38: =SUMIF('OI 2020'!$I$144:$I$165,C38,'OI 2020'!$K$144:$K$165) -> 91 | K38: =SUMIF('OI 2021'!$I$145:$I$166,C38,'OI 2021'!$K$145:$K$166) -> 257 | L38: =SUMIF('OI 2022'!$I$158:$I$175,$C38,'OI 2022'!$K$158:$K$175) -> 742 | M38: =SUMIF('OI 2023'!$I$158:$I$173,$C38,'OI 2023'!$J$158:$J$173) -> 668
C39: V150-5.6MW | D39: =SUMIF('OI 2014'!$I$87:$I$101,C39,'OI 2014'!$L$87:$L$101) -> 0 | E39: =SUMIF('OI 2015'!$I$87:$I$101,C39,'OI 2015'!$L$87:$L$101) -> 0 | F39: =SUMIF('OI 2016'!$I$87:$I$101,C39,'OI 2016'!$L$87:$L$101) -> 0 | G39: =SUMIF('OI 2017'!$I$112:$I$128,C39,'OI 2017'!$L$112:$L$128) -> 0 | H39: =SUMIF('OI 2018'!$I$112:$I$131,C39,'OI 2018'!$L$112:$L$131) -> 0 | I39: =SUMIF('OI 2019'!$I$113:$I$132,C39,'OI 2019'!$L$113:$L$132) -> 50.964286 | J39: =SUMIF('OI 2020'!$I$144:$I$165,C39,'OI 2020'!$K$144:$K$165) -> 22 | K39: =SUMIF('OI 2021'!$I$145:$I$166,C39,'OI 2021'!$K$145:$K$166) -> 7 | L39: =SUMIF('OI 2022'!$I$158:$I$175,$C39,'OI 2022'!$K$158:$K$175) -> 0 | M39: =SUMIF('OI 2023'!$I$158:$I$173,$C39,'OI 2023'!$J$158:$J$173) -> 1
C40: V155-3.3MW | D40: =SUMIF('OI 2014'!$I$87:$I$101,C40,'OI 2014'!$L$87:$L$101) -> 0 | E40: =SUMIF('OI 2015'!$I$87:$I$101,C40,'OI 2015'!$L$87:$L$101) -> 0 | F40: =SUMIF('OI 2016'!$I$87:$I$101,C40,'OI 2016'!$L$87:$L$101) -> 0 | G40: =SUMIF('OI 2017'!$I$112:$I$128,C40,'OI 2017'!$L$112:$L$128) -> 0 | H40: =SUMIF('OI 2018'!$I$112:$I$131,C40,'OI 2018'!$L$112:$L$131) -> 0 | I40: =SUMIF('OI 2019'!$I$113:$I$132,C40,'OI 2019'!$L$113:$L$132) -> 0 | J40: =SUMIF('OI 2020'!$I$144:$I$165,C40,'OI 2020'!$K$144:$K$165) -> 141 | K40: =SUMIF('OI 2021'!$I$145:$I$166,C40,'OI 2021'!$K$145:$K$166) -> 0 | L40: =SUMIF('OI 2022'!$I$158:$I$175,$C40,'OI 2022'!$K$158:$K$175) -> 0 | M40: =SUMIF('OI 2023'!$I$158:$I$173,$C40,'OI 2023'!$J$158:$J$173) -> 0
C41: V155-3.6MW | D41: =SUMIF('OI 2014'!$I$87:$I$101,C41,'OI 2014'!$L$87:$L$101) -> 0 | E41: =SUMIF('OI 2015'!$I$87:$I$101,C41,'OI 2015'!$L$87:$L$101) -> 0 | F41: =SUMIF('OI 2016'!$I$87:$I$101,C41,'OI 2016'!$L$87:$L$101) -> 0 | G41: =SUMIF('OI 2017'!$I$112:$I$128,C41,'OI 2017'!$L$112:$L$128) -> 0 | H41: =SUMIF('OI 2018'!$I$112:$I$131,C41,'OI 2018'!$L$112:$L$131) -> 0 | I41: =SUMIF('OI 2019'!$I$113:$I$132,C41,'OI 2019'!$L$113:$L$132) -> 0 | J41: =SUMIF('OI 2020'!$I$144:$I$165,C41,'OI 2020'!$K$144:$K$165) -> 0 | K41: =SUMIF('OI 2021'!$I$145:$I$166,C41,'OI 2021'!$K$145:$K$166) -> 0 | L41: =SUMIF('OI 2022'!$I$158:$I$175,$C41,'OI 2022'!$K$158:$K$175) -> 15 | M41: =SUMIF('OI 2023'!$I$158:$I$173,$C41,'OI 2023'!$J$158:$J$173) -> 36
C42: V162-5.6MW | D42: =SUMIF('OI 2014'!$I$87:$I$101,C42,'OI 2014'!$L$87:$L$101) -> 0 | E42: =SUMIF('OI 2015'!$I$87:$I$101,C42,'OI 2015'!$L$87:$L$101) -> 0 | F42: =SUMIF('OI 2016'!$I$87:$I$101,C42,'OI 2016'!$L$87:$L$101) -> 0 | G42: =SUMIF('OI 2017'!$I$112:$I$128,C42,'OI 2017'!$L$112:$L$128) -> 0 | H42: =SUMIF('OI 2018'!$I$112:$I$131,C42,'OI 2018'!$L$112:$L$131) -> 0 | I42: =SUMIF('OI 2019'!$I$113:$I$132,C42,'OI 2019'!$L$113:$L$132) -> 45 | J42: =SUMIF('OI 2020'!$I$144:$I$165,C42,'OI 2020'!$K$144:$K$165) -> 179 | K42: =SUMIF('OI 2021'!$I$145:$I$166,C42,'OI 2021'!$K$145:$K$166) -> 40 | L42: =SUMIF('OI 2022'!$I$158:$I$175,$C42,'OI 2022'!$K$158:$K$175) -> 0 | M42: =SUMIF('OI 2023'!$I$158:$I$173,$C42,'OI 2023'!$J$158:$J$173) -> 16
C43: V162-6.0MW | D43: =SUMIF('OI 2014'!$I$87:$I$101,C43,'OI 2014'!$L$87:$L$101) -> 0 | E43: =SUMIF('OI 2015'!$I$87:$I$101,C43,'OI 2015'!$L$87:$L$101) -> 0 | F43: =SUMIF('OI 2016'!$I$87:$I$101,C43,'OI 2016'!$L$87:$L$101) -> 0 | G43: =SUMIF('OI 2017'!$I$112:$I$128,C43,'OI 2017'!$L$112:$L$128) -> 0 | H43: =SUMIF('OI 2018'!$I$112:$I$131,C43,'OI 2018'!$L$112:$L$131) -> 0 | I43: =SUMIF('OI 2019'!$I$113:$I$132,C43,'OI 2019'!$L$113:$L$132) -> 0 | J43: =SUMIF('OI 2020'!$I$144:$I$165,C43,'OI 2020'!$K$144:$K$165) -> 38 | K43: =SUMIF('OI 2021'!$I$145:$I$166,C43,'OI 2021'!$K$145:$K$166) -> 303 | L43: =SUMIF('OI 2022'!$I$158:$I$175,$C43,'OI 2022'!$K$158:$K$175) -> 0 | M43: =SUMIF('OI 2023'!$I$158:$I$173,$C43,'OI 2023'!$J$158:$J$173) -> 0
C44: V162-6.2MW | D44: =SUMIF('OI 2014'!$I$87:$I$101,C44,'OI 2014'!$L$87:$L$101) -> 0 | E44: =SUMIF('OI 2015'!$I$87:$I$101,C44,'OI 2015'!$L$87:$L$101) -> 0 | F44: =SUMIF('OI 2016'!$I$87:$I$101,C44,'OI 2016'!$L$87:$L$101) -> 0 | G44: =SUMIF('OI 2017'!$I$112:$I$128,C44,'OI 2017'!$L$112:$L$128) -> 0 | H44: =SUMIF('OI 2018'!$I$112:$I$131,C44,'OI 2018'!$L$112:$L$131) -> 0 | I44: =SUMIF('OI 2019'!$I$113:$I$132,C44,'OI 2019'!$L$113:$L$132) -> 0 | J44: =SUMIF('OI 2020'!$I$144:$I$165,C44,'OI 2020'!$K$144:$K$165) -> 0 | K44: =SUMIF('OI 2021'!$I$145:$I$166,C44,'OI 2021'!$K$145:$K$166) -> 176 | L44: =SUMIF('OI 2022'!$I$158:$I$175,$C44,'OI 2022'!$K$158:$K$175) -> 392 | M44: =SUMIF('OI 2023'!$I$158:$I$173,$C44,'OI 2023'!$J$158:$J$173) -> 281
C45: V163-4.5MW | D45: =SUMIF('OI 2014'!$I$87:$I$101,C45,'OI 2014'!$L$87:$L$101) -> 0 | E45: =SUMIF('OI 2015'!$I$87:$I$101,C45,'OI 2015'!$L$87:$L$101) -> 0 | F45: =SUMIF('OI 2016'!$I$87:$I$101,C45,'OI 2016'!$L$87:$L$101) -> 0 | G45: =SUMIF('OI 2017'!$I$112:$I$128,C45,'OI 2017'!$L$112:$L$128) -> 0 | H45: =SUMIF('OI 2018'!$I$112:$I$131,C45,'OI 2018'!$L$112:$L$131) -> 0 | I45: =SUMIF('OI 2019'!$I$113:$I$132,C45,'OI 2019'!$L$113:$L$132) -> 0 | J45: =SUMIF('OI 2020'!$I$144:$I$165,C45,'OI 2020'!$K$144:$K$165) -> 0 | K45: =SUMIF('OI 2021'!$I$145:$I$166,C45,'OI 2021'!$K$145:$K$166) -> 0 | L45: =SUMIF('OI 2022'!$I$158:$I$175,$C45,'OI 2022'!$K$158:$K$175) -> 0 | M45: =SUMIF('OI 2023'!$I$158:$I$173,$C45,'OI 2023'!$J$158:$J$173) -> 960
C46: V164-10.0MW | D46: =SUMIF('OI 2014'!$I$87:$I$101,C46,'OI 2014'!$L$87:$L$101) -> 0 | E46: =SUMIF('OI 2015'!$I$87:$I$101,C46,'OI 2015'!$L$87:$L$101) -> 0 | F46: =SUMIF('OI 2016'!$I$87:$I$101,C46,'OI 2016'!$L$87:$L$101) -> 0 | G46: =SUMIF('OI 2017'!$I$112:$I$128,C46,'OI 2017'!$L$112:$L$128) -> 0 | H46: =SUMIF('OI 2018'!$I$112:$I$131,C46,'OI 2018'!$L$112:$L$131) -> 0 | I46: =SUMIF('OI 2019'!$I$113:$I$132,C46,'OI 2019'!$L$113:$L$132) -> 0 | J46: =SUMIF('OI 2020'!$I$144:$I$165,C46,'OI 2020'!$K$144:$K$165) -> 0 | K46: =SUMIF('OI 2021'!$I$145:$I$166,C46,'OI 2021'!$K$145:$K$166) -> 0 | L46: =SUMIF('OI 2022'!$I$158:$I$175,$C46,'OI 2022'!$K$158:$K$175) -> 6 | M46: =SUMIF('OI 2023'!$I$158:$I$173,$C46,'OI 2023'!$J$158:$J$173) -> 0
C47: V174-9.5MW | D47: =SUMIF('OI 2014'!$I$87:$I$101,C47,'OI 2014'!$L$87:$L$101) -> 0 | E47: =SUMIF('OI 2015'!$I$87:$I$101,C47,'OI 2015'!$L$87:$L$101) -> 0 | F47: =SUMIF('OI 2016'!$I$87:$I$101,C47,'OI 2016'!$L$87:$L$101) -> 0 | G47: =SUMIF('OI 2017'!$I$112:$I$128,C47,'OI 2017'!$L$112:$L$128) -> 0 | H47: =SUMIF('OI 2018'!$I$112:$I$131,C47,'OI 2018'!$L$112:$L$131) -> 0 | I47: =SUMIF('OI 2019'!$I$113:$I$132,C47,'OI 2019'!$L$113:$L$132) -> 0 | J47: =SUMIF('OI 2020'!$I$144:$I$165,C47,'OI 2020'!$K$144:$K$165) -> 0 | K47: =SUMIF('OI 2021'!$I$145:$I$166,C47,'OI 2021'!$K$145:$K$166) -> 77 | L47: =SUMIF('OI 2022'!$I$158:$I$175,$C47,'OI 2022'!$K$158:$K$175) -> 62 | M47: =SUMIF('OI 2023'!$I$158:$I$173,$C47,'OI 2023'!$J$158:$J$173) -> 0
Q53: India
Q54: Average service contract
Q55: Indian | R55: 2015 | S55: 2016 | T55: 2017 | U55: 2018 | V55: 2019
Q56: AOM4000 | T56: =AVERAGEIFS('OI 2017'!F$2:F$91,'OI 2017'!C$2:C$91,"India",'OI 2017'!E$2:E$91,"AOM4000") -> 10
Q57: AOM5000 | R57: =AVERAGEIFS('OI 2015'!F$2:F$72,'OI 2015'!C$2:C$72,"India",'OI 2015'!E$2:E$72,"AOM5000") -> 10 | T57: =AVERAGEIFS('OI 2017'!F$2:F$91,'OI 2017'!C$2:C$91,"India",'OI 2017'!E$2:E$91,"AOM5000") -> 15 | U57: =AVERAGEIFS('OI 2018'!F$2:F$100,'OI 2018'!C$2:C$100,"India",'OI 2018'!E$2:E$100,"AOM5000") -> 11.666667 | V57: =AVERAGEIFS('OI 2019'!F$2:F$94,'OI 2019'!C$2:C$94,"India",'OI 2019'!E$2:E$94,"AOM5000") -> 15
Q59: MW - service
Q60: Indian | R60: 2015 | S60: 2016 | T60: 2017 | U60: 2018 | V60: 2019
Q61: AOM4000 | R61: ='OI 2015'!F99 -> 0 | S61: 0 | T61: ='OI 2017'!F115 -> 350 | U61: ='OI 2018'!F115 -> 0 | V61: ='OI 2019'!F116 -> 0
Q62: AOM5000 | R62: ='OI 2015'!G99 -> 74 | S62: 0 | T62: ='OI 2017'!G115 -> 216 | U62: ='OI 2018'!G115 -> 322 | V62: ='OI 2019'!G116 -> 101
Q63: No info | R63: 0 | S63: 0 | T63: 0 | U63: ='OI 2018'!E115-'Order and Service summary'!U62-'Order and Service summary'!U61 -> 100 | V63: ='OI 2019'!E116-'Order and Service summary'!V62-'Order and Service summary'!V61 -> 0
C64: USA | D64: 2014 | E64: 2015 | F64: 2016 | G64: 2017 | H64: 2018 | I64: 2019 | J64: 2020 | K64: 2021 | L64: 2022 | M64: 2023 | Q64: total | R64: =SUM(R61:R63) -> 74 | S64: =SUM(S61:S63) -> 0 | T64: =SUM(T61:T63) -> 566 | U64: =SUM(U61:U63) -> 422 | V64: =SUM(V61:V63) -> 101
C65: AOM4000 | D65: ='OI 2014'!F86 -> 0 | E65: ='OI 2015'!F86 -> 438 | F65: ='OI 2016'!F86 -> 0 | G65: ='OI 2017'!F111 -> 200 | H65: ='OI 2018'!F111 -> 0
C66: AOM5000 | D66: ='OI 2014'!G86 -> 1978 | E66: ='OI 2015'!G86 -> 2172 | F66: ='OI 2016'!G86 -> 1008 | G66: ='OI 2017'!_xlnm.Extract -> 1510 | H66: ='OI 2018'!_xlnm.Extract -> 2599 | Q66: Indian | R66: 2015 | S66: 2016 | T66: 2017 | U66: 2018 | V66: 2019 | W66: 2020 | X66: 2021 | Y66: 2022 | AG66: Annual report | AH66: AR 17 | AI66: Ar16 | AJ66: AR15 | AK66: AR14
C67: No info | D67: ='OI 2014'!E86-'OI 2014'!F86-'OI 2014'!G86 -> 0 | E67: ='OI 2015'!E86-'OI 2015'!F86-'OI 2015'!G86 -> 258 | F67: ='OI 2016'!E86-'OI 2016'!F86-'OI 2016'!G86 -> 2276 | G67: ='OI 2017'!E111-'OI 2017'!F111-'OI 2017'!_xlnm.Extract -> 1206 | H67: ='OI 2018'!E111-'OI 2018'!F111-'OI 2018'!_xlnm.Extract -> 1252 | Q67: >2MW | R67: =SUMIFS('OI 2015'!D2:D72,'OI 2015'!C2:C72,"=India",'OI 2015'!K2:K72,"<2") -> 0 | S67: =SUMIFS('OI 2016'!D2:D73,'OI 2016'!C2:C73,"=India",'OI 2016'!K2:K73,"<2") -> 0 | T67: =SUMIFS('OI 2017'!D2:D91,'OI 2017'!C2:C91,"=India",'OI 2017'!K2:K91,"<2") -> 0 | U67: =SUMIFS('OI 2018'!D2:D92,'OI 2018'!C2:C92,"=India",'OI 2018'!K2:K92,"<2") -> 0 | V67: =SUMIFS('OI 2019'!D2:D92,'OI 2019'!C2:C92,"=India",'OI 2019'!K2:K92,"<2") -> 0 | W67: =SUMIFS('OI 2020'!D2:D122,'OI 2020'!C2:C122,"=India",'OI 2020'!K2:K122,"<2") -> 0 | X67: =SUMIFS('OI 2021'!D2:D122,'OI 2021'!C2:C122,"=India",'OI 2021'!K2:K122,"<2") -> 0 | Y67: =SUMIFS('OI 2022'!D2:D122,'OI 2022'!C2:C122,"=India",'OI 2022'!K2:K122,"<2") -> 0 | AG67: Type of contract | AH67: 2017 | AI67: 2016 | AJ67: 2015 | AK67: 2014
C68: total | D68: =SUM(D65:D67) -> 1978 | E68: =SUM(E65:E67) -> 2868 | F68: =SUM(F65:F67) -> 3284 | G68: =SUM(G65:G67) -> 2916 | H68: =SUM(H65:H67) -> 3851 | Q68: 2-2.99MW | R68: =SUMIFS('OI 2015'!D2:D72,'OI 2015'!C2:C72,"=India",'OI 2015'!K2:K72,"<3")-R67 -> 74 | S68: =SUMIFS('OI 2016'!D2:D73,'OI 2016'!C2:C73,"=India",'OI 2016'!K2:K73,"<3")-S67 -> 0 | T68: =SUMIFS('OI 2017'!D2:D91,'OI 2017'!C2:C91,"=India",'OI 2017'!K2:K91,"<3")-T67 -> 566 | U68: =SUMIFS('OI 2018'!D2:D92,'OI 2018'!C2:C92,"=India",'OI 2018'!K2:K92,"<3")-U67 -> 422 | V68: =SUMIFS('OI 2019'!D2:D92,'OI 2019'!C2:C92,"=India",'OI 2019'!K2:K92,"<3")-V67 -> 101 | W68: =SUMIFS('OI 2020'!D2:D122,'OI 2020'!C2:C122,"=India",'OI 2020'!K2:K122,"<3")-W67 -> 17 | X68: =SUMIFS('OI 2021'!D2:D122,'OI 2021'!C2:C122,"=India",'OI 2021'!K2:K122,"<3")-X67 -> 202 | Y68: =SUMIFS('OI 2022'!D2:D122,'OI 2022'!C2:C122,"=India",'OI 2022'!K2:K122,"<3")-Y67 -> 51 | AG68: AOM 2000 | AH68: 1.3 | AI68: 2.7 | AJ68: 4.3 | AK68: 0.2
Q69: 3-3.99MW | R69: =SUMIFS('OI 2015'!D2:D72,'OI 2015'!C2:C72,"=India",'OI 2015'!K2:K72,"<4")-R67-R68 -> 0 | S69: =SUMIFS('OI 2016'!D2:D73,'OI 2016'!C2:C73,"=India",'OI 2016'!K2:K73,"<4")-S67-S68 -> 0 | T69: =SUMIFS('OI 2017'!D2:D91,'OI 2017'!C2:C91,"=India",'OI 2017'!K2:K91,"<4")-T67-T68 -> 0 | U69: =SUMIFS('OI 2018'!D2:D92,'OI 2018'!C2:C92,"=India",'OI 2018'!K2:K92,"<4")-U67-U68 -> 0 | V69: =SUMIFS('OI 2019'!D2:D92,'OI 2019'!C2:C92,"=India",'OI 2019'!K2:K92,"<4")-V68-V67 -> 0 | W69: =SUMIFS('OI 2020'!D2:D122,'OI 2020'!C2:C122,"=India",'OI 2020'!K2:K122,"<4")-W68-W67 -> 0 | X69: =SUMIFS('OI 2021'!D2:D122,'OI 2021'!C2:C122,"=India",'OI 2021'!K2:K122,"<4")-X68-X67 -> 0 | Y69: =SUMIFS('OI 2022'!D2:D122,'OI 2022'!C2:C122,"=India",'OI 2022'!K2:K122,"<4")-Y68-Y67 -> 54 | AG69: AOM3000 | AH69: 3.4 | AI69: 4.2 | AJ69: 6.4 | AK69: 1.3
Q70: Total | R70: =SUM(R67:R69) -> 74 | S70: =SUM(S67:S69) -> 0 | T70: =SUM(T67:T69) -> 566 | U70: =SUM(U67:U69) -> 422 | V70: =SUM(V67:V69) -> 101 | W70: =SUM(W67:W69) -> 17 | X70: =SUM(X67:X69) -> 202 | Y70: =SUM(Y67:Y69) -> 105 | AG70: AOM4000 | AH70: 33.7 | AI70: 47 | AJ70: 42.3 | AK70: 40.9
AG71: AOM5000 | AH71: 61.6 | AI71: 46.1 | AJ71: 47 | AK71: 57.6
Q77: 2014 | R77: 2014 | S77: 2015 | T77: 2015 | U77: 2016 | V77: 2016 | W77: 2017 | X77: 2017 | Y77: 2018 | Z77: 2018 | AA77: 2019 | AB77: 2019 | AC77: 2020 | AD77: 2020 | AE77: 2021 | AF77: 2021 | AG77: 2022 | AH77: 2022
Q78: AOM4000 | R78: AOM5000 | S78: AOM4000 | T78: AOM5000 | U78: AOM4000 | V78: AOM5000 | W78: AOM4000 | X78: AOM5000 | Y78: AOM4000 | Z78: AOM5000 | AA78: AOM4000 | AB78: AOM5000 | AC78: AOM4000 | AD78: AOM5000 | AE78: AOM4000 | AF78: AOM5000 | AG78: AOM4000 | AH78: AOM5000
P79: 0-5 | Q79: ='OI 2014'!D116 -> 606 | R79: ='OI 2014'!E116 -> 1177 | S79: ='OI 2015'!D116 -> 33 | T79: ='OI 2015'!E116 -> 0 | U79: ='OI 2016'!D116 -> 438 | V79: ='OI 2016'!E116 -> 1880 | W79: ='OI 2017'!D140 -> 297 | X79: ='OI 2017'!E140 -> 726 | Y79: ='OI 2018'!D147 -> 580 | Z79: ='OI 2018'!E147 -> 1808 | AA79: ='OI 2019'!D148 -> 324 | AB79: ='OI 2019'!E148 -> 417 | AC79: ='OI 2020'!D179 -> 993 | AD79: ='OI 2020'!E179 -> 399 | AE79: ='OI 2021'!D181 -> 0 | AF79: ='OI 2021'!E181 -> 0 | AG79: ='OI 2022'!D193 -> 0 | AH79: ='OI 2022'!E193 -> 0
P80: 5-10 | Q80: ='OI 2014'!D117 -> 201 | R80: ='OI 2014'!E117 -> 1092 | S80: ='OI 2015'!D117 -> 0 | T80: ='OI 2015'!E117 -> 0 | U80: ='OI 2016'!D117 -> 521 | V80: ='OI 2016'!E117 -> 365 | W80: ='OI 2017'!D141 -> 447 | X80: ='OI 2017'!E141 -> 765 | Y80: ='OI 2018'!D148 -> 0 | Z80: ='OI 2018'!E148 -> 1594 | AA80: ='OI 2019'!D149 -> 98 | AB80: ='OI 2019'!E149 -> 2040 | AC80: ='OI 2020'!D180 -> 327 | AD80: ='OI 2020'!E180 -> 1615 | AE80: ='OI 2021'!D182 -> 0 | AF80: ='OI 2021'!E182 -> 0 | AG80: ='OI 2022'!D194 -> 0 | AH80: ='OI 2022'!E194 -> 0
P81: 10-15 | Q81: ='OI 2014'!D118 -> 427 | R81: ='OI 2014'!E118 -> 290 | S81: ='OI 2015'!D118 -> 0 | T81: ='OI 2015'!E118 -> 0 | U81: ='OI 2016'!D118 -> 323 | V81: ='OI 2016'!E118 -> 351 | W81: ='OI 2017'!D142 -> 310 | X81: ='OI 2017'!E142 -> 966 | Y81: ='OI 2018'!D149 -> 154 | Z81: ='OI 2018'!E149 -> 946.4 | AA81: ='OI 2019'!D150 -> 783 | AB81: ='OI 2019'!E150 -> 522 | AC81: ='OI 2020'!D181 -> 46 | AD81: ='OI 2020'!E181 -> 1189 | AE81: ='OI 2021'!D183 -> 0 | AF81: ='OI 2021'!E183 -> 0 | AG81: ='OI 2022'!D195 -> 0 | AH81: ='OI 2022'!E195 -> 0
P82: 15-20 | Q82: ='OI 2014'!D119 -> 0 | R82: ='OI 2014'!E119 -> 0 | S82: ='OI 2015'!D119 -> 0 | T82: ='OI 2015'!E119 -> 0 | U82: ='OI 2016'!D119 -> 536 | V82: ='OI 2016'!E119 -> 172 | W82: ='OI 2017'!D143 -> 255 | X82: ='OI 2017'!E143 -> 1236 | Y82: ='OI 2018'!D150 -> 131.8 | Z82: ='OI 2018'!E150 -> 1092 | AA82: ='OI 2019'!D151 -> 763 | AB82: ='OI 2019'!E151 -> 1067 | AC82: ='OI 2020'!D182 -> 653 | AD82: ='OI 2020'!E182 -> 3255 | AE82: ='OI 2021'!D184 -> 0 | AF82: ='OI 2021'!E184 -> 0 | AG82: ='OI 2022'!D196 -> 0 | AH82: ='OI 2022'!E196 -> 0
P83: 20+ | Q83: ='OI 2014'!D120 -> 0 | R83: ='OI 2014'!E120 -> 0 | S83: ='OI 2015'!D120 -> 0 | T83: ='OI 2015'!E120 -> 0 | U83: ='OI 2016'!D120 -> 0 | V83: ='OI 2016'!E120 -> 0 | W83: ='OI 2017'!D144 -> 54 | X83: ='OI 2017'!E144 -> 49 | Y83: ='OI 2018'!D151 -> 0 | Z83: ='OI 2018'!E151 -> 1402 | AA83: ='OI 2019'!D152 -> 246 | AB83: ='OI 2019'!E152 -> 2167 | AC83: ='OI 2020'!D183 -> 68 | AD83: ='OI 2020'!E183 -> 2125 | AE83: ='OI 2021'!D185 -> 0 | AF83: ='OI 2021'!E185 -> 0 | AG83: ='OI 2022'!D197 -> 0 | AH83: ='OI 2022'!E197 -> 0
P84: no info | Q84: ='OI 2014'!D121 -> 0 | R84: ='OI 2014'!E121 -> 0 | S84: ='OI 2015'!D121 -> 2330 | T84: ='OI 2015'!E121 -> 3421 | U84: ='OI 2016'!D121 -> 31 | V84: ='OI 2016'!E121 -> 422 | W84: ='OI 2017'!D145 -> 422 | X84: ='OI 2017'!E145 -> 809 | Y84: ='OI 2018'!D152 -> 337 | Z84: ='OI 2018'!E152 -> 518 | AA84: ='OI 2019'!D153 -> 0 | AB84: ='OI 2019'!E153 -> 388 | AC84: ='OI 2020'!D184 -> 0 | AD84: ='OI 2020'!E184 -> 921 | AE84: ='OI 2021'!D186 -> 587 | AF84: ='OI 2021'!E186 -> 8612 | AG84: ='OI 2022'!D198 -> 568 | AH84: ='OI 2022'!E198 -> 7190
C85: Germany | D85: 2014 | E85: 2015 | F85: 2016 | G85: 2017 | H85: 2018 | P85: sum | Q85: =SUM(Q79:Q83) -> 1234 | R85: =SUM(R79:R83) -> 2559 | S85: =SUM(S79:S83) -> 33 | T85: =SUM(T79:T83) -> 0 | U85: =SUM(U79:U83) -> 1818 | V85: =SUM(V79:V83) -> 2768 | W85: =SUM(W79:W83) -> 1363 | X85: =SUM(X79:X83) -> 3742 | ... AH85: =SUM(AH79:AH83) -> 0
C86: AOM4000 | D86: ='OI 2014'!F90 -> 79 | E86: ='OI 2015'!F90 -> 26 | F86: ='OI 2016'!F90 -> 76 | G86: ='OI 2017'!F114 -> 53 | H86: ='OI 2018'!F114 -> 58.8
C87: AOM5000 | D87: ='OI 2014'!G90 -> 99 | E87: ='OI 2015'!G90 -> 126 | F87: ='OI 2016'!G90 -> 83 | G87: ='OI 2017'!G114 -> 125 | H87: ='OI 2018'!G114 -> 21
C88: No info | D88: ='OI 2014'!E90-'OI 2014'!F90-'OI 2014'!G90 -> 0 | E88: ='OI 2015'!E90-'OI 2015'!F90-'OI 2015'!G90 -> 0 | F88: ='OI 2016'!E90-'OI 2016'!F90-'OI 2016'!G90 -> 0 | G88: ='OI 2017'!E114-'OI 2017'!F114-'OI 2017'!G114 -> 41 | H88: ='OI 2018'!E114-'OI 2018'!F114-'OI 2018'!G114 -> 0
C89: total | D89: =SUM(D86:D88) -> 178 | E89: =SUM(E86:E88) -> 152 | F89: =SUM(F86:F88) -> 159 | G89: =SUM(G86:G88) -> 219 | H89: =SUM(H86:H88) -> 79.8
S106: Site specific solutions
C108: China | D108: MW | E108: # | R108: Turbine model of platform | S108: 2008 | T108: 2009 | U108: 2010 | V108: 2011 | W108: 2012 | X108: 2013 | Y108: 2014 | Z108: 2015 | AA108: 2016 | AB108: 2017 | AC108: 2018 | AD108: 2019 | AE108: 2020 | AF108: 2021
C109: 2023 | D109: 0 | R109: # orders total | S109: 27 | T109: 26 | U109: 65 | V109: 56 | W109: 33 | X109: 48 | Y109: 46 | Z109: 71 | AA109: 72 | AB109: 90 | AC109: 91 | AD109: 92 | AE109: 120 | AF109: 82
C110: 2022 | D110: ='OI 2022'!E158 -> 0 | R110: multi turbine | S110: 3 | T110: 0 | U110: 9 | V110: 0 | W110: 1 | X110: 6 | Y110: 5 | Z110: 3 | AA110: 10 | AB110: 10 | AC110: 6 | AD110: 10 | AE110: 27 | AF110: 18
C111: 2021 | D111: ='OI 2021'!E146 -> 0 | R111: multi tower | S111: 0 | T111: 0 | U111: 0 | V111: 0 | W111: 0 | X111: 0 | Y111: 0 | Z111: 0 | AA111: 0 | AB111: 4 | AC111: 1 | AD111: 2 | AE111: 3 | AF111: 1
C112: 2020 | D112: ='OI 2020'!E144 -> 1331 | R112: Power optimization | S112: 0 | T112: 0 | U112: 0 | V112: 0 | W112: 0 | X112: 0 | Y112: 0 | Z112: 0 | AA112: 8 | AB112: 22 | AC112: 35 | AD112: 18 | AE112: 50 | AF112: 22
C113: 2019 | D113: ='OI 2019'!E113 -> 317
C114: 2018 | D114: ='OI 2018'!E112 -> 291
C115: 2017 | D115: ='OI 2017'!E112 -> 758 | R115: Turbine model of platform | S115: 2008 | T115: 2009 | U115: 2010 | V115: 2011 | W115: 2012 | X115: 2013 | Y115: 2014 | Z115: 2015 | AA115: 2016 | AB115: 2017 | AC115: 2018 | AD115: 2019 | AE115: 2020 | AF115: 2021
C116: 2016 | D116: ='OI 2016'!E87 -> 399 | R116: multi turbine | S116: =S110/S$109 -> 0.11111111 | T116: =T110/T$109 -> 0 | U116: =U110/U$109 -> 0.13846154 | V116: =V110/V$109 -> 0 | W116: =W110/W$109 -> 0.03030303 | X116: =X110/X$109 -> 0.125 | Y116: =Y110/Y$109 -> 0.10869565 | Z116: =Z110/Z$109 -> 0.042253521 | ... AF116: =AF110/AF$109 -> 0.2195122
C117: 2015 | D117: ='OI 2015'!E87 -> 520 | R117: multi tower | S117: =S111/S$109 -> 0 | T117: =T111/T$109 -> 0 | U117: =U111/U$109 -> 0 | V117: =V111/V$109 -> 0 | W117: =W111/W$109 -> 0 | X117: =X111/X$109 -> 0 | Y117: =Y111/Y$109 -> 0 | Z117: =Z111/Z$109 -> 0 | ... AF117: =AF111/AF$109 -> 0.012195122
C118: 2014 | D118: ='OI 2014'!E93 -> 102 | R118: Power optimization | S118: =S112/S$109 -> 0 | T118: =T112/T$109 -> 0 | U118: =U112/U$109 -> 0 | V118: =V112/V$109 -> 0 | W118: =W112/W$109 -> 0 | X118: =X112/X$109 -> 0 | Y118: =Y112/Y$109 -> 0 | Z118: =Z112/Z$109 -> 0 | ... AF118: =AF112/AF$109 -> 0.26829268
C119: 2013 | D119: ='OI 2013'!E87 -> 198
C120: 2012 | D120: ='OI 2012'!E87 -> 296.4
C121: 2011 | D121: ='OI 2011'!E95 -> 394
C122: 2010 | D122: ='OI 2010'!E95 -> 824
C123: 2009 | D123: ='OI 2009'!E95 -> 248
C124: 2008 | D124: ='OI 2008'!E95 -> 497.2

Sheet Market share
D6: 2026 | E6: 2025 | F6: 2024 | G6: 2023 | H6: 2022 | I6: 2021 | J6: 2020 | K6: 2019 | L6: 2018 | M6: 2017 | N6: 2016 | O6: 2015 | P6: 2014 | Q6: 2013 | R6: 2012 | S6: 2011
C7: AF | F7: ='OI 2024'!H233 -> 0.027769722 | G7: ='OI 2023'!H213 -> 0.035627742 | J7: ='OI 2020'!H218 -> 0.020171296
C8: AS | E8: ='OI 2025'!H236 -> 0.076372315 | F8: ='OI 2024'!H237 -> 0.0574971 | G8: ='OI 2023'!H217 -> 0.033204532 | H8: ='OI 2022'!H216 -> 0.10445845 | I8: ='OI 2021'!H216 -> 0.06116739 | J8: ='OI 2020'!H222 -> 0.201793
C9: AU | E9: ='OI 2025'!H238 -> 0.046269921 | F9: ='OI 2024'!H239 -> 0.094765081 | G9: ='OI 2023'!H219 -> 0.016635012 | H9: ='OI 2022'!H218 -> 0.13153595 | I9: ='OI 2021'!H217 -> 0.076410999 | J9: ='OI 2020'!H223 -> 0.057712319
C10: EU | E10: ='OI 2025'!H252 -> 0.49973054 | F10: ='OI 2024'!H255 -> 0.50442285 | G10: ='OI 2023'!H233 -> 0.37016177 | H10: ='OI 2022'!H233 -> 0.29190009 | I10: ='OI 2021'!H235 -> 0.45036179 | J10: ='OI 2020'!H238 -> 0.36156247
C11: NA | E11: ='OI 2025'!H256 -> 0.27946724 | F11: ='OI 2024'!H261 -> 0.33642691 | G11: ='OI 2023'!H235 -> 0.46250573 | H11: ='OI 2022'!H234 -> 0.21930439 | I11: ='OI 2021'!H238 -> 0.28760251 | J11: ='OI 2020'!H241 -> 0.19618987
C12: SA | E12: ='OI 2025'!H259 -> 0.098159982 | F12: ='OI 2024'!H263 -> 0.006888051 | G12: ='OI 2023'!H237 -> 0.11749296 | H12: ='OI 2022'!H236 -> 0.25280112 | I12: ='OI 2021'!H240 -> 0.12445731 | J12: ='OI 2020'!H244 -> 0.16257104

Sheet blade delivery
C1: turbines | G1: blades
B2: platform | C2: 2023 | D2: 2024 | E2: 2025 | G2: 2023 | H2: 2024 | I2: 2025
A3: =LEFT(B3,4) -> V100 | B3: V100-2.0MW | C3: =SUMIF(N$7:N$39,B3,P$7:P$39) -> 2 | D3: =SUMIF(T$7:T$39,B3,S$7:S$39) -> 0 | G3: =C3*3 -> 6 | H3: =D3*3 -> 0
A4: =LEFT(B4,4) -> V110 | B4: V110-2.2MW | C4: =SUMIF(N$7:N$39,B4,P$7:P$39) -> 33 | D4: =SUMIF(T$7:T$39,B4,S$7:S$39) -> 0 | G4: =C4*3 -> 99 | H4: =D4*3 -> 0
A5: =LEFT(B5,4) -> V117 | B5: V117-4.2MW | C5: =SUMIF(N$7:N$39,B5,P$7:P$39) -> 22 | D5: =SUMIF(T$7:T$39,B5,S$7:S$39) -> 12 | G5: =C5*3 -> 66 | H5: =D5*3 -> 36
A6: =LEFT(B6,4) -> V126 | B6: V126-3.45MW | C6: =SUMIF(N$7:N$39,B6,P$7:P$39) -> 11 | D6: =SUMIF(T$7:T$39,B6,S$7:S$39) -> 0 | G6: =C6*3 -> 33 | H6: =D6*3 -> 0 | P6: 2023 | S6: 2024
A7: =LEFT(B7,4) -> V136 | B7: V136-4.2MW | C7: =SUMIF(N$7:N$39,B7,P$7:P$39) -> 49 | D7: =SUMIF(T$7:T$39,B7,S$7:S$39) -> 0 | G7: =C7*3 -> 147 | H7: =D7*3 -> 0 | N7: V117-4.2MW | P7: 10 | S7: 43 | T7: V150-4.5MW
A8: =LEFT(B8,4) -> V136 | B8: V136-4.5MW | C8: =SUMIF(N$7:N$39,B8,P$7:P$39) -> 67 | D8: =SUMIF(T$7:T$39,B8,S$7:S$39) -> 0 | G8: =C8*3 -> 201 | H8: =D8*3 -> 0 | N8: V150-4.2MW | P8: 20 | S8: 31 | T8: V174-9.5MW
A9: =LEFT(B9,4) -> V150 | B9: V150-4.2MW | C9: =SUMIF(N$7:N$39,B9,P$7:P$39) -> 135 | D9: =SUMIF(T$7:T$39,B9,S$7:S$39) -> 0 | G9: =C9*3 -> 405 | H9: =D9*3 -> 0 | N9: V150-4.2MW | P9: 81 | S9: 94 | T9: V150-4.5MW
A10: =LEFT(B10,4) -> V150 | B10: V150-4.5MW | C10: =SUMIF(N$7:N$39,B10,P$7:P$39) -> 234 | D10: =SUMIF(T$7:T$39,B10,S$7:S$39) -> 276 | G10: =C10*3 -> 702 | H10: =D10*3 -> 828 | N10: V174-9.5MW | P10: 50 | S10: 3 | T10: V164-10.0MW
A11: =LEFT(B11,4) -> V162 | B11: V162-6.0MW | C11: =SUMIF(N$7:N$39,B11,P$7:P$39) -> 7 | D11: =SUMIF(T$7:T$39,B11,S$7:S$39) -> 0 | G11: =C11*3 -> 21 | H11: =D11*3 -> 0 | N11: V150-4.5MW | P11: 22 | S11: 19 | T11: V150-4.5MW
A12: =LEFT(B12,4) -> V162 | B12: V162-6.2MW | C12: =SUMIF(N$7:N$39,B12,P$7:P$39) -> 53 | D12: =SUMIF(T$7:T$39,B12,S$7:S$39) -> 12 | G12: =C12*3 -> 159 | H12: =D12*3 -> 36 | N12: V162-6.0MW | P12: 7 | S12: 120 | T12: V150-4.5MW
A13: =LEFT(B13,4) -> V164 | B13: V164-10.0MW | C13: =SUMIF(N$7:N$39,B13,P$7:P$39) -> 0 | D13: =SUMIF(T$7:T$39,B13,S$7:S$39) -> 3 | G13: =C13*3 -> 0 | H13: =D13*3 -> 9 | N13: V150-4.5MW | P13: 25 | S13: 12 | T13: V117-4.2MW
A14: =LEFT(B14,4) -> V174 | B14: V174-9.5MW | C14: =SUMIF(N$7:N$39,B14,P$7:P$39) -> 81 | D14: =SUMIF(T$7:T$39,B14,S$7:S$39) -> 31 | G14: =C14*3 -> 243 | H14: =D14*3 -> 93 | N14: V150-4.5MW | P14: 55 | S14: 12 | T14: V162-6.2MW
N15: V136-4.2MW | P15: 5
N16: V150-4.5MW | P16: 7
N17: V150-4.5MW | P17: 19
N18: V150-4.2MW | P18: 7
C19: turbines | G19: blades | N19: V117-4.2MW | P19: 12
C20: 2023 | D20: 2024 | E20: 2025 | G20: 2023 | H20: 2024 | I20: 2025 | N20: V150-4.2MW | P20: 18
B21: V100 | C21: =SUMIF(A$3:A$14,B21,C$3:C$14) -> 2 | D21: =SUMIF(A$3:A$14,B21,D$3:D$14) -> 0 | G21: =C21*3 -> 6 | H21: =D21*3 -> 0 | N21: V162-6.2MW | P21: 15
B22: V110 | C22: =SUMIF(A$3:A$14,B22,C$3:C$14) -> 33 | D22: =SUMIF(A$3:A$14,B22,D$3:D$14) -> 0 | G22: =C22*3 -> 99 | H22: =D22*3 -> 0 | N22: V136-4.5MW | P22: 8
B23: V117 | C23: =SUMIF(A$3:A$14,B23,C$3:C$14) -> 22 | D23: =SUMIF(A$3:A$14,B23,D$3:D$14) -> 12 | G23: =C23*3 -> 66 | H23: =D23*3 -> 36 | N23: V136-4.2MW | P23: 3
B24: V126 | C24: =SUMIF(A$3:A$14,B24,C$3:C$14) -> 11 | D24: =SUMIF(A$3:A$14,B24,D$3:D$14) -> 0 | G24: =C24*3 -> 33 | H24: =D24*3 -> 0 | N24: V174-9.5MW | P24: 31
B25: V136 | C25: =SUMIF(A$3:A$14,B25,C$3:C$14) -> 116 | D25: =SUMIF(A$3:A$14,B25,D$3:D$14) -> 0 | G25: =C25*3 -> 348 | H25: =D25*3 -> 0 | N25: V136-4.2MW | P25: 24
B26: V150 | C26: =SUMIF(A$3:A$14,B26,C$3:C$14) -> 369 | D26: =SUMIF(A$3:A$14,B26,D$3:D$14) -> 276 | G26: =C26*3 -> 1107 | H26: =D26*3 -> 828 | N26: V110-2.2MW | P26: 33
B27: V162 | C27: =SUMIF(A$3:A$14,B27,C$3:C$14) -> 60 | D27: =SUMIF(A$3:A$14,B27,D$3:D$14) -> 12 | G27: =C27*3 -> 180 | H27: =D27*3 -> 36 | N27: V150-4.5MW | P27: 19
B28: V164 | C28: =SUMIF(A$3:A$14,B28,C$3:C$14) -> 0 | D28: =SUMIF(A$3:A$14,B28,D$3:D$14) -> 3 | G28: =C28*3 -> 0 | H28: =D28*3 -> 9 | N28: V150-4.2MW | P28: 9
B29: V174 | C29: =SUMIF(A$3:A$14,B29,C$3:C$14) -> 81 | D29: =SUMIF(A$3:A$14,B29,D$3:D$14) -> 31 | G29: =C29*3 -> 243 | H29: =D29*3 -> 93 | N29: V162-6.2MW | P29: 15
N30: V126-3.45MW | P30: 11
N31: V136-4.2MW | P31: 7
N32: V100-2.0MW | P32: 2
N33: V136-4.5MW | P33: 59
N34: V136-4.2MW | P34: 10
N35: V150-4.5MW | P35: 23
N36: V150-4.5MW | P36: 23
N37: V162-6.2MW | P37: 11
N38: V150-4.5MW | P38: 41
N39: V162-6.2MW | P39: 12

Sheet delivery 2024
B1: date | C1: country | D1: size [MW] | E1: Service scheme | F1: Service time [years] | G1: customer | H1: # | I1: platform | J1: Rotor | K1: MW | L1: special mode | M1: Tower height | N1: Multi towerH | O1: # | P1: Multi platform | Q1: Rotor | R1: MW | S1: special mode | T1: Tower height | U1: # | V1: Multi platform | W1: Rotor | X1: MW | Z1: Note | AA1: delivery q | AB1: delivery y | AC1: platform check | AD1: country check
B3: 30.06.2021 | C3: Germany | D3: 476 | E3: offshore | F3: 10 | G3: Iberdrola | H3: 50 | I3: V174-9.5MW | J3: 174 | K3: 9.5 | Z3: offshore 75km from shore | AB3: 2024 | AC3: =COUNTIF($I$146:$I$176,I3) -> 0 | AD3: =COUNTIF($C$145:$C$176,C3) -> 0 | AF3: project complete
B4: 08.03.2022 | C4: Brazil | D4: 194 | E4: AOM5000 | F4: 5 | H4: 43 | I4: V150-4.5MW | J4: 150 | K4: 4.5 | AH4: 2024 | AI4: 1 | AJ4: 1
B5: 31.03.2022 | C5: Taiwan | D5: 295 | E5: AOM5000 | F5: 15 | G5: CIP | H5: 31 | I5: V174-9.5MW | J5: 174 | K5: 9.5 | AG5: 1 | AH5: 2024 | AI5: 1 | AJ5: 1 | AM5: 33 | AN5: V110-2.2MW
B6: 05.05.2022 | C6: Brazil | D6: 423 | E6: AOM5000 | F6: 20 | G6: Pan American Energy Energias Renováveis | H6: 94 | I6: V150-4.5MW | J6: 150 | K6: 4.5 | AH6: 2024 | AI6: 1 | AJ6: 1 | AM6: 7 | AN6: V136-4.2MW
B7: 27.06.2022 | C7: France | D7: 30 | E7: AOM5000 | F7: 15 | G7: Qair, TotalEnergies, BW Ideol | H7: 3 | I7: V164-10.0MW | J7: 164 | K7: 10 | AF7: 18 km offshore | AG7: 3 | AH7: 2024 | AI7: 1 | AJ7: 1 | AM7: 10 | AN7: V136-4.2MW
B8: 30.06.2022 | C8: Brazil | D8: 86 | E8: AOM5000 | F8: 25 | G8: PEC Energia | H8: 19 | I8: V150-4.5MW | J8: 150 | K8: 4.5 | AH8: 2024 | AI8: 1 | AJ8: 1 | AM8: 12 | AN8: V162-6.2MW
B9: 30.06.2022 | C9: UK | D9: 67 | E9: AOM5000 | G9: Red Rock Power limited | H9: 13 | I9: V136-4.5MW | J9: 136 | K9: 4.5 | O9: 2 | P9: V117-4.2MW | Q9: 117 | R9: 4.2 | AG9: 1 | AH9: 2024 | AI9: 1 | AJ9: 1
B10: 30.09.2022 | C10: Brazil | D10: 540 | E10: AOM5000 | F10: 25 | G10: ENGIE | H10: 120 | I10: V150-4.5MW | J10: 150 | K10: 4.5 | AG10: 3 | AH10: 2024 | AI10: 1 | AJ10: 1
B11: 30.09.2022 | C11: Japan | D11: 50 | E11: AOM5000 | F11: 20 | G11: Toda Corporation | H11: 12 | I11: V117-4.2MW | J11: 117 | K11: 4.2 | M11: 9x 114 + 3x84 | AG11: 2 | AH11: 2024 | AI11: 1 | AJ11: 1
B12: 30.09.2022 | C12: Finland | D12: 74 | E12: AOM5000 | F12: 30 | H12: 12 | I12: V162-6.2MW | J12: 162 | K12: 6.2 | AG12: 2 | AH12: 2024 | AI12: 1 | AJ12: 1
B20: region | C20: coutry | D20: Size MW
B21: AS | C21: Japan | D21: =SUMIF(C$2:C$13,C21,D$2:D$13) -> 50
B22: AS | C22: Taiwan | D22: =SUMIF(C$2:C$13,C22,D$2:D$13) -> 295
B23: EU | C23: Finland | D23: =SUMIF(C$2:C$13,C23,D$2:D$13) -> 74 | F23: =SQRT(D23)/5 -> 1.7204651
B24: EU | C24: France | D24: =SUMIF(C$2:C$13,C24,D$2:D$13) -> 30 | F24: =SQRT(D24)/5 -> 1.0954451
B25: EU | C25: Germany | D25: =SUMIF(C$2:C$13,C25,D$2:D$13) -> 476 | F25: =SQRT(D25)/5 -> 4.3634848
B26: EU | C26: UK | D26: =SUMIF(C$2:C$13,C26,D$2:D$13) -> 67 | F26: =SQRT(D26)/5 -> 1.6370706
B27: SA | C27: Brazil | D27: =SUMIF(C$2:C$13,C27,D$2:D$13) -> 1243

Sheet delivery 2023
B1: date | C1: country | D1: size [MW] | E1: Service scheme | F1: Service time [years] | G1: customer | H1: # | I1: platform | J1: Rotor | K1: MW | L1: special mode | M1: Tower height | N1: Multi towerH | O1: # | P1: Multi platform | Q1: Rotor | R1: MW | S1: special mode | T1: Tower height | U1: # | V1: Multi platform | W1: Rotor | X1: MW | Z1: Note | AA1: delivery q | AB1: delivery y | AC1: platform check | AD1: country check
B3: 31.03.2021 | C3: Ireland | D3: 30 | E3: AOM5000 | H3: 7 | I3: V117-4.2MW | J3: 117 | K3: 4.3 | L3: opt 4.3MW | M3: 76.5 | AA3: 2 | AB3: 2023 | AC3: 1 | AD3: 1
B4: 31.03.2021 | C4: Japan | D4: 42 | E4: AOM5000 | F4: 20 | G4: Toko Electrical Construction Co., Ltd | H4: 10 | I4: V117-4.2MW | J4: 117 | K4: 4.2 | L4: opt 4.2MW | M4: 94 | AA4: 1 | AB4: 2023 | AC4: 1 | AD4: 1 | AK4: 2023
B5: 03.05.2021 | C5: Sweden | D5: 86 | E5: AOM5000 | F5: 30 | G5: OX2 | H5: 20 | I5: V150-4.2MW | J5: 150 | K5: 4.3 | L5: opt 4.3MW | AA5: 2 | AB5: 2023 | AC5: 1 | AD5: 1 | AI5: V150-4.5MW | AK5: 25
B6: 16.06.2021 | C6: Brazil | D6: 348 | E6: AOM5000 | F6: 5 | H6: 81 | I6: V150-4.2MW | J6: 150 | K6: 4.3 | L6: opt 4.3MW | AB6: 2023 | AC6: 1 | AD6: 1
B7: 30.09.2021 | C7: Brazil | D7: 189 | E7: AOM5000 | F7: 20 | G7: Casa dos Ventos | H7: 42 | I7: V150-4.2MW | J7: 150 | K7: 4.5 | L7: opt 4.5MW | AA7: 3 | AB7: 2023 | AC7: 1 | AD7: 1
B8: 07.12.2021 | C8: Brazil | D8: 99 | E8: AOM5000 | F8: 15 | H8: 22 | I8: V150-4.5MW | J8: 150 | K8: 4.5 | AB8: 2023 | AC8: 1 | AD8: 1
B9: 29.12.2021 | C9: Finland | D9: 87 | E9: AOM5000 | F9: 25 | G9: ABO Wind AG | H9: 14 | I9: V162-6.2MW | J9: 162 | K9: 6.2 | AA9: 2 | AB9: 2023 | AC9: 1 | AD9: 1
B10: 30.12.2021 | C10: Germany | D10: 42 | E10: AOM4000 | F10: 20 | G10: Repowering Wöhrden Poolgesellschaft GmbH & Co KG | H10: 7 | I10: V162-6.0MW | J10: 162 | K10: 6 | AA10: 1 | AB10: 2023 | AC10: 1 | AD10: 1
B11: 31.12.2021 | C11: Brazil | D11: 113 | E11: AOM5000 | F11: 15 | H11: 25 | I11: V150-4.5MW | J11: 150 | K11: 4.5 | AA11: 2 | AB11: 2023 | AC11: 1 | AD11: 1
B12: 31.12.2021 | C12: Brazil | D12: 248 | E12: AOM5000 | F12: 20 | G12: Elera Renováveis | H12: 55 | I12: V150-4.5MW | J12: 150 | K12: 4.5 | AA12: 2 | AB12: 2023 | AC12: 1 | AD12: 1
B13: 03.03.2022 | C13: Estonia | D13: 21 | E13: AOM5000 | F13: 30 | G13: Enefit Green | H13: 5 | I13: V136-4.2MW | J13: 136 | K13: 4.2 | M13: 82 | AG13: 1 | AH13: 2023 | AI13: 1 | AJ13: 1
B14: 11.03.2022 | C14: Sweden | D14: 32 | E14: AOM5000 | F14: long-term | G14: Octopus Renewables | H14: 7 | I14: V150-4.5MW | J14: 150 | K14: 4.5 | AG14: 2 | AH14: 2023 | AI14: 1 | AJ14: 1
B15: 15.03.2022 | C15: Argentina | D15: 86 | E15: AOM5000 | F15: 30 | G15: PCR | H15: 19 | I15: V150-4.5MW | J15: 150 | K15: 4.5 | AG15: 1 | AH15: 2023 | AI15: 1 | AJ15: 1
B16: 18.03.2022 | C16: Italy | D16: 30 | E16: AOM5000 | F16: 15 | H16: 7 | I16: V150-4.2MW | J16: 150 | K16: 4.3 | L16: opt 4.3MW | AG16: 3 | AH16: 2023 | AI16: 1 | AJ16: 1
B17: 31.03.2022 | C17: Italy | D17: 97 | E17: AOM5000 | F17: multi-year | G17: ERG | H17: 12 | I17: V117-4.2MW | J17: 117 | K17: 4.2 | O17: 13 | P17: V117-3.45MW | Q17: 117 | R17: 3.45 | S17: opt 3.6MW | AG17: 1 | AH17: 2023 | AI17: 1 | AJ17: 1 | AM17: 7 | AN17: V150-4.2MW | AP17: 3 | AQ17: V164-10.0MW
B18: 31.03.2022 | C18: Australia | D18: 76 | H18: 18 | I18: V150-4.2MW | J18: 150 | K18: 4.2 | AG18: 1 | AH18: 2023 | AI18: 1 | AJ18: 1 | AM18: 12 | AN18: V117-4.2MW | AP18: 19 | AQ18: V150-4.5MW
B19: 31.03.2022 | C19: Finland | D19: 93 | E19: AOM5000 | F19: 30 | H19: 15 | I19: V162-6.2MW | J19: 162 | K19: 6.2 | AG19: 2 | AH19: 2023 | AI19: 1 | AJ19: 1 | AM19: 18 | AN19: V150-4.2MW | AP19: 120 | AQ19: V150-4.5MW
B20: 31.03.2022 | C20: Greece | D20: 36 | E20: AOM5000 | F20: 20 | H20: 8 | I20: V136-4.5MW | J20: 136 | K20: 4.5 | AG20: 2 | AH20: 2023 | AI20: 1 | AJ20: 1 | AM20: 15 | AN20: V162-6.2MW | AP20: 12 | AQ20: V117-4.2MW
B21: 31.03.2022 | C21: Italy | D21: 30 | E21: AOM4000 | F21: 10 | G21: A2A | H21: 3 | I21: V136-4.2MW | J21: 136 | K21: 4.2 | L21: opt 4.0MW | O21: 5 | P21: V136-3.45MW | Q21: 136 | R21: 3.6 | S21: Opt 3.6MW | AG21: 1 | AH21: 2023 | AI21: 1 | AJ21: 1 | AM21: 8 | AN21: V136-4.5MW | AP21: 12 | AQ21: V162-6.2MW
B22: 31.03.2022 | C22: Taiwan | D22: 295 | E22: offshore | F22: 14 | G22: Foxwell Energy Corp | H22: 31 | I22: V174-9.5MW | J22: 174 | K22: 9.5 | AG22: 1 | AH22: 2023 | AI22: 1 | AJ22: 1 | AM22: 24 | AN22: V136-4.2MW
B23: 08.06.2022 | C23: Italy | D23: 101 | E23: AOM5000 | G23: ERG | H23: 24 | I23: V136-4.2MW | J23: 136 | K23: 4.2 | AG23: 2 | AH23: 2023 | AI23: 1 | AJ23: 1 | AM23: 59 | AN23: V136-4.5MW
B24: 28.06.2022 | C24: Poland | D24: 73 | E24: AOM5000 | F24: 15 | G24: PAK-Polska Czysta Energia | H24: 33 | I24: V110-2.2MW | J24: 110 | K24: 2.2 | M24: 120 | AG24: 3 | AH24: 2023 | AI24: 1 | AJ24: 1 | AM24: 23 | AN24: V150-4.5MW
B25: 29.06.2022 | C25: United states | D25: 86 | E25: AOM5000 | F25: 10 | G25: Sacramento Municipal Unitility District | H25: 19 | I25: V150-4.5MW | J25: 150 | K25: 4.5 | AG25: 4 | AH25: 2023 | AI25: 1 | AJ25: 1 | AM25: 23 | AN25: V150-4.5MW
B26: 29.06.2022 | C26: Estonia | D26: 39 | E26: AOM5000 | F26: 30 | G26: Utilitas | H26: 9 | I26: V150-4.2MW | J26: 150 | K26: 4.3 | L26: opt 4.3MW | AG26: 2 | AH26: 2023 | AI26: 1 | AJ26: 1 | AM26: 11 | AN26: V162-6.2MW
B27: 29.06.2022 | C27: Finland | D27: 135 | E27: AOM5000 | F27: 35 | G27: Ilmatar Energy Oy | H27: 15 | I27: V162-6.2MW | J27: 162 | K27: 6.2 | O27: 10 | P27: V150-4.2MW | Q27: 150 | R27: 4.2 | Z27: # of turbines are assumed | AG27: 2 | AH27: 2023 | AI27: 1 | AJ27: 1 | AM27: 41 | AN27: V150-4.5MW
B28: 30.06.2022 | C28: Denmark | D28: 40 | E28: AOM5000 | F28: 20 | G28: Eurowind Energy | H28: 11 | I28: V126-3.45MW | J28: 126 | K28: 3.6 | L28: opt 3.6MW | AG28: 2 | AH28: 2023 | AI28: 1 | AJ28: 1
B29: 30.06.2022 | C29: Italy | D29: 39 | E29: AOM5000 | F29: 20 | G29: PLT engineering | H29: 7 | I29: V136-4.2MW | J29: 136 | K29: 4.3 | L29: opt 4.3MW | O29: 2 | P29: V117-4.2MW | Q29: 117 | R29: 4.2 | S29: opt 4.3MW | AG29: 2 | AH29: 2023 | AI29: 1 | AJ29: 1
B30: 30.06.2022 | C30: Italy | D30: 27 | E30: AOM4000 | F30: 10 | G30: IVPC | H30: 2 | I30: V100-2.0MW | J30: 100 | K30: 2.2 | L30: opt 2.2MW | O30: 6 | P30: V126-3.45MW | Q30: 126 | R30: 3.8 | S30: opt 3.8MW | AG30: 1 | AH30: 2023 | AI30: 1 | AJ30: 1
B31: 30.06.2022 | C31: United states | D31: 266 | E31: AOM5000 | F31: 30 | G31: Omega Energia | H31: 59 | I31: V136-4.5MW | J31: 136 | K31: 4.5 | AG31: 2 | AH31: 2023 | AI31: 1 | AJ31: 1
B32: 14.09.2022 | C32: New Zealand | D32: 43 | E32: AOM5000 | F32: 30 | G32: Mercury | H32: 10 | I32: V136-4.2MW | J32: 136 | K32: 4.3 | L32: opt 4.3MW | AG32: 2 | AH32: 2023 | AI32: 1 | AJ32: 1
B33: 19.09.2022 | C33: Spain | D33: 104 | E33: AOM4000 | F33: 10 | G33: Estudios y Proyectos Pradamap | H33: 23 | I33: V150-4.5MW | J33: 150 | K33: 4.5 | AH33: 2023 | AI33: 1 | AJ33: 1
B34: 21.09.2022 | C34: Brazil | D34: 104 | E34: AOM5000 | F34: 20 | G34: Polimix Energia | H34: 23 | I34: V150-4.5MW | J34: 150 | K34: 4.5 | AG34: 4 | AH34: 2023 | AI34: 1 | AJ34: 1
B35: 26.09.2022 | C35: Germany | D35: 66 | E35: AOM5000 | F35: 25 | G35: Gaarz IV Windkraft | H35: 11 | I35: V162-6.2MW | J35: 162 | K35: 6 | L35: opt 6.0MW | AG35: 3 | AH35: 2023 | AI35: 1 | AJ35: 1
B36: 29.09.2022 | C36: United states | D36: 185 | E36: AOM5000 | H36: 41 | I36: V150-4.5MW | J36: 150 | K36: 4.5 | AG36: 3 | AH36: 2023 | AI36: 1 | AJ36: 1
B37: 30.09.2022 | C37: Lithuania | D37: 74 | E37: AOM5000 | F37: 35 | G37: Vestas | H37: 12 | I37: V162-6.2MW | J37: 162 | K37: 6.2 | AF37: vestas EPC | AG37: 2 | AH37: 2023 | AI37: 1 | AJ37: 1
B38: 09.11.2022 | C38: United states | D38: 300 | E38: AOM5000 | F38: 10 | G38: Apex Clean Energy | H38: 50 | I38: V162-6.2MW | J38: 162 | K38: 6 | L38: opt 6.0MW | AG38: 3 | AH38: 2023 | AI38: 1 | AJ38: 1
B46: region | C46: coutry | D46: Size MW
B47: AS | C47: Japan | D47: =SUMIF(C$2:C$38,C47,D$2:D$38) -> 42
B48: AS | C48: Taiwan | D48: =SUMIF(C$2:C$38,C48,D$2:D$38) -> 295
B49: AU | C49: Australia | D49: =SUMIF(C$2:C$38,C49,D$2:D$38) -> 76
B50: AU | C50: New Zealand | D50: =SUMIF(C$2:C$38,C50,D$2:D$38) -> 43
B51: EU | C51: Denmark | D51: =SUMIF(C$2:C$38,C51,D$2:D$38) -> 40 | F51: =SQRT(D51)/5 -> 1.2649111
B52: EU | C52: Estonia | D52: =SUMIF(C$2:C$38,C52,D$2:D$38) -> 60 | F52: =SQRT(D52)/5 -> 1.5491933
B53: EU | C53: Finland | D53: =SUMIF(C$2:C$38,C53,D$2:D$38) -> 315 | F53: =SQRT(D53)/5 -> 3.5496479
B54: EU | C54: Germany | D54: =SUMIF(C$2:C$38,C54,D$2:D$38) -> 108 | F54: =SQRT(D54)/5 -> 2.078461
B55: EU | C55: Greece | D55: =SUMIF(C$2:C$38,C55,D$2:D$38) -> 36 | F55: =SQRT(D55)/5 -> 1.2
B56: EU | C56: Ireland | D56: =SUMIF(C$2:C$38,C56,D$2:D$38) -> 30 | F56: =SQRT(D56)/5 -> 1.0954451
B57: EU | C57: Italy | D57: =SUMIF(C$2:C$38,C57,D$2:D$38) -> 324 | F57: =SQRT(D57)/5 -> 3.6
B58: EU | C58: Lithuania | D58: =SUMIF(C$2:C$38,C58,D$2:D$38) -> 74 | F58: =SQRT(D58)/5 -> 1.7204651
B59: EU | C59: Poland | D59: =SUMIF(C$2:C$38,C59,D$2:D$38) -> 73 | F59: =SQRT(D59)/5 -> 1.7088007
B60: EU | C60: Spain | D60: =SUMIF(C$2:C$38,C60,D$2:D$38) -> 104 | F60: =SQRT(D60)/5 -> 2.0396078
B61: EU | C61: Sweden | D61: =SUMIF(C$2:C$38,C61,D$2:D$38) -> 118 | F61: =SQRT(D61)/5 -> 2.1725561
B62: NA | C62: United states | D62: =SUMIF(C$2:C$38,C62,D$2:D$38) -> 837
B63: SA | C63: Argentina | D63: =SUMIF(C$2:C$38,C63,D$2:D$38) -> 86
B64: SA | C64: Brazil | D64: =SUMIF(C$2:C$38,C64,D$2:D$38) -> 1101

Sheet OI 2025
B1: date | C1: country | D1: size [MW] | E1: Service scheme | F1: Service time [years] | G1: customer | H1: # | I1: platform | J1: Rotor | K1: MW | L1: special mode | M1: Tower height | N1: Multi towerH | O1: # | P1: Multi platform | Q1: Rotor | R1: MW | S1: special mode | T1: Tower height | U1: # | V1: Multi platform | W1: Rotor | X1: MW | Y1: Tower height | Z1: Note | AA1: # | AB1: Multi platform | AC1: Rotor | AD1: MW | AE1: Tower height | AF1: Note | AG1: delivery q | AH1: delivery y | AI1: platform check | AJ1: country check | AL1: Delivery days
B2: 22.01.2025 | C2: Ukraine | D2: 384 | E2: AOM5000 | F2: 20 | G2: DTEK | H2: 64 | I2: V162-6.2MW | J2: 162 | K2: 6 | L2: opt 6,0 | AG2: 1 | AH2: 2026 | AI2: =COUNTIF($I$177:$I$213,I2) -> 1 | AJ2: =COUNTIF($C$176:$C$210,C2) -> 1 | AK2: =COUNTIF($C$232:$C$266,C2) -> 1 | AL2: =_xlfn.DAYS(DATE(AH2,AG2*3-2,1),DATE(RIGHT(B2,4),MID(B2,4,2),LEFT(B2,2))) -> 344
B3: 13.03.2025 | C3: Germany | D3: 62 | E3: AOM4000 | F3: 20 | G3: Ørsted Wind Power A/S | H3: 11 | I3: V150-6.0MW | J3: 150 | K3: 5.6 | L3: opt 5,6 | AG3: 4 | AH3: 2026 | AI3: =COUNTIF($I$177:$I$213,I3) -> 1 | AJ3: =COUNTIF($C$176:$C$210,C3) -> 1 | AK3: =COUNTIF($C$232:$C$266,C3) -> 1 | AL3: =_xlfn.DAYS(DATE(AH3,AG3*3-2,1),DATE(RIGHT(B3,4),MID(B3,4,2),LEFT(B3,2))) -> 567
B4: 26.03.2025 | C4: Germany | D4: 62 | E4: AOM5000 | F4: 20 | G4: MIBRAG GmbH | H4: 10 | I4: V162-6.2MW | J4: 162 | K4: 6.2 | AG4: 1 | AH4: 2026 | AI4: =COUNTIF($I$177:$I$213,I4) -> 1 | AJ4: =COUNTIF($C$176:$C$210,C4) -> 1 | AK4: =COUNTIF($C$232:$C$266,C4) -> 1 | AL4: =_xlfn.DAYS(DATE(AH4,AG4*3-2,1),DATE(RIGHT(B4,4),MID(B4,4,2),LEFT(B4,2))) -> 281
B5: 28.03.2025 | C5: Taiwan | D5: 495 | G5: CIP | H5: 33 | I5: V236-15.0MW | J5: 236 | K5: 15 | AF5: offshore | AG5: 2 | AH5: 2027 | AI5: =COUNTIF($I$177:$I$213,I5) -> 1 | AJ5: =COUNTIF($C$176:$C$210,C5) -> 1 | AK5: =COUNTIF($C$232:$C$266,C5) -> 1 | AL5: =_xlfn.DAYS(DATE(AH5,AG5*3-2,1),DATE(RIGHT(B5,4),MID(B5,4,2),LEFT(B5,2))) -> 734
B6: 31.03.22025 | C6: Italy | D6: 50 | F6: 10 | G6: Edison Spa | H6: 11 | I6: V136-4.5MW | J6: 136 | K6: 4.5 | AG6: 2 | AH6: 2026 | AI6: =COUNTIF($I$177:$I$213,I6) -> 1 | AJ6: =COUNTIF($C$176:$C$210,C6) -> 1 | AK6: =COUNTIF($C$232:$C$266,C6) -> 1 | AL6: =_xlfn.DAYS(DATE(AH6,AG6*3-2,1),DATE(RIGHT(B6,4),MID(B6,4,2),LEFT(B6,2))) -> 366
B7: 31.03.22025 | C7: Germany | D7: 1020 | F7: 25 | G7: Vattenfall | H7: 68 | I7: V236-15.0MW | J7: 236 | K7: 15 | AG7: 2 | AH7: 2027 | AI7: =COUNTIF($I$177:$I$213,I7) -> 1 | AJ7: =COUNTIF($C$176:$C$210,C7) -> 1 | AK7: =COUNTIF($C$232:$C$266,C7) -> 1 | AL7: =_xlfn.DAYS(DATE(AH7,AG7*3-2,1),DATE(RIGHT(B7,4),MID(B7,4,2),LEFT(B7,2))) -> 731
B8: 31.03.22025 | C8: Germany | D8: 49 | G8: WPD | H8: 7 | I8: V162-6.2MW | J8: 162 | K8: 6.2 | O8: 1 | P8: V150-6.0MW | Q8: 150 | R8: 6 | AI8: =COUNTIF($I$177:$I$213,I8) -> 1 | AJ8: =COUNTIF($C$176:$C$210,C8) -> 1 | AK8: =COUNTIF($C$232:$C$266,C8) -> 1 | AL8: =_xlfn.DAYS(DATE(AH8,AG8*3-2,1),DATE(RIGHT(B8,4),MID(B8,4,2),LEFT(B8,2))) -> #NUM!
B9: 31.03.22025 | C9: Germany | D9: 29 | G9: WPD | H9: 2 | I9: V150-6.0MW | J9: 150 | K9: 6 | O9: 2 | P9: V162-5.6MW | Q9: 162 | R9: 5.6 | U9: 1 | V9: V162-6.2MW | W9: 162 | X9: 6.2 | AI9: =COUNTIF($I$177:$I$213,I9) -> 1 | AJ9: =COUNTIF($C$176:$C$210,C9) -> 1 | AK9: =COUNTIF($C$232:$C$266,C9) -> 1 | AL9: =_xlfn.DAYS(DATE(AH9,AG9*3-2,1),DATE(RIGHT(B9,4),MID(B9,4,2),LEFT(B9,2))) -> #NUM!
B10: 31.03.22025 | C10: Germany | D10: 21 | G10: WPD | H10: 5 | I10: V150-4.2MW | J10: 150 | K10: 4.2 | AI10: =COUNTIF($I$177:$I$213,I10) -> 1 | AJ10: =COUNTIF($C$176:$C$210,C10) -> 1 | AK10: =COUNTIF($C$232:$C$266,C10) -> 1 | AL10: =_xlfn.DAYS(DATE(AH10,AG10*3-2,1),DATE(RIGHT(B10,4),MID(B10,4,2),LEFT(B10,2))) -> #NUM!
B11: 31.03.22025 | C11: Germany | D11: 17 | G11: WPD | H11: 4 | I11: V150-4.2MW | J11: 150 | K11: 4.2 | AI11: =COUNTIF($I$177:$I$213,I11) -> 1 | AJ11: =COUNTIF($C$176:$C$210,C11) -> 1 | AK11: =COUNTIF($C$232:$C$266,C11) -> 1 | AL11: =_xlfn.DAYS(DATE(AH11,AG11*3-2,1),DATE(RIGHT(B11,4),MID(B11,4,2),LEFT(B11,2))) -> #NUM!
B12: 31.03.22025 | C12: Germany | D12: 12 | G12: WPD | H12: 2 | I12: V150-6.0MW | J12: 150 | K12: 6 | AI12: =COUNTIF($I$177:$I$213,I12) -> 1 | AJ12: =COUNTIF($C$176:$C$210,C12) -> 1 | AK12: =COUNTIF($C$232:$C$266,C12) -> 1 | AL12: =_xlfn.DAYS(DATE(AH12,AG12*3-2,1),DATE(RIGHT(B12,4),MID(B12,4,2),LEFT(B12,2))) -> #NUM!
B13: 31.03.22025 | C13: Germany | D13: 12 | G13: WPD | H13: 2 | I13: V162-6.2MW | J13: 162 | K13: 6.2 | AI13: =COUNTIF($I$177:$I$213,I13) -> 1 | AJ13: =COUNTIF($C$176:$C$210,C13) -> 1 | AK13: =COUNTIF($C$232:$C$266,C13) -> 1 | AL13: =_xlfn.DAYS(DATE(AH13,AG13*3-2,1),DATE(RIGHT(B13,4),MID(B13,4,2),LEFT(B13,2))) -> #NUM!
B14: 31.03.22025 | C14: Germany | D14: 7 | G14: WPD | H14: 1 | I14: V162-7.2MW | J14: 162 | K14: 7.2 | AI14: =COUNTIF($I$177:$I$213,I14) -> 1 | AJ14: =COUNTIF($C$176:$C$210,C14) -> 1 | AK14: =COUNTIF($C$232:$C$266,C14) -> 1 | AL14: =_xlfn.DAYS(DATE(AH14,AG14*3-2,1),DATE(RIGHT(B14,4),MID(B14,4,2),LEFT(B14,2))) -> #NUM!
B15: 31.03.22025 | C15: Germany | D15: 6 | G15: WPD | H15: 1 | I15: V162-6.2MW | J15: 162 | K15: 6 | L15: opt 6,0 | AI15: =COUNTIF($I$177:$I$213,I15) -> 1 | AJ15: =COUNTIF($C$176:$C$210,C15) -> 1 | AK15: =COUNTIF($C$232:$C$266,C15) -> 1 | AL15: =_xlfn.DAYS(DATE(AH15,AG15*3-2,1),DATE(RIGHT(B15,4),MID(B15,4,2),LEFT(B15,2))) -> #NUM!
A16: =SUM(D2:D16) -> 2398 | B16: 31.03.22025 | C16: United states | D16: 172 | E16: AOM5000 | F16: 10 | G16: Clearway Energy Grou | H16: 27 | I16: V117-4.2MW | J16: 117 | K16: 4.3 | L16: opt 4,3 | AI16: =COUNTIF($I$177:$I$213,I16) -> 1 | AJ16: =COUNTIF($C$176:$C$210,C16) -> 1 | AK16: =COUNTIF($C$232:$C$266,C16) -> 1 | AL16: =_xlfn.DAYS(DATE(AH16,AG16*3-2,1),DATE(RIGHT(B16,4),MID(B16,4,2),LEFT(B16,2))) -> #NUM!
B17: 05.05.2025 | C17: Germany | D17: 65 | E17: AOM5000 | F17: 20 | G17: Lindenhof GmbH | H17: 9 | I17: V162-7.2MW | J17: 162 | K17: 7.2 | AG17: 4 | AH17: 2026 | AI17: =COUNTIF($I$177:$I$213,I17) -> 1 | AJ17: =COUNTIF($C$176:$C$210,C17) -> 1 | AK17: =COUNTIF($C$232:$C$266,C17) -> 1 | AL17: =_xlfn.DAYS(DATE(AH17,AG17*3-2,1),DATE(RIGHT(B17,4),MID(B17,4,2),LEFT(B17,2))) -> 514
B18: 13.05.2025 | C18: Germany | D18: 22 | E18: AOM5000 | F18: 20 | G18: WWS Projektbau GmbH & Co. KG | H18: 3 | I18: V172-7.2MW | J18: 172 | K18: 7.2 | AG18: 4 | AH18: 2026 | AI18: =COUNTIF($I$177:$I$213,I18) -> 1 | AJ18: =COUNTIF($C$176:$C$210,C18) -> 1 | AK18: =COUNTIF($C$232:$C$266,C18) -> 1 | AL18: =_xlfn.DAYS(DATE(AH18,AG18*3-2,1),DATE(RIGHT(B18,4),MID(B18,4,2),LEFT(B18,2))) -> 506
B19: 13.05.2025 | C19: Germany | D19: 14 | E19: AOM4000 | F19: 20 | G19: Berliner Stadtwerke GmbH | H19: 2 | I19: V172-7.2MW | J19: 172 | K19: 7.2 | AI19: =COUNTIF($I$177:$I$213,I19) -> 1 | AJ19: =COUNTIF($C$176:$C$210,C19) -> 1 | AK19: =COUNTIF($C$232:$C$266,C19) -> 1 | AL19: =_xlfn.DAYS(DATE(AH19,AG19*3-2,1),DATE(RIGHT(B19,4),MID(B19,4,2),LEFT(B19,2))) -> #NUM!
B20: 13.05.2025 | C20: Germany | D20: 48 | E20: AOM5000 | F20: 20 | G20: ABO Energy | H20: 8 | I20: V150-6.0MW | J20: 150 | K20: 6 | AI20: =COUNTIF($I$177:$I$213,I20) -> 1 | AJ20: =COUNTIF($C$176:$C$210,C20) -> 1 | AK20: =COUNTIF($C$232:$C$266,C20) -> 1 | AL20: =_xlfn.DAYS(DATE(AH20,AG20*3-2,1),DATE(RIGHT(B20,4),MID(B20,4,2),LEFT(B20,2))) -> #NUM!
B21: 30.05.2025 | C21: Italy | D21: 32 | E21: AOM5000 | F21: 25 | H21: 5 | I21: V162-6.4MW | J21: 162 | K21: 6.4 | AG21: 4 | AH21: 2025 | AI21: =COUNTIF($I$177:$I$213,I21) -> 1 | AJ21: =COUNTIF($C$176:$C$210,C21) -> 1 | AK21: =COUNTIF($C$232:$C$266,C21) -> 1 | AL21: =_xlfn.DAYS(DATE(AH21,AG21*3-2,1),DATE(RIGHT(B21,4),MID(B21,4,2),LEFT(B21,2))) -> 124
B22: 30.05.2025 | C22: Italy | D22: 95 | E22: AOM4000 | G22: Dolomiti Energia Group and IVPC Group | H22: 5 | I22: V162-6.4MW | J22: 162 | K22: 6.4 | O22: 14 | P22: V136-4.5MW | Q22: 136 | R22: 4.5 | AG22: 2 | AH22: 2026 | AI22: =COUNTIF($I$177:$I$213,I22) -> 1 | AJ22: =COUNTIF($C$176:$C$210,C22) -> 1 | AK22: =COUNTIF($C$232:$C$266,C22) -> 1 | AL22: =_xlfn.DAYS(DATE(AH22,AG22*3-2,1),DATE(RIGHT(B22,4),MID(B22,4,2),LEFT(B22,2))) -> 306
B23: 03.06.2025 | C23: Argentina | D23: 102 | E23: AOM5000 | F23: 10 | H23: 16 | I23: V162-6.4MW | J23: 162 | K23: 6.4 | AG23: 4 | AH23: 2026 | AI23: =COUNTIF($I$177:$I$213,I23) -> 1 | AJ23: =COUNTIF($C$176:$C$210,C23) -> 1 | AK23: =COUNTIF($C$232:$C$266,C23) -> 1 | AL23: =_xlfn.DAYS(DATE(AH23,AG23*3-2,1),DATE(RIGHT(B23,4),MID(B23,4,2),LEFT(B23,2))) -> 485
B24: 09.06.2025 | C24: Spain | D24: 46 | E24: AOM4000 | F24: 10 | G24: Naturgy | H24: 7 | I24: V150-6.0MW | J24: 150 | K24: 6 | O24: 2 | P24: V110-2.2MW | Q24: 110 | R24: 2.2 | AG24: 4 | AH24: 2025 | AI24: =COUNTIF($I$177:$I$213,I24) -> 1 | AJ24: =COUNTIF($C$176:$C$210,C24) -> 1 | AK24: =COUNTIF($C$232:$C$266,C24) -> 1 | AL24: =_xlfn.DAYS(DATE(AH24,AG24*3-2,1),DATE(RIGHT(B24,4),MID(B24,4,2),LEFT(B24,2))) -> 114
B25: 17.06.2025 | C25: Canada | D25: 124 | E25: AOM5000 | F25: 10 | G25: EDF | H25: 20 | I25: V162-6.2MW | J25: 162 | K25: 6.2 | AG25: 2 | AH25: 2026 | AI25: =COUNTIF($I$177:$I$213,I25) -> 1 | AJ25: =COUNTIF($C$176:$C$210,C25) -> 1 | AK25: =COUNTIF($C$232:$C$266,C25) -> 1 | AL25: =_xlfn.DAYS(DATE(AH25,AG25*3-2,1),DATE(RIGHT(B25,4),MID(B25,4,2),LEFT(B25,2))) -> 288
B26: 30.06.2025 | C26: Germany | D26: 175 | E26: AOM4000 | F26: 20 | G26: Boreas Energie GmbH | H26: 29 | I26: V162-6.2MW | J26: 162 | K26: 6 | L26: opt 6,0 | AG26: 3 | AH26: 2026 | AI26: =COUNTIF($I$177:$I$213,I26) -> 1 | AJ26: =COUNTIF($C$176:$C$210,C26) -> 1 | AK26: =COUNTIF($C$232:$C$266,C26) -> 1 | AL26: =_xlfn.DAYS(DATE(AH26,AG26*3-2,1),DATE(RIGHT(B26,4),MID(B26,4,2),LEFT(B26,2))) -> 366
B27: 30.06.2025 | C27: France | D27: 50 | E27: AOM5000 | F27: 25 | H27: 12 | I27: V117-4.2MW | J27: 117 | K27: 4.2 | AG27: 3 | AH27: 2026 | AI27: =COUNTIF($I$177:$I$213,I27) -> 1 | AJ27: =COUNTIF($C$176:$C$210,C27) -> 1 | AK27: =COUNTIF($C$232:$C$266,C27) -> 1 | AL27: =_xlfn.DAYS(DATE(AH27,AG27*3-2,1),DATE(RIGHT(B27,4),MID(B27,4,2),LEFT(B27,2))) -> 366
B28: 30.06.2025 | C28: Greece | D28: 32 | E28: AOM4000 | F28: 20 | H28: 7 | I28: V136-4.5MW | J28: 136 | K28: 4.5 | AG28: 4 | AH28: 2025 | AI28: =COUNTIF($I$177:$I$213,I28) -> 1 | AJ28: =COUNTIF($C$176:$C$210,C28) -> 1 | AK28: =COUNTIF($C$232:$C$266,C28) -> 1 | AL28: =_xlfn.DAYS(DATE(AH28,AG28*3-2,1),DATE(RIGHT(B28,4),MID(B28,4,2),LEFT(B28,2))) -> 93
B29: 30.06.2025 | C29: Romania | D29: 28 | E29: AOM4000 | F29: 20 | H29: 8 | I29: V117-3.45MW | J29: 117 | K29: 3.45 | AG29: 2 | AH29: 2026 | AI29: =COUNTIF($I$177:$I$213,I29) -> 1 | AJ29: =COUNTIF($C$176:$C$210,C29) -> 1 | AK29: =COUNTIF($C$232:$C$266,C29) -> 1 | AL29: =_xlfn.DAYS(DATE(AH29,AG29*3-2,1),DATE(RIGHT(B29,4),MID(B29,4,2),LEFT(B29,2))) -> 275
B30: 30.06.2025 | C30: Japan | D30: 21 | E30: AOM4000 | F30: 20 | G30: Chubu Electric Power Co., Ltd. | H30: 5 | I30: V117-4.2MW | J30: 117 | K30: 4.2 | AG30: 1 | AH30: 2027 | AI30: =COUNTIF($I$177:$I$213,I30) -> 1 | AJ30: =COUNTIF($C$176:$C$210,C30) -> 1 | AK30: =COUNTIF($C$232:$C$266,C30) -> 1 | AL30: =_xlfn.DAYS(DATE(AH30,AG30*3-2,1),DATE(RIGHT(B30,4),MID(B30,4,2),LEFT(B30,2))) -> 550
B31: 30.06.2025 | C31: Romania | D31: 143 | E31: AOM5000 | F31: 20 | G31: Eurowind Energy | H31: 23 | I31: V162-6.2MW | J31: 162 | K31: 6.2 | AG31: 3 | AH31: 2026 | AI31: =COUNTIF($I$177:$I$213,I31) -> 1 | AJ31: =COUNTIF($C$176:$C$210,C31) -> 1 | AK31: =COUNTIF($C$232:$C$266,C31) -> 1 | AL31: =_xlfn.DAYS(DATE(AH31,AG31*3-2,1),DATE(RIGHT(B31,4),MID(B31,4,2),LEFT(B31,2))) -> 366
A32: =SUM(D17:D32) -> 1112 | B32: 30.06.2025 | C32: Germany | D32: 115 | E32: AOM5000 | F32: 25 | G32: ENERTRAG | H32: 16 | I32: V172-7.2MW | J32: 172 | K32: 7.2 | AG32: 2 | AH32: 2027 | AI32: =COUNTIF($I$177:$I$213,I32) -> 1 | AJ32: =COUNTIF($C$176:$C$210,C32) -> 1 | AK32: =COUNTIF($C$232:$C$266,C32) -> 1 | AL32: =_xlfn.DAYS(DATE(AH32,AG32*3-2,1),DATE(RIGHT(B32,4),MID(B32,4,2),LEFT(B32,2))) -> 640
B33: 15.07.2025 | C33: Finland | D33: 74 | E33: AOM5000 | F33: 25 | G33: TOWII Renewables A/S | H33: 12 | I33: V162-6.2MW | J33: 162 | K33: 6.2 | AG33: 2 | AH33: 2026 | AI33: =COUNTIF($I$177:$I$213,I33) -> 1 | AJ33: =COUNTIF($C$176:$C$210,C33) -> 1 | AK33: =COUNTIF($C$232:$C$266,C33) -> 1 | AL33: =_xlfn.DAYS(DATE(AH33,AG33*3-2,1),DATE(RIGHT(B33,4),MID(B33,4,2),LEFT(B33,2))) -> 260
B34: 17.07.2025 | C34: United states | D34: 527 | E34: AOM5000 | F34: 5 | H34: 117 | I34: V150-4.5MW | J34: 150 | K34: 4.5 | AG34: 2 | AH34: 2026 | AI34: =COUNTIF($I$177:$I$213,I34) -> 1 | AJ34: =COUNTIF($C$176:$C$210,C34) -> 1 | AK34: =COUNTIF($C$232:$C$266,C34) -> 1 | AL34: =_xlfn.DAYS(DATE(AH34,AG34*3-2,1),DATE(RIGHT(B34,4),MID(B34,4,2),LEFT(B34,2))) -> 258
B35: 21.07.2025 | C35: Romania | D35: 269 | E35: AOM5000 | F35: 15 | G35: First Look Solutions S.R.L | H35: 42 | I35: V162-6.4MW | J35: 162 | K35: 6.4 | AG35: 3 | AH35: 2026 | AI35: =COUNTIF($I$177:$I$213,I35) -> 1 | AJ35: =COUNTIF($C$176:$C$210,C35) -> 1 | AK35: =COUNTIF($C$232:$C$266,C35) -> 1 | AL35: =_xlfn.DAYS(DATE(AH35,AG35*3-2,1),DATE(RIGHT(B35,4),MID(B35,4,2),LEFT(B35,2))) -> 345
B36: 01.08.2025 | C36: Chile | D36: 128 | E36: AOM5000 | F36: 10 | H36: 20 | I36: V162-6.4MW | J36: 162 | K36: 6.4 | AG36: 1 | AH36: 2027 | AI36: =COUNTIF($I$177:$I$213,I36) -> 1 | AJ36: =COUNTIF($C$176:$C$210,C36) -> 1 | AK36: =COUNTIF($C$232:$C$266,C36) -> 1 | AL36: =_xlfn.DAYS(DATE(AH36,AG36*3-2,1),DATE(RIGHT(B36,4),MID(B36,4,2),LEFT(B36,2))) -> 518
B37: 07.08.2025 | C37: Germany | D37: 74 | E37: AOM4000 | F37: 20 | G37: Prezeller Wind GmbH & Co. KG | H37: 12 | I37: V162-6.2MW | J37: 162 | K37: 6.2 | AG37: 3 | AH37: 2026 | AI37: =COUNTIF($I$177:$I$213,I37) -> 1 | AJ37: =COUNTIF($C$176:$C$210,C37) -> 1 | AK37: =COUNTIF($C$232:$C$266,C37) -> 1 | AL37: =_xlfn.DAYS(DATE(AH37,AG37*3-2,1),DATE(RIGHT(B37,4),MID(B37,4,2),LEFT(B37,2))) -> 328
B38: 07.08.2025 | C38: Canada | D38: 274 | E38: AOM5000 | F38: 10 | G38: EDF | H38: 25 | I38: V162-6.0MW | J38: 162 | K38: 6 | O38: 20 | P38: V162-6.2MW | Q38: 162 | R38: 6.2 | AG38: 3 | AH38: 2026 | AI38: =COUNTIF($I$177:$I$213,I38) -> 1 | AJ38: =COUNTIF($C$176:$C$210,C38) -> 1 | AK38: =COUNTIF($C$232:$C$266,C38) -> 1 | AL38: =_xlfn.DAYS(DATE(AH38,AG38*3-2,1),DATE(RIGHT(B38,4),MID(B38,4,2),LEFT(B38,2))) -> 328
B39: 08.08.2025 | C39: Romania | D39: 96 | E39: AOM5000 | G39: OX2 Construction AB | H39: 15 | I39: V162-6.4MW | J39: 162 | K39: 6.4 | AG39: 2 | AH39: 2026 | AI39: =COUNTIF($I$177:$I$213,I39) -> 1 | AJ39: =COUNTIF($C$176:$C$210,C39) -> 1 | AK39: =COUNTIF($C$232:$C$266,C39) -> 1 | AL39: =_xlfn.DAYS(DATE(AH39,AG39*3-2,1),DATE(RIGHT(B39,4),MID(B39,4,2),LEFT(B39,2))) -> 236
B40: 11.08.2025 | C40: Poland | D40: 40 | E40: AOM5000 | F40: 20 | H40: 10 | I40: V136-4.2MW | J40: 136 | K40: 4 | L40: opt 4,0 | AG40: 3 | AH40: 2026 | AI40: =COUNTIF($I$177:$I$213,I40) -> 1 | AJ40: =COUNTIF($C$176:$C$210,C40) -> 1 | AK40: =COUNTIF($C$232:$C$266,C40) -> 1 | AL40: =_xlfn.DAYS(DATE(AH40,AG40*3-2,1),DATE(RIGHT(B40,4),MID(B40,4,2),LEFT(B40,2))) -> 324
B41: 11.08.2025 | C41: United states | D41: 950 | AI41: =COUNTIF($I$177:$I$213,I41) -> 0 | AJ41: =COUNTIF($C$176:$C$210,C41) -> 1 | AK41: =COUNTIF($C$232:$C$266,C41) -> 1 | AL41: =_xlfn.DAYS(DATE(AH41,AG41*3-2,1),DATE(RIGHT(B41,4),MID(B41,4,2),LEFT(B41,2))) -> #NUM!
B42: 02.09.2025 | C42: Germany | D42: 94 | E42: AOM4000 | F42: 20 | G42: Energiekontor AG | H42: 13 | I42: V162-7.2MW | J42: 162 | K42: 7.2 | AG42: 2 | AH42: 2027 | AI42: =COUNTIF($I$177:$I$213,I42) -> 1 | AJ42: =COUNTIF($C$176:$C$210,C42) -> 1 | AK42: =COUNTIF($C$232:$C$266,C42) -> 1 | AL42: =_xlfn.DAYS(DATE(AH42,AG42*3-2,1),DATE(RIGHT(B42,4),MID(B42,4,2),LEFT(B42,2))) -> 576
B43: 08.09.2025 | C43: Germany | D43: 86 | E43: AOM4000 | F43: 20 | G43: WestfalenWIND | H43: 12 | I43: V172-7.2MW | J43: 172 | K43: 7.2 | AG43: 3 | AH43: 2026 | AI43: =COUNTIF($I$177:$I$213,I43) -> 1 | AJ43: =COUNTIF($C$176:$C$210,C43) -> 1 | AK43: =COUNTIF($C$232:$C$266,C43) -> 1 | AL43: =_xlfn.DAYS(DATE(AH43,AG43*3-2,1),DATE(RIGHT(B43,4),MID(B43,4,2),LEFT(B43,2))) -> 296
B44: 12.09.2025 | C44: Argentina | D44: 217 | E44: AOM5000 | F44: 25 | H44: 29 | I44: V162-6.4MW | J44: 162 | K44: 6.4 | O44: 5 | P44: V162-6.2MW | Q44: 162 | R44: 6.2 | AG44: 3 | AH44: 2026 | AI44: =COUNTIF($I$177:$I$213,I44) -> 1 | AJ44: =COUNTIF($C$176:$C$210,C44) -> 1 | AK44: =COUNTIF($C$232:$C$266,C44) -> 1 | AL44: =_xlfn.DAYS(DATE(AH44,AG44*3-2,1),DATE(RIGHT(B44,4),MID(B44,4,2),LEFT(B44,2))) -> 292
B45: 19.09.2025 | C45: Germany | D45: 42 | E45: AOM4000 | F45: 25 | G45: Alterric Deutschland GmbH | H45: 7 | I45: V150-6.0MW | J45: 150 | K45: 6 | AG45: 2 | AH45: 2026 | AI45: =COUNTIF($I$177:$I$213,I45) -> 1 | AJ45: =COUNTIF($C$176:$C$210,C45) -> 1 | AK45: =COUNTIF($C$232:$C$266,C45) -> 1 | AL45: =_xlfn.DAYS(DATE(AH45,AG45*3-2,1),DATE(RIGHT(B45,4),MID(B45,4,2),LEFT(B45,2))) -> 194
B46: 23.09.2025 | C46: United states | D46: 320 | AI46: =COUNTIF($I$177:$I$213,I46) -> 0 | AJ46: =COUNTIF($C$176:$C$210,C46) -> 1 | AK46: =COUNTIF($C$232:$C$266,C46) -> 1 | AL46: =_xlfn.DAYS(DATE(AH46,AG46*3-2,1),DATE(RIGHT(B46,4),MID(B46,4,2),LEFT(B46,2))) -> #NUM!
B47: 29.09.2025 | C47: Spain | D47: 27 | E47: AOM5000 | H47: 6 | I47: V150-4.5MW | J47: 150 | K47: 4.5 | AG47: 1 | AH47: 2026 | AI47: =COUNTIF($I$177:$I$213,I47) -> 1 | AJ47: =COUNTIF($C$176:$C$210,C47) -> 1 | AK47: =COUNTIF($C$232:$C$266,C47) -> 1 | AL47: =_xlfn.DAYS(DATE(AH47,AG47*3-2,1),DATE(RIGHT(B47,4),MID(B47,4,2),LEFT(B47,2))) -> 94
B48: 29.09.2025 | C48: Greece | D48: 41 | E48: AOM5000 | F48: 20 | G48: CNI S. A | H48: 5 | I48: V135-4.5MW | J48: 135 | K48: 4.5 | O48: 4 | P48: V136-4.5MW | Q48: 136 | R48: 4.5 | AG48: 3 | AH48: 2026 | AI48: =COUNTIF($I$177:$I$213,I48) -> 1 | AJ48: =COUNTIF($C$176:$C$210,C48) -> 1 | AK48: =COUNTIF($C$232:$C$266,C48) -> 1 | AL48: =_xlfn.DAYS(DATE(AH48,AG48*3-2,1),DATE(RIGHT(B48,4),MID(B48,4,2),LEFT(B48,2))) -> 275
B49: 29.09.2025 | C49: Costa Rica | D49: 22 | E49: AOM4000 | F49: 8 | H49: 5 | I49: V117-4.3MW | J49: 117 | K49: 4.3 | AG49: 3 | AH49: 2026 | AI49: =COUNTIF($I$177:$I$213,I49) -> 1 | AJ49: =COUNTIF($C$176:$C$210,C49) -> 1 | AK49: =COUNTIF($C$232:$C$266,C49) -> 1 | AL49: =_xlfn.DAYS(DATE(AH49,AG49*3-2,1),DATE(RIGHT(B49,4),MID(B49,4,2),LEFT(B49,2))) -> 275
B50: 29.09.2025 | C50: South Korea | D50: 43 | E50: AOM5000 | F50: 20 | G50: Youngduk Wind Power | H50: 7 | I50: V162-6.2MW | J50: 162 | K50: 6.2 | AG50: 3 | AH50: 2026 | AI50: =COUNTIF($I$177:$I$213,I50) -> 1 | AJ50: =COUNTIF($C$176:$C$210,C50) -> 1 | AK50: =COUNTIF($C$232:$C$266,C50) -> 1 | AL50: =_xlfn.DAYS(DATE(AH50,AG50*3-2,1),DATE(RIGHT(B50,4),MID(B50,4,2),LEFT(B50,2))) -> 275
B51: 30.09.2025 | C51: Italy | D51: 22 | E51: AOM5000 | F51: 10 | H51: 4 | I51: V162-5.6MW | J51: 162 | K51: 5.6 | AG51: 2 | AH51: 2026 | AI51: =COUNTIF($I$177:$I$213,I51) -> 1 | AJ51: =COUNTIF($C$176:$C$210,C51) -> 1 | AK51: =COUNTIF($C$232:$C$266,C51) -> 1 | AL51: =_xlfn.DAYS(DATE(AH51,AG51*3-2,1),DATE(RIGHT(B51,4),MID(B51,4,2),LEFT(B51,2))) -> 183
B52: 30.09.2025 | C52: Italy | D52: 29 | E52: AOM4000 | F52: 10 | G52: Campana Energie Rinnovabili s.r.l. | H52: 4 | I52: V162-6.2MW | J52: 162 | K52: 6.2 | O52: 1 | P52: V150-4.5MW | Q52: 150 | R52: 4.5 | AG52: 2 | AH52: 2026 | AI52: =COUNTIF($I$177:$I$213,I52) -> 1 | AJ52: =COUNTIF($C$176:$C$210,C52) -> 1 | AK52: =COUNTIF($C$232:$C$266,C52) -> 1 | AL52: =_xlfn.DAYS(DATE(AH52,AG52*3-2,1),DATE(RIGHT(B52,4),MID(B52,4,2),LEFT(B52,2))) -> 183
B53: 30.09.2025 | C53: Italy | D53: 42 | E53: AOM5000 | H53: 7 | I53: V162-6.0MW | J53: 162 | K53: 6 | AG53: 2 | AH53: 2026 | AI53: =COUNTIF($I$177:$I$213,I53) -> 1 | AJ53: =COUNTIF($C$176:$C$210,C53) -> 1 | AK53: =COUNTIF($C$232:$C$266,C53) -> 1 | AL53: =_xlfn.DAYS(DATE(AH53,AG53*3-2,1),DATE(RIGHT(B53,4),MID(B53,4,2),LEFT(B53,2))) -> 183
B54: 30.09.2025 | C54: Germany | D54: 72 | E54: AOM5000 | F54: 20 | G54: Raiffeisen Windpark Saterland GmbH | H54: 10 | I54: V162-7.2MW | J54: 162 | K54: 7.2 | AG54: 3 | AH54: 2027 | AI54: =COUNTIF($I$177:$I$213,I54) -> 1 | AJ54: =COUNTIF($C$176:$C$210,C54) -> 1 | AK54: =COUNTIF($C$232:$C$266,C54) -> 1 | AL54: =_xlfn.DAYS(DATE(AH54,AG54*3-2,1),DATE(RIGHT(B54,4),MID(B54,4,2),LEFT(B54,2))) -> 639
B55: 30.09.2025 | C55: Germany | D55: 43 | E55: AOM5000 | F55: 20 | G55: Eurowind Energy A/S | H55: 7 | I55: V162-6.2MW | J55: 162 | K55: 6.2 | AG55: 1 | AH55: 2027 | AI55: =COUNTIF($I$177:$I$213,I55) -> 1 | AJ55: =COUNTIF($C$176:$C$210,C55) -> 1 | AK55: =COUNTIF($C$232:$C$266,C55) -> 1 | AL55: =_xlfn.DAYS(DATE(AH55,AG55*3-2,1),DATE(RIGHT(B55,4),MID(B55,4,2),LEFT(B55,2))) -> 458
B56: 30.09.2025 | C56: Germany | D56: 109 | E56: AOM4000 | F56: 20 | G56: Windstrom | H56: 7 | I56: V162-6.2MW | J56: 162 | K56: 6.2 | O56: 11 | P56: V150-6.0MW | Q56: 150 | R56: 6 | AG56: 3 | AH56: 2026 | AI56: =COUNTIF($I$177:$I$213,I56) -> 1 | AJ56: =COUNTIF($C$176:$C$210,C56) -> 1 | AK56: =COUNTIF($C$232:$C$266,C56) -> 1 | AL56: =_xlfn.DAYS(DATE(AH56,AG56*3-2,1),DATE(RIGHT(B56,4),MID(B56,4,2),LEFT(B56,2))) -> 274
B57: 30.09.2025 | C57: Denmark | D57: 59 | E57: AOM5000 | F57: 25 | H57: 13 | I57: V136-4.5MW | J57: 136 | K57: 4.5 | AG57: 3 | AH57: 2026 | AI57: =COUNTIF($I$177:$I$213,I57) -> 1 | AJ57: =COUNTIF($C$176:$C$210,C57) -> 1 | AK57: =COUNTIF($C$232:$C$266,C57) -> 1 | AL57: =_xlfn.DAYS(DATE(AH57,AG57*3-2,1),DATE(RIGHT(B57,4),MID(B57,4,2),LEFT(B57,2))) -> 274
B58: 30.09.2025 | C58: UK | D58: 63 | E58: AOM5000 | F58: 30 | G58: Vatteltall | H58: 14 | I58: V136-4.5MW | J58: 136 | K58: 4.5 | AG58: 2 | AH58: 2027 | AI58: =COUNTIF($I$177:$I$213,I58) -> 1 | AJ58: =COUNTIF($C$176:$C$210,C58) -> 1 | AK58: =COUNTIF($C$232:$C$266,C58) -> 1 | AL58: =_xlfn.DAYS(DATE(AH58,AG58*3-2,1),DATE(RIGHT(B58,4),MID(B58,4,2),LEFT(B58,2))) -> 548
B59: 30.09.2025 | C59: Germany | D59: 58 | E59: AOM5000 | F59: 20 | G59: BBWind | H59: 8 | I59: V172-7.2MW | J59: 172 | K59: 7.2 | AG59: 4 | AH59: 2026 | AI59: =COUNTIF($I$177:$I$213,I59) -> 1 | AJ59: =COUNTIF($C$176:$C$210,C59) -> 1 | AK59: =COUNTIF($C$232:$C$266,C59) -> 1 | AL59: =_xlfn.DAYS(DATE(AH59,AG59*3-2,1),DATE(RIGHT(B59,4),MID(B59,4,2),LEFT(B59,2))) -> 366
B60: 30.09.2025 | C60: Germany | D60: 44 | E60: AOM5000 | F60: 20 | G60: BBWind | H60: 1 | I60: V172-7.2MW | J60: 172 | K60: 7.2 | O60: 6 | P60: V162-6.2MW | Q60: 162 | R60: 6.2 | AG60: 1 | AH60: 2027 | AI60: =COUNTIF($I$177:$I$213,I60) -> 1 | AJ60: =COUNTIF($C$176:$C$210,C60) -> 1 | AK60: =COUNTIF($C$232:$C$266,C60) -> 1 | AL60: =_xlfn.DAYS(DATE(AH60,AG60*3-2,1),DATE(RIGHT(B60,4),MID(B60,4,2),LEFT(B60,2))) -> 458
B61: 30.09.2025 | C61: Germany | D61: 22 | E61: AOM5000 | F61: 20 | G61: BBWind | H61: 3 | I61: V172-7.2MW | J61: 172 | K61: 7.2 | AG61: 1 | AH61: 2027 | AI61: =COUNTIF($I$177:$I$213,I61) -> 1 | AJ61: =COUNTIF($C$176:$C$210,C61) -> 1 | AK61: =COUNTIF($C$232:$C$266,C61) -> 1 | AL61: =_xlfn.DAYS(DATE(AH61,AG61*3-2,1),DATE(RIGHT(B61,4),MID(B61,4,2),LEFT(B61,2))) -> 458
B62: 30.09.2025 | C62: Germany | D62: 36 | E62: AOM5000 | F62: 20 | G62: BBWind | H62: 5 | I62: V172-7.2MW | J62: 172 | K62: 7.2 | AG62: 4 | AH62: 2027 | AI62: =COUNTIF($I$177:$I$213,I62) -> 1 | AJ62: =COUNTIF($C$176:$C$210,C62) -> 1 | AK62: =COUNTIF($C$232:$C$266,C62) -> 1 | AL62: =_xlfn.DAYS(DATE(AH62,AG62*3-2,1),DATE(RIGHT(B62,4),MID(B62,4,2),LEFT(B62,2))) -> 731
B63: 30.09.2025 | C63: Germany | D63: 29 | E63: AOM5000 | F63: 20 | G63: BBWind | H63: 4 | I63: V172-7.2MW | J63: 172 | K63: 7.2 | AG63: 4 | AH63: 2027 | AI63: =COUNTIF($I$177:$I$213,I63) -> 1 | AJ63: =COUNTIF($C$176:$C$210,C63) -> 1 | AK63: =COUNTIF($C$232:$C$266,C63) -> 1 | AL63: =_xlfn.DAYS(DATE(AH63,AG63*3-2,1),DATE(RIGHT(B63,4),MID(B63,4,2),LEFT(B63,2))) -> 731
B64: 30.09.2025 | C64: Germany | D64: 22 | E64: AOM5000 | F64: 20 | G64: BBWind | H64: 3 | I64: V172-7.2MW | J64: 172 | K64: 7.2 | AG64: 1 | AH64: 2027 | AI64: =COUNTIF($I$177:$I$213,I64) -> 1 | AJ64: =COUNTIF($C$176:$C$210,C64) -> 1 | AK64: =COUNTIF($C$232:$C$266,C64) -> 1 | AL64: =_xlfn.DAYS(DATE(AH64,AG64*3-2,1),DATE(RIGHT(B64,4),MID(B64,4,2),LEFT(B64,2))) -> 458
B65: 30.09.2025 | C65: Germany | D65: 22 | E65: AOM5000 | F65: 20 | G65: BBWind | H65: 3 | I65: V172-7.2MW | J65: 172 | K65: 7.2 | AG65: 4 | AH65: 2027 | AI65: =COUNTIF($I$177:$I$213,I65) -> 1 | AJ65: =COUNTIF($C$176:$C$210,C65) -> 1 | AK65: =COUNTIF($C$232:$C$266,C65) -> 1 | AL65: =_xlfn.DAYS(DATE(AH65,AG65*3-2,1),DATE(RIGHT(B65,4),MID(B65,4,2),LEFT(B65,2))) -> 731
A66: =SUM(D33:D66) -> 4003 | B66: 30.09.2025 | C66: Germany | D66: 7 | E66: AOM4000 | F66: 20 | G66: BBWind | H66: 1 | I66: V172-7.2MW | J66: 172 | K66: 7.2 | AG66: 1 | AH66: 2027 | AI66: =COUNTIF($I$177:$I$213,I66) -> 1 | AJ66: =COUNTIF($C$176:$C$210,C66) -> 1 | AK66: =COUNTIF($C$232:$C$266,C66) -> 1 | AL66: =_xlfn.DAYS(DATE(AH66,AG66*3-2,1),DATE(RIGHT(B66,4),MID(B66,4,2),LEFT(B66,2))) -> 458
B67: 04.11.2025 | C67: Germany | D67: 72 | E67: AOM5000 | F67: 25 | G67: Enertrag SE | H67: 10 | I67: V172-7.2MW | J67: 172 | K67: 7.2 | AG67: 3 | AH67: 2026 | AI67: =COUNTIF($I$177:$I$213,I67) -> 1 | AJ67: =COUNTIF($C$176:$C$210,C67) -> 1 | AK67: =COUNTIF($C$232:$C$266,C67) -> 1 | AL67: =_xlfn.DAYS(DATE(AH67,AG67*3-2,1),DATE(RIGHT(B67,4),MID(B67,4,2),LEFT(B67,2))) -> 239
B68: 04.11.2025 | C68: Germany | D68: 50 | E68: AOM4000 | F68: 20 | G68: Windpark Niederlungwitz Struktur GmbH | H68: 8 | I68: V162-6.2MW | J68: 162 | K68: 6.2 | AG68: 3 | AH68: 2026 | AI68: =COUNTIF($I$177:$I$213,I68) -> 1 | AJ68: =COUNTIF($C$176:$C$210,C68) -> 1 | AK68: =COUNTIF($C$232:$C$266,C68) -> 1 | AL68: =_xlfn.DAYS(DATE(AH68,AG68*3-2,1),DATE(RIGHT(B68,4),MID(B68,4,2),LEFT(B68,2))) -> 239
B69: 04.11.2025 | C69: Germany | D69: 48 | E69: AOM4000 | F69: 25 | G69: Energiekontor AG & Loscon | H69: 8 | I69: V150-6.0MW | J69: 150 | K69: 6 | AG69: 1 | AH69: 2027 | AI69: =COUNTIF($I$177:$I$213,I69) -> 1 | AJ69: =COUNTIF($C$176:$C$210,C69) -> 1 | AK69: =COUNTIF($C$232:$C$266,C69) -> 1 | AL69: =_xlfn.DAYS(DATE(AH69,AG69*3-2,1),DATE(RIGHT(B69,4),MID(B69,4,2),LEFT(B69,2))) -> 423
B70: 04.11.2025 | C70: Italy | D70: 30 | E70: AOM5000 | F70: 20 | G70: PLT | H70: 5 | I70: V162-6.0MW | J70: 162 | K70: 6 | AG70: 4 | AH70: 2026 | AI70: =COUNTIF($I$177:$I$213,I70) -> 1 | AJ70: =COUNTIF($C$176:$C$210,C70) -> 1 | AK70: =COUNTIF($C$232:$C$266,C70) -> 1 | AL70: =_xlfn.DAYS(DATE(AH70,AG70*3-2,1),DATE(RIGHT(B70,4),MID(B70,4,2),LEFT(B70,2))) -> 331
B71: 07.11.2025 | C71: United states and Canada | D71: 347 | AI71: =COUNTIF($I$177:$I$213,I71) -> 0 | AJ71: =COUNTIF($C$176:$C$210,C71) -> 1 | AK71: =COUNTIF($C$232:$C$266,C71) -> 1 | AL71: =_xlfn.DAYS(DATE(AH71,AG71*3-2,1),DATE(RIGHT(B71,4),MID(B71,4,2),LEFT(B71,2))) -> #NUM!
B72: 01.12.2025 | C72: EU | D72: 660 | AI72: =COUNTIF($I$177:$I$213,I72) -> 0 | AJ72: =COUNTIF($C$176:$C$210,C72) -> 0 | AK72: =COUNTIF($C$232:$C$266,C72) -> 1 | AL72: =_xlfn.DAYS(DATE(AH72,AG72*3-2,1),DATE(RIGHT(B72,4),MID(B72,4,2),LEFT(B72,2))) -> #NUM!
B73: 05.12.2025 | C73: Italy | D73: 10 | E73: AOM4000 | F73: 10 | G73: Cementeria Costantinopoli Srl | H73: 3 | I73: V117-3.45MW | J73: 117 | K73: 3.45 | AG73: 4 | AH73: 2026 | AI73: =COUNTIF($I$177:$I$213,I73) -> 1 | AJ73: =COUNTIF($C$176:$C$210,C73) -> 1 | AK73: =COUNTIF($C$232:$C$266,C73) -> 1 | AL73: =_xlfn.DAYS(DATE(AH73,AG73*3-2,1),DATE(RIGHT(B73,4),MID(B73,4,2),LEFT(B73,2))) -> 300
B74: 11.12.2025 | C74: Germany | D74: 79 | E74: AOM5000 | F74: 25 | G74: Uhl Windkraft | H74: 11 | I74: V172-7.2MW | J74: 172 | K74: 7.2 | AI74: =COUNTIF($I$177:$I$213,I74) -> 1 | AJ74: =COUNTIF($C$176:$C$210,C74) -> 1 | AK74: =COUNTIF($C$232:$C$266,C74) -> 1 | AL74: =_xlfn.DAYS(DATE(AH74,AG74*3-2,1),DATE(RIGHT(B74,4),MID(B74,4,2),LEFT(B74,2))) -> #NUM!
B75: 11.12.2025 | C75: Germany | D75: 80 | E75: AOM4000 | F75: 15 | G75: wpd GmbH | H75: 11 | I75: V162-6.2MW | J75: 162 | K75: 6.2 | O75: 2 | P75: V150-6.0MW | Q75: 150 | R75: 6 | AI75: =COUNTIF($I$177:$I$213,I75) -> 1 | AJ75: =COUNTIF($C$176:$C$210,C75) -> 1 | AK75: =COUNTIF($C$232:$C$266,C75) -> 1 | AL75: =_xlfn.DAYS(DATE(AH75,AG75*3-2,1),DATE(RIGHT(B75,4),MID(B75,4,2),LEFT(B75,2))) -> #NUM!
B76: 11.12.2025 | C76: Poland | D76: 32 | E76: AOM5000 | F76: 20 | G76: FW LUBIEŃ 1 SP. Z o.o. /Greenvolt Power Group Sp. z o.o. | H76: 8 | I76: V150-4.0MW | J76: 150 | K76: 4 | AI76: =COUNTIF($I$177:$I$213,I76) -> 0 | AJ76: =COUNTIF($C$176:$C$210,C76) -> 1 | AK76: =COUNTIF($C$232:$C$266,C76) -> 1 | AL76: =_xlfn.DAYS(DATE(AH76,AG76*3-2,1),DATE(RIGHT(B76,4),MID(B76,4,2),LEFT(B76,2))) -> #NUM!
B77: 15.12.2025 | C77: Finland | D77: 124 | E77: AOM5000 | F77: 25 | G77: OX2 AB | H77: 20 | I77: V162-6.2MW | J77: 162 | K77: 6.2 | AG77: 2 | AH77: 2027 | AI77: =COUNTIF($I$177:$I$213,I77) -> 1 | AJ77: =COUNTIF($C$176:$C$210,C77) -> 1 | AK77: =COUNTIF($C$232:$C$266,C77) -> 1 | AL77: =_xlfn.DAYS(DATE(AH77,AG77*3-2,1),DATE(RIGHT(B77,4),MID(B77,4,2),LEFT(B77,2))) -> 472
B78: 15.12.2025 | C78: Finland | D78: 108 | E78: AOM5000 | F78: 25 | G78: OX2 AB | H78: 15 | I78: V162-6.4MW | J78: 162 | K78: 6.4 | O78: 2 | P78: V162-6.2MW | Q78: 162 | R78: 6.2 | AG78: 2 | AH78: 2027 | AI78: =COUNTIF($I$177:$I$213,I78) -> 1 | AJ78: =COUNTIF($C$176:$C$210,C78) -> 1 | AK78: =COUNTIF($C$232:$C$266,C78) -> 1 | AL78: =_xlfn.DAYS(DATE(AH78,AG78*3-2,1),DATE(RIGHT(B78,4),MID(B78,4,2),LEFT(B78,2))) -> 472
B79: 15.12.2025 | C79: Finland | D79: 45 | E79: AOM5000 | F79: 25 | G79: OX2 AB | H79: 7 | I79: V162-6.4MW | J79: 162 | K79: 6.4 | AG79: 2 | AH79: 2027 | AI79: =COUNTIF($I$177:$I$213,I79) -> 1 | AJ79: =COUNTIF($C$176:$C$210,C79) -> 1 | AK79: =COUNTIF($C$232:$C$266,C79) -> 1 | AL79: =_xlfn.DAYS(DATE(AH79,AG79*3-2,1),DATE(RIGHT(B79,4),MID(B79,4,2),LEFT(B79,2))) -> 472
B80: 17.12.2025 | C80: Brazil | D80: 828 | E80: AOM5000 | F80: 25 | G80: Casa dos Ventos | H80: 184 | I80: V150-4.5MW | J80: 150 | K80: 4.5 | AG80: 3 | AH80: 2026 | AI80: =COUNTIF($I$177:$I$213,I80) -> 1 | AJ80: =COUNTIF($C$176:$C$210,C80) -> 1 | AK80: =COUNTIF($C$232:$C$266,C80) -> 1 | AL80: =_xlfn.DAYS(DATE(AH80,AG80*3-2,1),DATE(RIGHT(B80,4),MID(B80,4,2),LEFT(B80,2))) -> 196
B81: 17.12.2025 | C81: Australia | D81: 108 | F81: 30 | G81: Tilt Renewables | H81: 18 | I81: V162-6.0MW | J81: 162 | K81: 6 | AG81: 1 | AH81: 2027 | AI81: =COUNTIF($I$177:$I$213,I81) -> 1 | AJ81: =COUNTIF($C$176:$C$210,C81) -> 1 | AK81: =COUNTIF($C$232:$C$266,C81) -> 1 | AL81: =_xlfn.DAYS(DATE(AH81,AG81*3-2,1),DATE(RIGHT(B81,4),MID(B81,4,2),LEFT(B81,2))) -> 380
B82: 19.12.2025 | C82: Australia | D82: 205 | E82: AOM5000 | F82: 30 | H82: 33 | I82: V162-6.2MW | J82: 162 | K82: 6.2 | AG82: 1 | AH82: 2027 | AI82: =COUNTIF($I$177:$I$213,I82) -> 1 | AJ82: =COUNTIF($C$176:$C$210,C82) -> 1 | AK82: =COUNTIF($C$232:$C$266,C82) -> 1 | AL82: =_xlfn.DAYS(DATE(AH82,AG82*3-2,1),DATE(RIGHT(B82,4),MID(B82,4,2),LEFT(B82,2))) -> 378
B83: 22.12.2025 | C83: United states | D83: 320 | AI83: =COUNTIF($I$177:$I$213,I83) -> 0 | AJ83: =COUNTIF($C$176:$C$210,C83) -> 1 | AK83: =COUNTIF($C$232:$C$266,C83) -> 1 | AL83: =_xlfn.DAYS(DATE(AH83,AG83*3-2,1),DATE(RIGHT(B83,4),MID(B83,4,2),LEFT(B83,2))) -> #NUM!
B84: 23.12.2025 | C84: Germany | D84: 43 | E84: AOM5000 | F84: 20 | G84: Windkraft Presen-Burgstaaken GmbH & Co. KG | H84: 7 | I84: V162-6.2MW | J84: 162 | K84: 6.2 | AG84: 1 | AH84: 2027 | AI84: =COUNTIF($I$177:$I$213,I84) -> 1 | AJ84: =COUNTIF($C$176:$C$210,C84) -> 1 | AK84: =COUNTIF($C$232:$C$266,C84) -> 1 | AL84: =_xlfn.DAYS(DATE(AH84,AG84*3-2,1),DATE(RIGHT(B84,4),MID(B84,4,2),LEFT(B84,2))) -> 374
B85: 23.12.2025 | C85: Germany | D85: 49 | E85: AOM5000 | F85: 20 | G85: Projekt Projektierungsgesellschaft für regenerative Energiesysteme mbH | H85: 6 | I85: V162-7.2MW | J85: 162 | K85: 7.2 | O85: 1 | P85: V150-5.6MW | Q85: 150 | R85: 5.6 | AG85: 2 | AH85: 2027 | AI85: =COUNTIF($I$177:$I$213,I85) -> 1 | AJ85: =COUNTIF($C$176:$C$210,C85) -> 1 | AK85: =COUNTIF($C$232:$C$266,C85) -> 1 | AL85: =_xlfn.DAYS(DATE(AH85,AG85*3-2,1),DATE(RIGHT(B85,4),MID(B85,4,2),LEFT(B85,2))) -> 464
B86: 23.12.2025 | C86: Germany | D86: 48 | E86: AOM4000 | F86: 25 | G86: iterra energy GmbH | H86: 8 | I86: V150-6.0MW | J86: 150 | K86: 6 | AG86: 1 | AH86: 2027 | AI86: =COUNTIF($I$177:$I$213,I86) -> 1 | AJ86: =COUNTIF($C$176:$C$210,C86) -> 1 | AK86: =COUNTIF($C$232:$C$266,C86) -> 1 | AL86: =_xlfn.DAYS(DATE(AH86,AG86*3-2,1),DATE(RIGHT(B86,4),MID(B86,4,2),LEFT(B86,2))) -> 374
B87: 23.12.2025 | C87: Germany | D87: 24 | E87: AOM4000 | F87: 25 | G87: iterra energy GmbH | H87: 4 | I87: V150-6.0 MW | AG87: 2 | AH87: 2027 | AI87: =COUNTIF($I$177:$I$213,I87) -> 1 | AJ87: =COUNTIF($C$176:$C$210,C87) -> 1 | AK87: =COUNTIF($C$232:$C$266,C87) -> 1 | AL87: =_xlfn.DAYS(DATE(AH87,AG87*3-2,1),DATE(RIGHT(B87,4),MID(B87,4,2),LEFT(B87,2))) -> 464
B88: 23.12.2025 | C88: Germany | D88: 38 | E88: AOM4000 | F88: 25 | G88: JUWI GmbH | H88: 5 | I88: V162-6.2MW | O88: 1 | P88: V162-7.2 MW | Q88: 162 | R88: 7.2 | AG88: 1 | AH88: 2027 | AI88: =COUNTIF($I$177:$I$213,I88) -> 1 | AJ88: =COUNTIF($C$176:$C$210,C88) -> 1 | AK88: =COUNTIF($C$232:$C$266,C88) -> 1 | AL88: =_xlfn.DAYS(DATE(AH88,AG88*3-2,1),DATE(RIGHT(B88,4),MID(B88,4,2),LEFT(B88,2))) -> 374
B89: 23.12.2025 | C89: Germany | D89: 25 | E89: AOM4000 | F89: 20 | G89: JUWI GmbH | H89: 4 | I89: V162-6.2MW | AG89: 2 | AH89: 2027 | AI89: =COUNTIF($I$177:$I$213,I89) -> 1 | AJ89: =COUNTIF($C$176:$C$210,C89) -> 1 | AK89: =COUNTIF($C$232:$C$266,C89) -> 1 | AL89: =_xlfn.DAYS(DATE(AH89,AG89*3-2,1),DATE(RIGHT(B89,4),MID(B89,4,2),LEFT(B89,2))) -> 464
B90: 23.12.2025 | C90: Germany | D90: 46 | E90: AOM4000 | F90: 20 | H90: 3 | I90: V172-7.2MW | O90: 3 | P90: V162-6.2 MW | Q90: 162 | R90: 6.2 | AI90: =COUNTIF($I$177:$I$213,I90) -> 1 | AJ90: =COUNTIF($C$176:$C$210,C90) -> 1 | AK90: =COUNTIF($C$232:$C$266,C90) -> 1 | AL90: =_xlfn.DAYS(DATE(AH90,AG90*3-2,1),DATE(RIGHT(B90,4),MID(B90,4,2),LEFT(B90,2))) -> #NUM!
B91: 29.12.2025 | C91: South Korea | D91: 390 | F91: 20 | G91: Shinan-Ui | H91: 26 | I91: V236-15.0MW | J91: 236 | K91: 15 | AG91: 3 | AH91: 2027 | AI91: =COUNTIF($I$177:$I$213,I91) -> 1 | AJ91: =COUNTIF($C$176:$C$210,C91) -> 1 | AK91: =COUNTIF($C$232:$C$266,C91) -> 1 | AL91: =_xlfn.DAYS(DATE(AH91,AG91*3-2,1),DATE(RIGHT(B91,4),MID(B91,4,2),LEFT(B91,2))) -> 549
B92: 29.12.2025 | C92: Ireland | D92: 99 | E92: AOM5000 | F92: 20 | H92: 22 | I92: V136-4.5MW | J92: 136 | K92: 4.5 | AG92: 1 | AH92: 2027 | AI92: =COUNTIF($I$177:$I$213,I92) -> 1 | AJ92: =COUNTIF($C$176:$C$210,C92) -> 1 | AK92: =COUNTIF($C$232:$C$266,C92) -> 1 | AL92: =_xlfn.DAYS(DATE(AH92,AG92*3-2,1),DATE(RIGHT(B92,4),MID(B92,4,2),LEFT(B92,2))) -> 368
B93: 29.12.2025 | C93: Ireland | D93: 47 | H93: 11 | I93: V117-4.3MW | J93: 117 | K93: 4.3 | AI93: =COUNTIF($I$177:$I$213,I93) -> 1 | AJ93: =COUNTIF($C$176:$C$210,C93) -> 1 | AK93: =COUNTIF($C$232:$C$266,C93) -> 1 | AL93: =_xlfn.DAYS(DATE(AH93,AG93*3-2,1),DATE(RIGHT(B93,4),MID(B93,4,2),LEFT(B93,2))) -> #NUM!
B94: 29.12.2025 | C94: Ireland | D94: 42 | E94: AOM5000 | F94: 20 | G94: Invis Energy | H94: 7 | I94: V150-6.0MW | J94: 150 | K94: 6 | AG94: 3 | AH94: 2026 | AI94: =COUNTIF($I$177:$I$213,I94) -> 1 | AJ94: =COUNTIF($C$176:$C$210,C94) -> 1 | AK94: =COUNTIF($C$232:$C$266,C94) -> 1 | AL94: =_xlfn.DAYS(DATE(AH94,AG94*3-2,1),DATE(RIGHT(B94,4),MID(B94,4,2),LEFT(B94,2))) -> 184
B95: 29.12.2025 | C95: Italy | D95: 125 | E95: AOM5000 | G95: ERG | H95: 18 | I95: V163-4.5MW | J95: 163 | K95: 4.5 | O95: 6 | P95: V136-4.5MW | Q95: 136 | R95: 4.5 | U95: 4 | V95: V117-4.2MW | W95: 117 | X95: 4.2 | AG95: 3 | AH95: 2026 | AI95: =COUNTIF($I$177:$I$213,I95) -> 1 | AJ95: =COUNTIF($C$176:$C$210,C95) -> 1 | AK95: =COUNTIF($C$232:$C$266,C95) -> 1 | AL95: =_xlfn.DAYS(DATE(AH95,AG95*3-2,1),DATE(RIGHT(B95,4),MID(B95,4,2),LEFT(B95,2))) -> 184
B96: 29.12.2025 | C96: Spain | D96: 88 | E96: AOM4000 | F96: 20 | G96: Capital Energy | H96: 4 | I96: V162-6.2MW | J96: 162 | K96: 6.2 | O96: 9 | P96: V163-4.5MW | Q96: 163 | R96: 4.5 | U96: 5 | V96: V150-4.5MW | W96: 150 | X96: 4.5 | AG96: 1 | AH96: 2027 | AI96: =COUNTIF($I$177:$I$213,I96) -> 1 | AJ96: =COUNTIF($C$176:$C$210,C96) -> 1 | AK96: =COUNTIF($C$232:$C$266,C96) -> 1 | AL96: =_xlfn.DAYS(DATE(AH96,AG96*3-2,1),DATE(RIGHT(B96,4),MID(B96,4,2),LEFT(B96,2))) -> 368
B97: 29.12.2025 | C97: Portugal | D97: 45 | E97: AOM5000 | G97: Saeta | H97: 10 | I97: V163-4.5MW | J97: 163 | K97: 4.5 | AG97: 4 | AH97: 2026 | AI97: =COUNTIF($I$177:$I$213,I97) -> 1 | AJ97: =COUNTIF($C$176:$C$210,C97) -> 1 | AK97: =COUNTIF($C$232:$C$266,C97) -> 1 | AL97: =_xlfn.DAYS(DATE(AH97,AG97*3-2,1),DATE(RIGHT(B97,4),MID(B97,4,2),LEFT(B97,2))) -> 276
B98: 29.12.2025 | C98: Portugal | D98: 32 | E98: AOM4000 | F98: 20 | G98: Hyperion | H98: 7 | I98: V163-4.5MW | J98: 163 | K98: 4.5 | AG98: 1 | AH98: 2027 | AI98: =COUNTIF($I$177:$I$213,I98) -> 1 | AJ98: =COUNTIF($C$176:$C$210,C98) -> 1 | AK98: =COUNTIF($C$232:$C$266,C98) -> 1 | AL98: =_xlfn.DAYS(DATE(AH98,AG98*3-2,1),DATE(RIGHT(B98,4),MID(B98,4,2),LEFT(B98,2))) -> 368
B99: 30.12.2025 | C99: South Korea | D99: 43 | E99: AOM5000 | F99: 20 | G99: DaeMyoung Energy Co., Ltd | H99: 7 | I99: V162-6.2MW | J99: 162 | K99: 6.2 | AG99: 3 | AH99: 2027 | AI99: =COUNTIF($I$177:$I$213,I99) -> 1 | AJ99: =COUNTIF($C$176:$C$210,C99) -> 1 | AK99: =COUNTIF($C$232:$C$266,C99) -> 1 | AL99: =_xlfn.DAYS(DATE(AH99,AG99*3-2,1),DATE(RIGHT(B99,4),MID(B99,4,2),LEFT(B99,2))) -> 548
B100: 30.12.2025 | C100: Italy | D100: 102 | F100: 10 | G100: Edison | H100: 12 | I100: V150-4.5MW | J100: 150 | K100: 4.5 | O100: 5 | P100: V150-5.6MW | Q100: 150 | R100: 5.6 | U100: 4 | V100: V136-4.5MW | W100: 136 | X100: 4.5 | AG100: 4 | AH100: 2026 | AI100: =COUNTIF($I$177:$I$213,I100) -> 1 | AJ100: =COUNTIF($C$176:$C$210,C100) -> 1 | AK100: =COUNTIF($C$232:$C$266,C100) -> 1 | AL100: =_xlfn.DAYS(DATE(AH100,AG100*3-2,1),DATE(RIGHT(B100,4),MID(B100,4,2),LEFT(B100,2))) -> 275
...

Sheet OI 2024
B1: date | C1: country | D1: size [MW] | E1: Service scheme | F1: Service time [years] | G1: customer | H1: # | I1: platform | J1: Rotor | K1: MW | L1: special mode | M1: Tower height | N1: Multi towerH | O1: # | P1: Multi platform | Q1: Rotor | R1: MW | S1: special mode | T1: Tower height | U1: # | V1: Multi platform | W1: Rotor | X1: MW | Y1: Tower height | Z1: Note | AA1: # | AB1: Multi platform | AC1: Rotor | AD1: MW | AE1: Tower height | AF1: Note | AG1: delivery q | AH1: delivery y | AI1: platform check | AJ1: country check | AL1: Delivery days
B2: 10.02.2024 | C2: Italy | D2: 63 | E2: AOM5000 | F2: 10 | H2: 14 | I2: V150-4.5MW | J2: 150 | K2: 4.5 | AG2: 2 | AH2: 2025 | AI2: =COUNTIF($I$177:$I$208,I2) -> 1 | AJ2: =COUNTIF($C$176:$C$205,C2) -> 1 | AK2: =COUNTIF($C$232:$C$270,C2) -> 1 | AL2: =_xlfn.DAYS(DATE(AH2,AG2*3-2,1),DATE(RIGHT(B2,4),MID(B2,4,2),LEFT(B2,2))) -> 416
B3: 26.02.2024 | C3: United states | D3: 153 | E3: AOM5000 | H3: 34 | I3: V150-4.5MW | J3: 150 | K3: 4.5 | AG3: 4 | AH3: 2026 | AI3: =COUNTIF($I$177:$I$208,I3) -> 1 | AJ3: =COUNTIF($C$176:$C$205,C3) -> 1 | AK3: =COUNTIF($C$232:$C$270,C3) -> 1 | AL3: =_xlfn.DAYS(DATE(AH3,AG3*3-2,1),DATE(RIGHT(B3,4),MID(B3,4,2),LEFT(B3,2))) -> 948
B4: 05.03.2024 | C4: Germany | D4: 65 | E4: AOM5000 | F4: 25 | G4: Enova Power | H4: 9 | I4: V172-7.2MW | J4: 172 | K4: 7.2 | AG4: 4 | AH4: 2025 | AI4: =COUNTIF($I$177:$I$208,I4) -> 1 | AJ4: =COUNTIF($C$176:$C$205,C4) -> 1 | AK4: =COUNTIF($C$232:$C$270,C4) -> 1 | AL4: =_xlfn.DAYS(DATE(AH4,AG4*3-2,1),DATE(RIGHT(B4,4),MID(B4,4,2),LEFT(B4,2))) -> 575
B5: 08.03.2024 | C5: Denmark | D5: 15 | E5: AOM4000 | F5: 20 | G5: Thyborøn-Harboøre | H5: 1 | I5: V236-15.0MW | J5: 236 | K5: 15 | AF5: 2800 local share holders | AG5: 2 | AH5: 2024 | AI5: =COUNTIF($I$177:$I$208,I5) -> 1 | AJ5: =COUNTIF($C$176:$C$205,C5) -> 1 | AK5: =COUNTIF($C$232:$C$270,C5) -> 1 | AL5: =_xlfn.DAYS(DATE(AH5,AG5*3-2,1),DATE(RIGHT(B5,4),MID(B5,4,2),LEFT(B5,2))) -> 24
B6: 14.03.2024 | C6: Mexico | D6: 319 | E6: AOM5000 | F6: 10 | G6: Sempra | H6: 46 | I6: V163-4.5MW | J6: 163 | K6: 4.5 | O6: 18 | P6: V162-6.2MW | Q6: 162 | R6: 6.2 | AG6: 4 | AH6: 2024 | AI6: =COUNTIF($I$177:$I$208,I6) -> 1 | AJ6: =COUNTIF($C$176:$C$205,C6) -> 1 | AK6: =COUNTIF($C$232:$C$270,C6) -> 1 | AL6: =_xlfn.DAYS(DATE(AH6,AG6*3-2,1),DATE(RIGHT(B6,4),MID(B6,4,2),LEFT(B6,2))) -> 201
B7: 19.03.2024 | C7: Spain | D7: 51 | E7: AOM5000 | F7: 20 | G7: ENHOL | H7: 8 | I7: V162-6.2MW | J7: 162 | K7: 6.2 | L7: opt 6.4 | AG7: 4 | AH7: 2024 | AI7: =COUNTIF($I$177:$I$208,I7) -> 1 | AJ7: =COUNTIF($C$176:$C$205,C7) -> 1 | AK7: =COUNTIF($C$232:$C$270,C7) -> 1 | AL7: =_xlfn.DAYS(DATE(AH7,AG7*3-2,1),DATE(RIGHT(B7,4),MID(B7,4,2),LEFT(B7,2))) -> 196
B8: 27.03.2024 | C8: Poland | D8: 37 | E8: AOM5000 | F8: 25 | G8: Energa Green Development | H8: 17 | I8: V110-2.0MW | J8: 110 | K8: 2.2 | L8: opt 2.2 | AG8: 3 | AH8: 2025 | AI8: =COUNTIF($I$177:$I$208,I8) -> 1 | AJ8: =COUNTIF($C$176:$C$205,C8) -> 1 | AK8: =COUNTIF($C$232:$C$270,C8) -> 1 | AL8: =_xlfn.DAYS(DATE(AH8,AG8*3-2,1),DATE(RIGHT(B8,4),MID(B8,4,2),LEFT(B8,2))) -> 461
B9: 29.03.2024 | C9: Sweden | D9: 88 | E9: AOM5000 | G9: Eolus | H9: 11 | I9: V162-6.2MW | J9: 162 | K9: 6.4 | L9: opt 6.4 | O9: 4 | P9: V150-4.5MW | Q9: 150 | R9: 4.5 | AG9: 1 | AH9: 2025 | AI9: =COUNTIF($I$177:$I$208,I9) -> 1 | AJ9: =COUNTIF($C$176:$C$205,C9) -> 1 | AK9: =COUNTIF($C$232:$C$270,C9) -> 1 | AL9: =_xlfn.DAYS(DATE(AH9,AG9*3-2,1),DATE(RIGHT(B9,4),MID(B9,4,2),LEFT(B9,2))) -> 278
B10: 29.03.2024 | C10: South Korea | D10: 77 | G10: GS E&R | H10: 18 | I10: V136-4.2MW | J10: 136 | K10: 4.3 | L10: opt 4.3 | AG10: 1 | AH10: 2025 | AI10: =COUNTIF($I$177:$I$208,I10) -> 1 | AJ10: =COUNTIF($C$176:$C$205,C10) -> 1 | AK10: =COUNTIF($C$232:$C$270,C10) -> 1 | AL10: =_xlfn.DAYS(DATE(AH10,AG10*3-2,1),DATE(RIGHT(B10,4),MID(B10,4,2),LEFT(B10,2))) -> 278
B11: 29.03.2024 | C11: Italy | D11: 81 | F11: 10 | G11: Edison Rinnovabili | H11: 18 | I11: V136-4.5MW | J11: 136 | K11: 4.5 | AG11: 2 | AH11: 2025 | AI11: =COUNTIF($I$177:$I$208,I11) -> 1 | AJ11: =COUNTIF($C$176:$C$205,C11) -> 1 | AK11: =COUNTIF($C$232:$C$270,C11) -> 1 | AL11: =_xlfn.DAYS(DATE(AH11,AG11*3-2,1),DATE(RIGHT(B11,4),MID(B11,4,2),LEFT(B11,2))) -> 368
A12: =SUM(D2:D12) -> 1503 | B12: 29.03.2024 | C12: United states | D12: 554 | E12: AOM5000 | H12: 123 | I12: V163-4.5MW | AG12: 3 | AH12: 2026 | AI12: =COUNTIF($I$177:$I$208,I12) -> 1 | AJ12: =COUNTIF($C$176:$C$205,C12) -> 1 | AK12: =COUNTIF($C$232:$C$270,C12) -> 1 | AL12: =_xlfn.DAYS(DATE(AH12,AG12*3-2,1),DATE(RIGHT(B12,4),MID(B12,4,2),LEFT(B12,2))) -> 824
B13: 21.05.2024 | C13: Austria | D13: 84 | E13: AOM5000 | F13: 25 | G13: BE Energy | H13: 14 | I13: V150-6.0MW | J13: 150 | K13: 6 | AG13: 2 | AH13: 2025 | AI13: =COUNTIF($I$177:$I$208,I13) -> 1 | AJ13: =COUNTIF($C$176:$C$205,C13) -> 1 | AK13: =COUNTIF($C$232:$C$270,C13) -> 1 | AL13: =_xlfn.DAYS(DATE(AH13,AG13*3-2,1),DATE(RIGHT(B13,4),MID(B13,4,2),LEFT(B13,2))) -> 315
B14: 03.06.2024 | C14: Lithuania | D14: 124 | E14: AOM5000 | F14: lifetime | G14: Telsiai | H14: 20 | I14: V162-6.2MW | J14: 162 | K14: 6.2 | AG14: 1 | AH14: 2026 | AI14: =COUNTIF($I$177:$I$208,I14) -> 1 | AJ14: =COUNTIF($C$176:$C$205,C14) -> 1 | AK14: =COUNTIF($C$232:$C$270,C14) -> 1 | AL14: =_xlfn.DAYS(DATE(AH14,AG14*3-2,1),DATE(RIGHT(B14,4),MID(B14,4,2),LEFT(B14,2))) -> 577
B15: 06.06.2024 | C15: Austria | D15: 68 | E15: AOM4000 | F15: 24 | G15: Erneuerbare Energie | H15: 10 | I15: V162-6.2MW | J15: 162 | K15: 6.2 | O15: 1 | P15: V150-6.0MW | Q15: 150 | R15: 6 | AG15: 2 | AH15: 2025 | AI15: =COUNTIF($I$177:$I$208,I15) -> 1 | AJ15: =COUNTIF($C$176:$C$205,C15) -> 1 | AK15: =COUNTIF($C$232:$C$270,C15) -> 1 | AL15: =_xlfn.DAYS(DATE(AH15,AG15*3-2,1),DATE(RIGHT(B15,4),MID(B15,4,2),LEFT(B15,2))) -> 299
B16: 10.06.2024 | C16: Germany | D16: 72 | E16: AOM5000 | F16: 20 | G16: Denker & Wulf AG | H16: 10 | I16: V162-7.2MW | J16: 162 | K16: 7.2 | AG16: 4 | AH16: 2025 | AI16: =COUNTIF($I$177:$I$208,I16) -> 1 | AJ16: =COUNTIF($C$176:$C$205,C16) -> 1 | AK16: =COUNTIF($C$232:$C$270,C16) -> 1 | AL16: =_xlfn.DAYS(DATE(AH16,AG16*3-2,1),DATE(RIGHT(B16,4),MID(B16,4,2),LEFT(B16,2))) -> 478
B17: 13.06.2024 | C17: South Korea | D17: 90 | E17: AOM5000 | H17: 21 | I17: V136-4.2MW | J17: 136 | K17: 4.3 | L17: opt 4.3 | AG17: 2 | AH17: 2025 | AI17: =COUNTIF($I$177:$I$208,I17) -> 1 | AJ17: =COUNTIF($C$176:$C$205,C17) -> 1 | AK17: =COUNTIF($C$232:$C$270,C17) -> 1 | AL17: =_xlfn.DAYS(DATE(AH17,AG17*3-2,1),DATE(RIGHT(B17,4),MID(B17,4,2),LEFT(B17,2))) -> 292
B18: 14.06.2024 | C18: Germany | D18: 660 | F18: 5 | G18: RWE | H18: 44 | I18: V236-15.0MW | J18: 236 | K18: 15 | AG18: 2 | AH18: 2026 | AI18: =COUNTIF($I$177:$I$208,I18) -> 1 | AJ18: =COUNTIF($C$176:$C$205,C18) -> 1 | AK18: =COUNTIF($C$232:$C$270,C18) -> 1 | AL18: =_xlfn.DAYS(DATE(AH18,AG18*3-2,1),DATE(RIGHT(B18,4),MID(B18,4,2),LEFT(B18,2))) -> 656
B19: 17.06.2024 | C19: Romania | D19: 192 | E19: AOM5000 | F19: 15 | G19: Rezolz Energy | H19: 30 | I19: V162-6.2MW | J19: 162 | K19: 6.4 | L19: opt 6.4 | AG19: 1 | AH19: 2025 | AI19: =COUNTIF($I$177:$I$208,I19) -> 1 | AJ19: =COUNTIF($C$176:$C$205,C19) -> 1 | AK19: =COUNTIF($C$232:$C$270,C19) -> 1 | AL19: =_xlfn.DAYS(DATE(AH19,AG19*3-2,1),DATE(RIGHT(B19,4),MID(B19,4,2),LEFT(B19,2))) -> 198
B20: 18.06.2024 | C20: Australia | D20: 577 | E20: AOM5000 | F20: 30 | G20: TagEnergy | H20: 63 | I20: V162-6.2MW | J20: 162 | K20: 6.2 | AG20: 1 | AH20: 2025 | AI20: =COUNTIF($I$177:$I$208,I20) -> 1 | AJ20: =COUNTIF($C$176:$C$205,C20) -> 1 | AK20: =COUNTIF($C$232:$C$270,C20) -> 1 | AL20: =_xlfn.DAYS(DATE(AH20,AG20*3-2,1),DATE(RIGHT(B20,4),MID(B20,4,2),LEFT(B20,2))) -> 197
B21: 25.06.2024 | C21: Spain | D21: 50 | E21: AOM4000 | F21: 25 | G21: Elawan Energy | H21: 8 | I21: V162-6.2MW | J21: 162 | K21: 6.2 | L21: opt 6.4 (3) | AG21: 1 | AH21: 2025 | AI21: =COUNTIF($I$177:$I$208,I21) -> 1 | AJ21: =COUNTIF($C$176:$C$205,C21) -> 1 | AK21: =COUNTIF($C$232:$C$270,C21) -> 1 | AL21: =_xlfn.DAYS(DATE(AH21,AG21*3-2,1),DATE(RIGHT(B21,4),MID(B21,4,2),LEFT(B21,2))) -> 190
B22: 25.06.2024 | C22: New Zealand | D22: 155 | E22: AOM5000 | F22: 30 | G22: Mercury Energy | H22: 36 | I22: V136-4.2MW | J22: 136 | K22: 4.3 | L22: opt 4.3 | AG22: 4 | AH22: 2025 | AI22: =COUNTIF($I$177:$I$208,I22) -> 1 | AJ22: =COUNTIF($C$176:$C$205,C22) -> 1 | AK22: =COUNTIF($C$232:$C$270,C22) -> 1 | AL22: =_xlfn.DAYS(DATE(AH22,AG22*3-2,1),DATE(RIGHT(B22,4),MID(B22,4,2),LEFT(B22,2))) -> 463
B23: 28.06.2024 | C23: UK | D23: 81 | E23: AOM5000 | G23: Invenergy | H23: 18 | I23: V136-4.5MW | J23: 136 | K23: 4.5 | AG23: 2 | AH23: 2025 | AI23: =COUNTIF($I$177:$I$208,I23) -> 1 | AJ23: =COUNTIF($C$176:$C$205,C23) -> 1 | AK23: =COUNTIF($C$232:$C$270,C23) -> 1 | AL23: =_xlfn.DAYS(DATE(AH23,AG23*3-2,1),DATE(RIGHT(B23,4),MID(B23,4,2),LEFT(B23,2))) -> 277
B24: 28.06.2024 | C24: Germany | D24: 105 | E24: AOM5000 | F24: 20 | G24: LEAG | H24: 17 | I24: V162-6.2MW | J24: 162 | K24: 6.2 | AG24: 4 | AH24: 2025 | AI24: =COUNTIF($I$177:$I$208,I24) -> 1 | AJ24: =COUNTIF($C$176:$C$205,C24) -> 1 | AK24: =COUNTIF($C$232:$C$270,C24) -> 1 | AL24: =_xlfn.DAYS(DATE(AH24,AG24*3-2,1),DATE(RIGHT(B24,4),MID(B24,4,2),LEFT(B24,2))) -> 460
B25: 28.06.2024 | C25: Germany | D25: 114 | E25: AOM5000 | F25: 25 | G25: SAB WindTeam | H25: 17 | I25: V162-6.2MW | J25: 162 | K25: 6.2 | O25: 2 | P25: V136-4.2MW | Q25: 136 | R25: 4.2 | AG25: 2 | AH25: 2025 | AI25: =COUNTIF($I$177:$I$208,I25) -> 1 | AJ25: =COUNTIF($C$176:$C$205,C25) -> 1 | AK25: =COUNTIF($C$232:$C$270,C25) -> 1 | AL25: =_xlfn.DAYS(DATE(AH25,AG25*3-2,1),DATE(RIGHT(B25,4),MID(B25,4,2),LEFT(B25,2))) -> 277
B26: 28.06.2024 | C26: Turkey | D26: 45 | E26: AOM4000 | F26: 15 | H26: 10 | I26: V150-4.5MW | J26: 150 | K26: 4.5 | AG26: 2 | AH26: 2025 | AI26: =COUNTIF($I$177:$I$208,I26) -> 1 | AJ26: =COUNTIF($C$176:$C$205,C26) -> 1 | AK26: =COUNTIF($C$232:$C$270,C26) -> 1 | AL26: =_xlfn.DAYS(DATE(AH26,AG26*3-2,1),DATE(RIGHT(B26,4),MID(B26,4,2),LEFT(B26,2))) -> 277
B27: 28.06.2024 | C27: South Africa | D27: 144 | E27: AOM5000 | F27: 10 | G27: African Clean Energy Development | H27: 32 | I27: V163-4.5MW | J27: 163 | K27: 4.5 | AG27: 2 | AH27: 2025 | AI27: =COUNTIF($I$177:$I$208,I27) -> 1 | AJ27: =COUNTIF($C$176:$C$205,C27) -> 1 | AK27: =COUNTIF($C$232:$C$270,C27) -> 1 | AL27: =_xlfn.DAYS(DATE(AH27,AG27*3-2,1),DATE(RIGHT(B27,4),MID(B27,4,2),LEFT(B27,2))) -> 277
B28: 28.06.2024 | C28: Lithuania | D28: 99 | E28: AOM5000 | F28: 35 | G28: Aquila Clean Energy | H28: 16 | I28: V162-6.2MW | J28: 162 | K28: 6.2 | AG28: 4 | AH28: 2024 | AI28: =COUNTIF($I$177:$I$208,I28) -> 1 | AJ28: =COUNTIF($C$176:$C$205,C28) -> 1 | AK28: =COUNTIF($C$232:$C$270,C28) -> 1 | AL28: =_xlfn.DAYS(DATE(AH28,AG28*3-2,1),DATE(RIGHT(B28,4),MID(B28,4,2),LEFT(B28,2))) -> 95
B29: 28.06.2024 | C29: Turkey | D29: 63 | E29: AOM4000 | F29: 10 | G29: Kangal Energy | H29: 12 | I29: V150-4.5MW | J29: 150 | K29: 4.5 | O29: 2 | P29: V136-4.5MW | Q29: 136 | R29: 4.5 | AG29: 2 | AH29: 2025 | AI29: =COUNTIF($I$177:$I$208,I29) -> 1 | AJ29: =COUNTIF($C$176:$C$205,C29) -> 1 | AK29: =COUNTIF($C$232:$C$270,C29) -> 1 | AL29: =_xlfn.DAYS(DATE(AH29,AG29*3-2,1),DATE(RIGHT(B29,4),MID(B29,4,2),LEFT(B29,2))) -> 277
B30: 28.06.2024 | C30: Argentina | D30: 95 | E30: AOM5000 | F30: 30 | H30: 21 | I30: V150-4.5MW | J30: 150 | K30: 4.5 | AG30: 2 | AH30: 2025 | AI30: =COUNTIF($I$177:$I$208,I30) -> 1 | AJ30: =COUNTIF($C$176:$C$205,C30) -> 1 | AK30: =COUNTIF($C$232:$C$270,C30) -> 1 | AL30: =_xlfn.DAYS(DATE(AH30,AG30*3-2,1),DATE(RIGHT(B30,4),MID(B30,4,2),LEFT(B30,2))) -> 277
A31: =SUM(D13:D31) -> 2902 | B31: 28.06.2024 | C31: United states | D31: 84 | E31: AOM5000 | H31: 38 | I31: V110-2.2MW | J31: 110 | K31: 2.2 | AG31: 3 | AH31: 2025 | AI31: =COUNTIF($I$177:$I$208,I31) -> 1 | AJ31: =COUNTIF($C$176:$C$205,C31) -> 1 | AK31: =COUNTIF($C$232:$C$270,C31) -> 1 | AL31: =_xlfn.DAYS(DATE(AH31,AG31*3-2,1),DATE(RIGHT(B31,4),MID(B31,4,2),LEFT(B31,2))) -> 368
B32: 03.07.2024 | C32: Canada | D32: 347 | E32: AOM5000 | H32: 56 | I32: V162-6.2MW | J32: 162 | K32: 6.2 | AG32: 1 | AH32: 2025 | AI32: =COUNTIF($I$177:$I$208,I32) -> 1 | AJ32: =COUNTIF($C$176:$C$205,C32) -> 1 | AK32: =COUNTIF($C$232:$C$270,C32) -> 1 | AL32: =_xlfn.DAYS(DATE(AH32,AG32*3-2,1),DATE(RIGHT(B32,4),MID(B32,4,2),LEFT(B32,2))) -> 182
B33: 18.07.2024 | C33: United states | D33: 117 | E33: AOM5000 | H33: 26 | I33: V150-4.5MW | J33: 150 | K33: 4.5 | AG33: 2 | AH33: 2025 | AI33: =COUNTIF($I$177:$I$208,I33) -> 1 | AJ33: =COUNTIF($C$176:$C$205,C33) -> 1 | AK33: =COUNTIF($C$232:$C$270,C33) -> 1 | AL33: =_xlfn.DAYS(DATE(AH33,AG33*3-2,1),DATE(RIGHT(B33,4),MID(B33,4,2),LEFT(B33,2))) -> 257
B34: 22.07.2024 | C34: United states | D34: 136 | H34: 62 | I34: V120-2.2MW | J34: 120 | K34: 2.2 | AG34: 3 | AH34: 2025 | AI34: =COUNTIF($I$177:$I$208,I34) -> 1 | AJ34: =COUNTIF($C$176:$C$205,C34) -> 1 | AK34: =COUNTIF($C$232:$C$270,C34) -> 1 | AL34: =_xlfn.DAYS(DATE(AH34,AG34*3-2,1),DATE(RIGHT(B34,4),MID(B34,4,2),LEFT(B34,2))) -> 344
B35: 29.07.2024 | C35: Netherlands | D35: 795 | G35: RWE & TotalEnergies | H35: 53 | I35: V236-15.0MW | J35: 236 | K35: 15 | AF35: Hollandse Kust West VII | AI35: =COUNTIF($I$177:$I$208,I35) -> 1 | AJ35: =COUNTIF($C$176:$C$205,C35) -> 1 | AK35: =COUNTIF($C$232:$C$270,C35) -> 1 | AL35: =_xlfn.DAYS(DATE(AH35,AG35*3-2,1),DATE(RIGHT(B35,4),MID(B35,4,2),LEFT(B35,2))) -> #NUM!
B36: 30.07.2024 | C36: Germany | D36: 49 | E36: AOM5000 | G36: WindBauer | H36: 6 | I36: V162-7.2MW | J36: 162 | K36: 7.2 | O36: 1 | P36: V150-6.0MW | Q36: 150 | R36: 6 | AG36: 1 | AH36: 2026 | AI36: =COUNTIF($I$177:$I$208,I36) -> 1 | AJ36: =COUNTIF($C$176:$C$205,C36) -> 1 | AK36: =COUNTIF($C$232:$C$270,C36) -> 1 | AL36: =_xlfn.DAYS(DATE(AH36,AG36*3-2,1),DATE(RIGHT(B36,4),MID(B36,4,2),LEFT(B36,2))) -> 520
B37: 07.08.2024 | C37: South Africa | D37: 144 | E37: AOM5000 | F37: 10 | G37: African Clean Energy Development | H37: 32 | I37: V163-4.5MW | J37: 163 | K37: 4.5 | AG37: 2 | AH37: 2025 | AI37: =COUNTIF($I$177:$I$208,I37) -> 1 | AJ37: =COUNTIF($C$176:$C$205,C37) -> 1 | AK37: =COUNTIF($C$232:$C$270,C37) -> 1 | AL37: =_xlfn.DAYS(DATE(AH37,AG37*3-2,1),DATE(RIGHT(B37,4),MID(B37,4,2),LEFT(B37,2))) -> 237
B38: 08.08.2024 | C38: Romania | D38: 99 | E38: AOM5000 | F38: 35 | G38: OX2 | H38: 16 | I38: V162-6.2MW | J38: 162 | K38: 6.2 | AG38: 3 | AH38: 2025 | AI38: =COUNTIF($I$177:$I$208,I38) -> 1 | AJ38: =COUNTIF($C$176:$C$205,C38) -> 1 | AK38: =COUNTIF($C$232:$C$270,C38) -> 1 | AL38: =_xlfn.DAYS(DATE(AH38,AG38*3-2,1),DATE(RIGHT(B38,4),MID(B38,4,2),LEFT(B38,2))) -> 327
B39: 09.08.2024 | C39: Spain | D39: 41 | E39: AOM4000 | F39: 20 | G39: Green Mind Ventures | H39: 6 | I39: V163-4.5MW | J39: 163 | K39: 4.5 | O39: 3 | P39: V136-4.5MW | Q39: 136 | R39: 4.5 | AG39: 2 | AH39: 2025 | AI39: =COUNTIF($I$177:$I$208,I39) -> 1 | AJ39: =COUNTIF($C$176:$C$205,C39) -> 1 | AK39: =COUNTIF($C$232:$C$270,C39) -> 1 | AL39: =_xlfn.DAYS(DATE(AH39,AG39*3-2,1),DATE(RIGHT(B39,4),MID(B39,4,2),LEFT(B39,2))) -> 235
B40: 09.08.2024 | C40: Germany | D40: 58 | E40: AOM5000 | F40: 25 | G40: Uhl Windkraft | H40: 8 | I40: V172-7.2MW | J40: 172 | K40: 7.2 | AG40: 1 | AH40: 2026 | AI40: =COUNTIF($I$177:$I$208,I40) -> 1 | AJ40: =COUNTIF($C$176:$C$205,C40) -> 1 | AK40: =COUNTIF($C$232:$C$270,C40) -> 1 | AL40: =_xlfn.DAYS(DATE(AH40,AG40*3-2,1),DATE(RIGHT(B40,4),MID(B40,4,2),LEFT(B40,2))) -> 510
B41: 13.08.2024 | C41: Dominican Republic | D41: 50 | E41: AOM5000 | F41: 20 | H41: 11 | I41: V163-4.5MW | J41: 163 | K41: 4.5 | AG41: 4 | AH41: 2025 | AI41: =COUNTIF($I$177:$I$208,I41) -> 1 | AJ41: =COUNTIF($C$176:$C$205,C41) -> 1 | AK41: =COUNTIF($C$232:$C$270,C41) -> 1 | AL41: =_xlfn.DAYS(DATE(AH41,AG41*3-2,1),DATE(RIGHT(B41,4),MID(B41,4,2),LEFT(B41,2))) -> 414
B42: 13.08.2024 | C42: Italy | D42: 29 | E42: AOM5000 | F42: 20 | G42: VGE | H42: 3 | I42: V162-6.2MW | J42: 162 | K42: 6.2 | AG42: 4 | AH42: 2025 | AI42: =COUNTIF($I$177:$I$208,I42) -> 1 | AJ42: =COUNTIF($C$176:$C$205,C42) -> 1 | AK42: =COUNTIF($C$232:$C$270,C42) -> 1 | AL42: =_xlfn.DAYS(DATE(AH42,AG42*3-2,1),DATE(RIGHT(B42,4),MID(B42,4,2),LEFT(B42,2))) -> 414
B43: 13.08.2024 | C43: Greece | D43: 27 | E43: AOM5000 | F43: 20 | H43: 6 | I43: V150-4.5MW | J43: 150 | K43: 4.5 | AG43: 2 | AH43: 2025 | AI43: =COUNTIF($I$177:$I$208,I43) -> 1 | AJ43: =COUNTIF($C$176:$C$205,C43) -> 1 | AK43: =COUNTIF($C$232:$C$270,C43) -> 1 | AL43: =_xlfn.DAYS(DATE(AH43,AG43*3-2,1),DATE(RIGHT(B43,4),MID(B43,4,2),LEFT(B43,2))) -> 231
B44: 13.08.2024 | C44: France | D44: 46 | E44: AOM5000 | F44: 20 | H44: 21 | I44: V110-2.2MW | J44: 110 | K44: 2.2 | AG44: 3 | AH44: 2025 | AI44: =COUNTIF($I$177:$I$208,I44) -> 1 | AJ44: =COUNTIF($C$176:$C$205,C44) -> 1 | AK44: =COUNTIF($C$232:$C$270,C44) -> 1 | AL44: =_xlfn.DAYS(DATE(AH44,AG44*3-2,1),DATE(RIGHT(B44,4),MID(B44,4,2),LEFT(B44,2))) -> 322
B45: 13.08.2024 | C45: United states | D45: 252 | E45: AOM5000 | F45: 10 | H45: 56 | I45: V163-4.5MW | J45: 163 | K45: 4.5 | AG45: 3 | AH45: 2026 | AI45: =COUNTIF($I$177:$I$208,I45) -> 1 | AJ45: =COUNTIF($C$176:$C$205,C45) -> 1 | AK45: =COUNTIF($C$232:$C$270,C45) -> 1 | AL45: =_xlfn.DAYS(DATE(AH45,AG45*3-2,1),DATE(RIGHT(B45,4),MID(B45,4,2),LEFT(B45,2))) -> 687
B46: 15.08.2024 | C46: Australia | D46: 285 | E46: AOM5000 | G46: CS Energy | H46: 46 | I46: V162-6.2MW | J46: 162 | K46: 6.2 | AG46: 1 | AH46: 2026 | AI46: =COUNTIF($I$177:$I$208,I46) -> 1 | AJ46: =COUNTIF($C$176:$C$205,C46) -> 1 | AK46: =COUNTIF($C$232:$C$270,C46) -> 1 | AL46: =_xlfn.DAYS(DATE(AH46,AG46*3-2,1),DATE(RIGHT(B46,4),MID(B46,4,2),LEFT(B46,2))) -> 504
B47: 21.08.2024 | C47: United states | D47: 114 | E47: AOM5000 | G47: Competitive Power Ventures | H47: 19 | I47: V162-6.0MW | J47: 162 | K47: 6 | AG47: 1 | AH47: 2025 | AI47: =COUNTIF($I$177:$I$208,I47) -> 1 | AJ47: =COUNTIF($C$176:$C$205,C47) -> 1 | AK47: =COUNTIF($C$232:$C$270,C47) -> 1 | AL47: =_xlfn.DAYS(DATE(AH47,AG47*3-2,1),DATE(RIGHT(B47,4),MID(B47,4,2),LEFT(B47,2))) -> 133
B48: 03.08.2024 | C48: Germany | D48: 55 | E48: AOM5000 | F48: 20 | G48: BWP | H48: 6 | I48: V162-6.2MW | J48: 162 | K48: 6.2 | O48: 3 | P48: V150-6.0MW | Q48: 150 | R48: 6 | AG48: 3 | AH48: 2025 | AI48: =COUNTIF($I$177:$I$208,I48) -> 1 | AJ48: =COUNTIF($C$176:$C$205,C48) -> 1 | AK48: =COUNTIF($C$232:$C$270,C48) -> 1 | AL48: =_xlfn.DAYS(DATE(AH48,AG48*3-2,1),DATE(RIGHT(B48,4),MID(B48,4,2),LEFT(B48,2))) -> 332
B49: 09.09.2024 | C49: United states | D49: 810 | F49: 5 | G49: Equinor | H49: 54 | I49: V236-15.0MW | J49: 236 | K49: 15 | AG49: 2 | AH49: 2026 | AI49: =COUNTIF($I$177:$I$208,I49) -> 1 | AJ49: =COUNTIF($C$176:$C$205,C49) -> 1 | AK49: =COUNTIF($C$232:$C$270,C49) -> 1 | AL49: =_xlfn.DAYS(DATE(AH49,AG49*3-2,1),DATE(RIGHT(B49,4),MID(B49,4,2),LEFT(B49,2))) -> 569
B50: 24.09.2024 | C50: Japan | D50: 134 | E50: AOM5000 | F50: 20 | G50: Invenergy | H50: 32 | I50: V117-4.2MW | J50: 117 | K50: 4.2 | AG50: 2 | AH50: 2027 | AI50: =COUNTIF($I$177:$I$208,I50) -> 1 | AJ50: =COUNTIF($C$176:$C$205,C50) -> 1 | AK50: =COUNTIF($C$232:$C$270,C50) -> 1 | AL50: =_xlfn.DAYS(DATE(AH50,AG50*3-2,1),DATE(RIGHT(B50,4),MID(B50,4,2),LEFT(B50,2))) -> 919
B51: 30.09.2024 | C51: Japan | D51: 34 | E51: AOM5000 | F51: 20 | G51: Tohoku Electric | H51: 8 | I51: V117-4.2MW | J51: 117 | K51: 4.2 | AG51: 1 | AH51: 2026 | AI51: =COUNTIF($I$177:$I$208,I51) -> 1 | AJ51: =COUNTIF($C$176:$C$205,C51) -> 1 | AK51: =COUNTIF($C$232:$C$270,C51) -> 1 | AL51: =_xlfn.DAYS(DATE(AH51,AG51*3-2,1),DATE(RIGHT(B51,4),MID(B51,4,2),LEFT(B51,2))) -> 458
B52: 30.09.2024 | C52: Costa Rica | D52: 34 | E52: AOM5000 | F52: 5 | H52: 8 | I52: V117-4.2MW | J52: 117 | K52: 4.2 | AG52: 2 | AH52: 2025 | AI52: =COUNTIF($I$177:$I$208,I52) -> 1 | AJ52: =COUNTIF($C$176:$C$205,C52) -> 1 | AK52: =COUNTIF($C$232:$C$270,C52) -> 1 | AL52: =_xlfn.DAYS(DATE(AH52,AG52*3-2,1),DATE(RIGHT(B52,4),MID(B52,4,2),LEFT(B52,2))) -> 183
B53: 30.09.2024 | C53: Italy | D53: 45 | E53: AOM5000 | F53: 18 | G53: Libeccio | H53: 7 | I53: V162-6.2MW | J53: 162 | K53: 6.4 | AG53: 3 | AH53: 2025 | AI53: =COUNTIF($I$177:$I$208,I53) -> 1 | AJ53: =COUNTIF($C$176:$C$205,C53) -> 1 | AK53: =COUNTIF($C$232:$C$270,C53) -> 1 | AL53: =_xlfn.DAYS(DATE(AH53,AG53*3-2,1),DATE(RIGHT(B53,4),MID(B53,4,2),LEFT(B53,2))) -> 274
A54: =SUM(D32:D54) -> 3742 | B54: 30.09.2024 | C54: Spain | D54: 41 | E54: AOM5000 | F54: 15 | G54: Altano Energy | H54: 9 | I54: V163-4.5MW | J54: 163 | K54: 4.5 | AG54: 3 | AH54: 2025 | AI54: =COUNTIF($I$177:$I$208,I54) -> 1 | AJ54: =COUNTIF($C$176:$C$205,C54) -> 1 | AK54: =COUNTIF($C$232:$C$270,C54) -> 1 | AL54: =_xlfn.DAYS(DATE(AH54,AG54*3-2,1),DATE(RIGHT(B54,4),MID(B54,4,2),LEFT(B54,2))) -> 274
B55: 16.10.2024 | C55: United states | D55: 137 | E55: AOM5000 | F55: 20 | G55: Exus Manament partners | H55: 62 | I55: V120-2.2MW | J55: 120 | K55: 2.2 | AG55: 4 | AH55: 2025 | AI55: =COUNTIF($I$177:$I$208,I55) -> 1 | AJ55: =COUNTIF($C$176:$C$205,C55) -> 1 | AK55: =COUNTIF($C$232:$C$270,C55) -> 1 | AL55: =_xlfn.DAYS(DATE(AH55,AG55*3-2,1),DATE(RIGHT(B55,4),MID(B55,4,2),LEFT(B55,2))) -> 350
B56: 18.10.2024 | C56: Germany | D56: 70 | E56: AOM5000 | F56: 25 | G56: Terrawatt | H56: 7 | I56: V162-6.0MW | J56: 162 | K56: 5.6 | O56: 5 | P56: V162-6.2MW | Q56: 162 | R56: 6.2 | AG56: 3 | AH56: 2025 | AI56: =COUNTIF($I$177:$I$208,I56) -> 1 | AJ56: =COUNTIF($C$176:$C$205,C56) -> 1 | AK56: =COUNTIF($C$232:$C$270,C56) -> 1 | AL56: =_xlfn.DAYS(DATE(AH56,AG56*3-2,1),DATE(RIGHT(B56,4),MID(B56,4,2),LEFT(B56,2))) -> 256
B57: 29.10.2024 | C57: Romania | D57: 50 | E57: AOM5000 | F57: 20 | G57: Eolenerg | H57: 9 | I57: V150-4.2MW | J57: 150 | K57: 4.2 | O57: 3 | P57: V150-4.0MW | Q57: 150 | R57: 4 | AG57: 3 | AH57: 2025 | AI57: =COUNTIF($I$177:$I$208,I57) -> 1 | AJ57: =COUNTIF($C$176:$C$205,C57) -> 1 | AK57: =COUNTIF($C$232:$C$270,C57) -> 1 | AL57: =_xlfn.DAYS(DATE(AH57,AG57*3-2,1),DATE(RIGHT(B57,4),MID(B57,4,2),LEFT(B57,2))) -> 245
B58: 05.11.2024 | C58: United states | D58: 203 | E58: AOM5000 | F58: 10 | G58: Apex Clean Energy | H58: 45 | I58: V163-4.5MW | J58: 163 | K58: 4.5 | AG58: 4 | AH58: 2025 | AI58: =COUNTIF($I$177:$I$208,I58) -> 1 | AJ58: =COUNTIF($C$176:$C$205,C58) -> 1 | AK58: =COUNTIF($C$232:$C$270,C58) -> 1 | AL58: =_xlfn.DAYS(DATE(AH58,AG58*3-2,1),DATE(RIGHT(B58,4),MID(B58,4,2),LEFT(B58,2))) -> 330
B59: 13.11.2024 | C59: Germany | D59: 93 | E59: AOM5000 | F59: 20 | G59: Mibrag | H59: 15 | I59: V162-6.2MW | J59: 162 | K59: 6.2 | AG59: 2 | AH59: 2026 | AI59: =COUNTIF($I$177:$I$208,I59) -> 1 | AJ59: =COUNTIF($C$176:$C$205,C59) -> 1 | AK59: =COUNTIF($C$232:$C$270,C59) -> 1 | AL59: =_xlfn.DAYS(DATE(AH59,AG59*3-2,1),DATE(RIGHT(B59,4),MID(B59,4,2),LEFT(B59,2))) -> 504
B60: 13.11.2024 | C60: Germany | D60: 101 | E60: AOM5000 | F60: 25 | G60: Windpark Reinhardswald | H60: 18 | I60: V150-6.0MW | J60: 150 | K60: 5.6 | AG60: 2 | AH60: 2025 | AI60: =COUNTIF($I$177:$I$208,I60) -> 1 | AJ60: =COUNTIF($C$176:$C$205,C60) -> 1 | AK60: =COUNTIF($C$232:$C$270,C60) -> 1 | AL60: =_xlfn.DAYS(DATE(AH60,AG60*3-2,1),DATE(RIGHT(B60,4),MID(B60,4,2),LEFT(B60,2))) -> 139
B61: 18.11.2024 | C61: South Korea | D61: 50 | E61: AOM5000 | F61: 20 | H61: 8 | I61: V162-6.2MW | J61: 162 | K61: 6.2 | AG61: 2 | AH61: 2025 | AI61: =COUNTIF($I$177:$I$208,I61) -> 1 | AJ61: =COUNTIF($C$176:$C$205,C61) -> 1 | AK61: =COUNTIF($C$232:$C$270,C61) -> 1 | AL61: =_xlfn.DAYS(DATE(AH61,AG61*3-2,1),DATE(RIGHT(B61,4),MID(B61,4,2),LEFT(B61,2))) -> 134
B62: 28.11.2024 | C62: Germany | D62: 900 | F62: 5 | G62: RWE | H62: 16 | I62: V236-15.0MW | J62: 236 | K62: 15 | AF62: phase b of the 14.06.2024 order | AG62: 2 | AH62: 2028 | AI62: =COUNTIF($I$177:$I$208,I62) -> 1 | AJ62: =COUNTIF($C$176:$C$205,C62) -> 1 | AK62: =COUNTIF($C$232:$C$270,C62) -> 1 | AL62: =_xlfn.DAYS(DATE(AH62,AG62*3-2,1),DATE(RIGHT(B62,4),MID(B62,4,2),LEFT(B62,2))) -> 1220
B63: 02.12.2024 | C63: United states | D63: 342 | E63: AOM5000 | F63: 10 | G63: Invenergy | H63: 76 | I63: V150-4.5MW | J63: 150 | K63: 4.5 | AG63: 4 | AH63: 2025 | AI63: =COUNTIF($I$177:$I$208,I63) -> 1 | AJ63: =COUNTIF($C$176:$C$205,C63) -> 1 | AK63: =COUNTIF($C$232:$C$270,C63) -> 1 | AL63: =_xlfn.DAYS(DATE(AH63,AG63*3-2,1),DATE(RIGHT(B63,4),MID(B63,4,2),LEFT(B63,2))) -> 303
B64: 13.12.2024 | C64: UK | D64: 1080 | G64: ESB | H64: 72 | I64: V236-15.0MW | J64: 236 | K64: 15 | AG64: 2 | AH64: 2026 | AI64: =COUNTIF($I$177:$I$208,I64) -> 1 | AJ64: =COUNTIF($C$176:$C$205,C64) -> 1 | AK64: =COUNTIF($C$232:$C$270,C64) -> 1 | AL64: =_xlfn.DAYS(DATE(AH64,AG64*3-2,1),DATE(RIGHT(B64,4),MID(B64,4,2),LEFT(B64,2))) -> 474
B65: 17.12.2024 | C65: UK | D65: 217 | E65: AOM5000 | F65: 20 | G65: SSE Generation | H65: 35 | I65: V162-6.2MW | J65: 162 | K65: 6.2 | AG65: 4 | AH65: 2026 | AI65: =COUNTIF($I$177:$I$208,I65) -> 1 | AJ65: =COUNTIF($C$176:$C$205,C65) -> 1 | AK65: =COUNTIF($C$232:$C$270,C65) -> 1 | AL65: =_xlfn.DAYS(DATE(AH65,AG65*3-2,1),DATE(RIGHT(B65,4),MID(B65,4,2),LEFT(B65,2))) -> 653
B66: 18.12.2024 | C66: Germany | D66: 62 | E66: AOM5000 | F66: 20 | G66: Meridian windpark | H66: 10 | I66: V162-6.2MW | J66: 162 | K66: 6.2 | AG66: 3 | AH66: 2026 | AI66: =COUNTIF($I$177:$I$208,I66) -> 1 | AJ66: =COUNTIF($C$176:$C$205,C66) -> 1 | AK66: =COUNTIF($C$232:$C$270,C66) -> 1 | AL66: =_xlfn.DAYS(DATE(AH66,AG66*3-2,1),DATE(RIGHT(B66,4),MID(B66,4,2),LEFT(B66,2))) -> 560
B67: 18.12.2024 | C67: New Zealand | D67: 77 | E67: AOM5000 | F67: 30 | G67: Mercury Energy | H67: 12 | I67: V162-6.4MW | J67: 162 | K67: 6.4 | AG67: 2 | AH67: 2026 | AI67: =COUNTIF($I$177:$I$208,I67) -> 1 | AJ67: =COUNTIF($C$176:$C$205,C67) -> 1 | AK67: =COUNTIF($C$232:$C$270,C67) -> 1 | AL67: =_xlfn.DAYS(DATE(AH67,AG67*3-2,1),DATE(RIGHT(B67,4),MID(B67,4,2),LEFT(B67,2))) -> 469
B68: 18.12.2024 | C68: United states | D68: 86 | E68: AOM5000 | F68: 10 | G68: Brookfield renewable | H68: 19 | I68: V163-4.5MW | J68: 163 | K68: 4.5 | AG68: 4 | AH68: 2025 | AI68: =COUNTIF($I$177:$I$208,I68) -> 1 | AJ68: =COUNTIF($C$176:$C$205,C68) -> 1 | AK68: =COUNTIF($C$232:$C$270,C68) -> 1 | AL68: =_xlfn.DAYS(DATE(AH68,AG68*3-2,1),DATE(RIGHT(B68,4),MID(B68,4,2),LEFT(B68,2))) -> 287
B69: 19.12.2024 | C69: Sweden | D69: 224 | E69: AOM5000 | G69: Vinliden Vindkraft | H69: 35 | I69: V162-6.4MW | J69: 162 | K69: 6.4 | AG69: 2 | AH69: 2026 | AI69: =COUNTIF($I$177:$I$208,I69) -> 1 | AJ69: =COUNTIF($C$176:$C$205,C69) -> 1 | AK69: =COUNTIF($C$232:$C$270,C69) -> 1 | AL69: =_xlfn.DAYS(DATE(AH69,AG69*3-2,1),DATE(RIGHT(B69,4),MID(B69,4,2),LEFT(B69,2))) -> 468
B70: 20.12.2024 | C70: Japan | D70: 38 | H70: 9 | I70: V117-4.2MW | J70: 117 | K70: 4.2 | AG70: 2 | AH70: 2026 | AI70: =COUNTIF($I$177:$I$208,I70) -> 1 | AJ70: =COUNTIF($C$176:$C$205,C70) -> 1 | AK70: =COUNTIF($C$232:$C$270,C70) -> 1 | AL70: =_xlfn.DAYS(DATE(AH70,AG70*3-2,1),DATE(RIGHT(B70,4),MID(B70,4,2),LEFT(B70,2))) -> 467
B71: 20.12.2024 | C71: Japan | D71: 34 | H71: 8 | I71: V117-4.2MW | J71: 117 | K71: 4.2 | AG71: 2 | AH71: 2026 | AI71: =COUNTIF($I$177:$I$208,I71) -> 1 | AJ71: =COUNTIF($C$176:$C$205,C71) -> 1 | AK71: =COUNTIF($C$232:$C$270,C71) -> 1 | AL71: =_xlfn.DAYS(DATE(AH71,AG71*3-2,1),DATE(RIGHT(B71,4),MID(B71,4,2),LEFT(B71,2))) -> 467
B72: 20.12.2024 | C72: Japan | D72: 21 | E72: AOM5000 | G72: GK JRE | H72: 5 | I72: V136-4.2MW | J72: 136 | K72: 4.2 | AG72: 2 | AH72: 2026 | AI72: =COUNTIF($I$177:$I$208,I72) -> 1 | AJ72: =COUNTIF($C$176:$C$205,C72) -> 1 | AK72: =COUNTIF($C$232:$C$270,C72) -> 1 | AL72: =_xlfn.DAYS(DATE(AH72,AG72*3-2,1),DATE(RIGHT(B72,4),MID(B72,4,2),LEFT(B72,2))) -> 467
B73: 23.12.2024 | C73: Australia | D73: 108 | E73: AOM5000 | F73: 30 | G73: Bright Energy | H73: 30 | I73: V136-3.6MW | J73: 136 | K73: 3.6 | AG73: 2 | AH73: 2026 | AI73: =COUNTIF($I$177:$I$208,I73) -> 1 | AJ73: =COUNTIF($C$176:$C$205,C73) -> 1 | AK73: =COUNTIF($C$232:$C$270,C73) -> 1 | AL73: =_xlfn.DAYS(DATE(AH73,AG73*3-2,1),DATE(RIGHT(B73,4),MID(B73,4,2),LEFT(B73,2))) -> 464
B74: 23.12.2024 | C74: Poland | D74: 29 | E74: AOM5000 | F74: 20 | G74: Eurowind energy | H74: 13 | I74: V110-2.2MW | J74: 110 | K74: 2.2 | AG74: 1 | AH74: 2026 | AI74: =COUNTIF($I$177:$I$208,I74) -> 1 | AJ74: =COUNTIF($C$176:$C$205,C74) -> 1 | AK74: =COUNTIF($C$232:$C$270,C74) -> 1 | AL74: =_xlfn.DAYS(DATE(AH74,AG74*3-2,1),DATE(RIGHT(B74,4),MID(B74,4,2),LEFT(B74,2))) -> 374
B75: 23.12.2024 | C75: Denmark | D75: 27 | E75: AOM5000 | G75: Hallendrup gruppen | H75: 6 | I75: V136-4.5MW | J75: 136 | K75: 4.5 | AG75: 4 | AH75: 2025 | AI75: =COUNTIF($I$177:$I$208,I75) -> 1 | AJ75: =COUNTIF($C$176:$C$205,C75) -> 1 | AK75: =COUNTIF($C$232:$C$270,C75) -> 1 | AL75: =_xlfn.DAYS(DATE(AH75,AG75*3-2,1),DATE(RIGHT(B75,4),MID(B75,4,2),LEFT(B75,2))) -> 282
B76: 23.12.2024 | C76: Italy | D76: 32 | E76: AOM5000 | F76: 20 | G76: GR value | H76: 5 | I76: V162-6.2MW | J76: 162 | K76: 6.2 | AG76: 3 | AH76: 2025 | AI76: =COUNTIF($I$177:$I$208,I76) -> 1 | AJ76: =COUNTIF($C$176:$C$205,C76) -> 1 | AK76: =COUNTIF($C$232:$C$270,C76) -> 1 | AL76: =_xlfn.DAYS(DATE(AH76,AG76*3-2,1),DATE(RIGHT(B76,4),MID(B76,4,2),LEFT(B76,2))) -> 190
B77: 23.12.2024 | C77: Portugal | D77: 63 | E77: AOM5000 | F77: 30 | H77: 14 | I77: V163-4.5MW | J77: 163 | K77: 4.5 | AG77: 3 | AH77: 2025 | AI77: =COUNTIF($I$177:$I$208,I77) -> 1 | AJ77: =COUNTIF($C$176:$C$205,C77) -> 1 | AK77: =COUNTIF($C$232:$C$270,C77) -> 1 | AL77: =_xlfn.DAYS(DATE(AH77,AG77*3-2,1),DATE(RIGHT(B77,4),MID(B77,4,2),LEFT(B77,2))) -> 190
B78: 24.12.2024 | C78: Australia | D78: 105 | E78: AOM5000 | F78: 30 | G78: King Rocks wind farm | H78: 17 | I78: V162-6.2MW | J78: 162 | K78: 6.2 | AG78: 3 | AH78: 2026 | AI78: =COUNTIF($I$177:$I$208,I78) -> 1 | AJ78: =COUNTIF($C$176:$C$205,C78) -> 1 | AK78: =COUNTIF($C$232:$C$270,C78) -> 1 | AL78: =_xlfn.DAYS(DATE(AH78,AG78*3-2,1),DATE(RIGHT(B78,4),MID(B78,4,2),LEFT(B78,2))) -> 554
B79: 26.12.2024 | C79: Spain | D79: 99 | E79: AOM4000 | F79: 10 | G79: Iberdrola | H79: 11 | I79: V150-4.5MW | J79: 150 | K79: 4.5 | AG79: 2 | AH79: 2025 | AI79: =COUNTIF($I$177:$I$208,I79) -> 1 | AJ79: =COUNTIF($C$176:$C$205,C79) -> 1 | AK79: =COUNTIF($C$232:$C$270,C79) -> 1 | AL79: =_xlfn.DAYS(DATE(AH79,AG79*3-2,1),DATE(RIGHT(B79,4),MID(B79,4,2),LEFT(B79,2))) -> 96
B80: 27.12.2024 | C80: Germany | D80: 86 | E80: AOM5000 | F80: 25 | G80: Oberhessische | H80: 12 | I80: V172-7.2MW | J80: 172 | K80: 7.2 | AG80: 2 | AH80: 2026 | AI80: =COUNTIF($I$177:$I$208,I80) -> 1 | AJ80: =COUNTIF($C$176:$C$205,C80) -> 1 | AK80: =COUNTIF($C$232:$C$270,C80) -> 1 | AL80: =_xlfn.DAYS(DATE(AH80,AG80*3-2,1),DATE(RIGHT(B80,4),MID(B80,4,2),LEFT(B80,2))) -> 460
B81: 27.12.2024 | C81: Germany | D81: 48 | E81: AOM5000 | F81: 20 | G81: Windpark Ohrenbach | H81: 8 | I81: V162-6.0MW | J81: 162 | K81: 6 | AG81: 2 | AH81: 2026 | AI81: =COUNTIF($I$177:$I$208,I81) -> 1 | AJ81: =COUNTIF($C$176:$C$205,C81) -> 1 | AK81: =COUNTIF($C$232:$C$270,C81) -> 1 | AL81: =_xlfn.DAYS(DATE(AH81,AG81*3-2,1),DATE(RIGHT(B81,4),MID(B81,4,2),LEFT(B81,2))) -> 460
B82: 27.12.2024 | C82: Latvia | D82: 64 | E82: AOM5000 | F82: 35 | G82: Ventspils wind | H82: 10 | I82: V162-6.4MW | J82: 162 | K82: 6.4 | AG82: 1 | AH82: 2026 | AI82: =COUNTIF($I$177:$I$208,I82) -> 1 | AJ82: =COUNTIF($C$176:$C$205,C82) -> 1 | AK82: =COUNTIF($C$232:$C$270,C82) -> 1 | AL82: =_xlfn.DAYS(DATE(AH82,AG82*3-2,1),DATE(RIGHT(B82,4),MID(B82,4,2),LEFT(B82,2))) -> 370
B83: 27.12.2024 | C83: Japan | D83: 315 | G83: Oga Katagami | H83: 21 | I83: V236-15.0MW | J83: 236 | K83: 15 | AG83: 2 | AH83: 2026 | AI83: =COUNTIF($I$177:$I$208,I83) -> 1 | AJ83: =COUNTIF($C$176:$C$205,C83) -> 1 | AK83: =COUNTIF($C$232:$C$270,C83) -> 1 | AL83: =_xlfn.DAYS(DATE(AH83,AG83*3-2,1),DATE(RIGHT(B83,4),MID(B83,4,2),LEFT(B83,2))) -> 460
B84: 30.12.2024 | C84: United states | D84: 163 | E84: AOM5000 | F84: 10 | G84: Clearway energy group | H84: 38 | I84: V117-4.2MW | J84: 117 | K84: 4.2 | AG84: 3 | AH84: 2026 | AI84: =COUNTIF($I$177:$I$208,I84) -> 1 | AJ84: =COUNTIF($C$176:$C$205,C84) -> 1 | AK84: =COUNTIF($C$232:$C$270,C84) -> 1 | AL84: =_xlfn.DAYS(DATE(AH84,AG84*3-2,1),DATE(RIGHT(B84,4),MID(B84,4,2),LEFT(B84,2))) -> 548
B85: 30.12.2024 | C85: Denmark | D85: 50 | E85: AOM5000 | F85: 20 | G85: K/S energipark | H85: 11 | I85: V136-4.5MW | J85: 136 | K85: 4.5 | AG85: 1 | AH85: 2026 | AI85: =COUNTIF($I$177:$I$208,I85) -> 1 | AJ85: =COUNTIF($C$176:$C$205,C85) -> 1 | AK85: =COUNTIF($C$232:$C$270,C85) -> 1 | AL85: =_xlfn.DAYS(DATE(AH85,AG85*3-2,1),DATE(RIGHT(B85,4),MID(B85,4,2),LEFT(B85,2))) -> 367
B86: 30.12.2024 | C86: Guatemala | D86: 63 | E86: AOM5000 | F86: 5 | H86: 14 | I86: V150-4.5MW | J86: 150 | K86: 4.5 | AG86: 4 | AH86: 2026 | AI86: =COUNTIF($I$177:$I$208,I86) -> 1 | AJ86: =COUNTIF($C$176:$C$205,C86) -> 1 | AK86: =COUNTIF($C$232:$C$270,C86) -> 1 | AL86: =_xlfn.DAYS(DATE(AH86,AG86*3-2,1),DATE(RIGHT(B86,4),MID(B86,4,2),LEFT(B86,2))) -> 640
B87: 30.12.2024 | C87: South Africa | D87: 95 | E87: AOM5000 | F87: 20 | H87: 21 | I87: V150-4.5MW | J87: 150 | K87: 4.5 | AG87: 2 | AH87: 2026 | AI87: =COUNTIF($I$177:$I$208,I87) -> 1 | AJ87: =COUNTIF($C$176:$C$205,C87) -> 1 | AK87: =COUNTIF($C$232:$C$270,C87) -> 1 | AL87: =_xlfn.DAYS(DATE(AH87,AG87*3-2,1),DATE(RIGHT(B87,4),MID(B87,4,2),LEFT(B87,2))) -> 457
B88: 30.12.2024 | C88: France | D88: 55 | H88: 13 | I88: V136-4.2MW | J88: 136 | K88: 4.2 | AG88: 2 | AH88: 2025 | AI88: =COUNTIF($I$177:$I$208,I88) -> 1 | AJ88: =COUNTIF($C$176:$C$205,C88) -> 1 | AK88: =COUNTIF($C$232:$C$270,C88) -> 1 | AL88: =_xlfn.DAYS(DATE(AH88,AG88*3-2,1),DATE(RIGHT(B88,4),MID(B88,4,2),LEFT(B88,2))) -> 92
B89: 30.12.2024 | C89: France | D89: 31 | E89: AOM5000 | F89: 20 | H89: 5 | I89: V126-3.45MW | J89: 126 | K89: 3.6 | O89: 3 | P89: V150-4.2MW | Q89: 150 | R89: 4.2 | AG89: 2 | AH89: 2025 | AI89: =COUNTIF($I$177:$I$208,I89) -> 1 | AJ89: =COUNTIF($C$176:$C$205,C89) -> 1 | AK89: =COUNTIF($C$232:$C$270,C89) -> 1 | AL89: =_xlfn.DAYS(DATE(AH89,AG89*3-2,1),DATE(RIGHT(B89,4),MID(B89,4,2),LEFT(B89,2))) -> 92
B90: 30.12.2024 | C90: United states | D90: 203 | E90: AOM5000 | H90: 45 | I90: V163-4.5MW | J90: 163 | K90: 4.5 | AG90: 3 | AH90: 2026 | AI90: =COUNTIF($I$177:$I$208,I90) -> 1 | AJ90: =COUNTIF($C$176:$C$205,C90) -> 1 | AK90: =COUNTIF($C$232:$C$270,C90) -> 1 | AL90: =_xlfn.DAYS(DATE(AH90,AG90*3-2,1),DATE(RIGHT(B90,4),MID(B90,4,2),LEFT(B90,2))) -> 548
B91: 30.12.2024 | C91: United states | D91: 270 | E91: AOM5000 | H91: 60 | I91: V163-4.5MW | J91: 163 | K91: 4.5 | AG91: 2 | AH91: 2026 | AI91: =COUNTIF($I$177:$I$208,I91) -> 1 | AJ91: =COUNTIF($C$176:$C$205,C91) -> 1 | AK91: =COUNTIF($C$232:$C$270,C91) -> 1 | AL91: =_xlfn.DAYS(DATE(AH91,AG91*3-2,1),DATE(RIGHT(B91,4),MID(B91,4,2),LEFT(B91,2))) -> 457
B92: 30.12.2024 | C92: United states | D92: 203 | E92: AOM5000 | H92: 45 | I92: V163-4.5MW | J92: 163 | K92: 4.5 | AG92: 3 | AH92: 2027 | AI92: =COUNTIF($I$177:$I$208,I92) -> 1 | AJ92: =COUNTIF($C$176:$C$205,C92) -> 1 | AK92: =COUNTIF($C$232:$C$270,C92) -> 1 | AL92: =_xlfn.DAYS(DATE(AH92,AG92*3-2,1),DATE(RIGHT(B92,4),MID(B92,4,2),LEFT(B92,2))) -> 913
B93: 30.12.2024 | C93: Spain | D93: 49.5 | E93: AOM4000 | F93: 10 | H93: 11 | I93: V150-4.5MW | J93: 150 | K93: 4.5 | AG93: 3 | AH93: 2025 | AI93: =COUNTIF($I$177:$I$208,I93) -> 1 | AJ93: =COUNTIF($C$176:$C$205,C93) -> 1 | AK93: =COUNTIF($C$232:$C$270,C93) -> 1 | AL93: =_xlfn.DAYS(DATE(AH93,AG93*3-2,1),DATE(RIGHT(B93,4),MID(B93,4,2),LEFT(B93,2))) -> 183
B94: 30.12.2024 | C94: France | D94: 58.5 | E94: AOM5000 | F94: 25 | H94: 10 | I94: V136-3.45MW | J94: 136 | K94: 3 | O94: 8 | P94: V126-3.45MW | Q94: 126 | R94: 3.6 | AG94: 2 | AH94: 2026 | AI94: =COUNTIF($I$177:$I$208,I94) -> 1 | AJ94: =COUNTIF($C$176:$C$205,C94) -> 1 | AK94: =COUNTIF($C$232:$C$270,C94) -> 1 | AL94: =_xlfn.DAYS(DATE(AH94,AG94*3-2,1),DATE(RIGHT(B94,4),MID(B94,4,2),LEFT(B94,2))) -> 457
A95: =SUM(D55:D95) -> 6028 | B95: 30.12.2024 | C95: Italy | D95: 26 | E95: AOM4000 | F95: 10 | G95: Alerion San Marco | H95: 3 | I95: V150-6.0MW | J95: 150 | K95: 6 | O95: 2 | P95: V117-4.2MW | Q95: 117 | R95: 4.2 | AG95: 4 | AH95: 2025 | AI95: =COUNTIF($I$177:$I$208,I95) -> 1 | AJ95: =COUNTIF($C$176:$C$205,C95) -> 1 | AK95: =COUNTIF($C$232:$C$270,C95) -> 1 | AL95: =_xlfn.DAYS(DATE(AH95,AG95*3-2,1),DATE(RIGHT(B95,4),MID(B95,4,2),LEFT(B95,2))) -> 275
B111: Unannounced
B112: Q1 | D112: 797
B113: Q2 | D113: 694
B114: Q3 | D114: 690
B115: Q4 | D115: 490
...

Sheet OI 2023
B1: date | C1: country | D1: size [MW] | E1: Service scheme | F1: Service time [years] | G1: customer | H1: No_WTG_1 | I1: platform | J1: Rotor_1 | K1: MW_1 | L1: special mode_1 | M1: Tower height_1 | N1: Multi towerH | O1: No_WTG_2 | P1: Multi platform | Q1: Rotor_2 | R1: MW_2 | S1: special mode_2 | T1: Tower height_2 | U1: No_WTG_3 | V1: Multi platform | W1: Rotor | X1: MW | Y1: Tower height | Z1: Note | AA1: No_WTG_4 | AB1: Multi platform | AC1: Rotor | AD1: MW | AE1: Tower height | AF1: Note | AG1: delivery q | AH1: delivery y | AI1: platform check | AJ1: country check | AL1: Delivery days
B2: 10.03.2023 | C2: Estonia | D2: 68 | E2: AOM5000 | F2: 20 | G2: Dirkshof Estonia OU | H2: 15 | I2: V150-4,5MW | J2: 150 | K2: 4.5 | AG2: 3 | AH2: 2023 | AI2: =COUNTIF($I$158:$I$188,I2) -> 0 | AJ2: =COUNTIF($C$157:$C$180,C2) -> 1 | AK2: =COUNTIF($C$214:$C$239,C2) -> 1 | AL2: =_xlfn.DAYS(DATE(AH2,AG2*3-2,1),DATE(RIGHT(B2,4),MID(B2,4,2),LEFT(B2,2))) -> 113
B3: 08.03.2023 | C3: Argentina | D3: 95 | E3: AOM5000 | F3: 20 | G3: Pampa Energia | H3: 21 | I3: V150-4.5MW | J3: 150 | K3: 4.5 | AG3: 4 | AH3: 2023 | AI3: =COUNTIF($I$158:$I$188,I3) -> 1 | AJ3: =COUNTIF($C$157:$C$180,C3) -> 1 | AK3: =COUNTIF($C$213:$C$238,C3) -> 1 | AL3: =_xlfn.DAYS(DATE(AH3,AG3*3-2,1),DATE(RIGHT(B3,4),MID(B3,4,2),LEFT(B3,2))) -> 207
B4: 08.03.2023 | C4: United states | D4: 56 | E4: AOM5000 | F4: 10 | G4: RPM Access | H4: 13 | I4: V150-4.2MW | J4: 150 | K4: 4.3 | L4: opt 4.3MW | AG4: 4 | AH4: 2023 | AI4: =COUNTIF($I$158:$I$188,I4) -> 1 | AJ4: =COUNTIF($C$157:$C$180,C4) -> 1 | AK4: =COUNTIF($C$213:$C$238,C4) -> 1 | AL4: =_xlfn.DAYS(DATE(AH4,AG4*3-2,1),DATE(RIGHT(B4,4),MID(B4,4,2),LEFT(B4,2))) -> 207
B5: 14.03.2023 | C5: South Africa | D5: 373 | E5: AOM5000 | F5: 15 | G5: Red Rocket | H5: 64 | I5: V150-4.5MW | J5: 150 | K5: 4.5 | O5: 12 | P5: V163-4.5MW | Q5: 163 | R5: 4.5 | U5: 5 | V5: V162-6.2MW | W5: 162 | X5: 6.2 | AG5: 3 | AH5: 2024 | AI5: =COUNTIF($I$158:$I$188,I5) -> 1 | AJ5: =COUNTIF($C$157:$C$180,C5) -> 1 | AK5: =COUNTIF($C$213:$C$238,C5) -> 1 | AL5: =_xlfn.DAYS(DATE(AH5,AG5*3-2,1),DATE(RIGHT(B5,4),MID(B5,4,2),LEFT(B5,2))) -> 475
B6: 17.03.2023 | C6: Finland | D6: 50 | E6: AOM5000 | F6: 20 | G6: Prime Capital | H6: 8 | I6: V162-6.2MW | J6: 162 | K6: 6.2 | AG6: 3 | AH6: 2023 | AI6: =COUNTIF($I$158:$I$188,I6) -> 1 | AJ6: =COUNTIF($C$157:$C$180,C6) -> 1 | AK6: =COUNTIF($C$213:$C$238,C6) -> 1 | AL6: =_xlfn.DAYS(DATE(AH6,AG6*3-2,1),DATE(RIGHT(B6,4),MID(B6,4,2),LEFT(B6,2))) -> 106
B7: 17.03.2023 | C7: Germany | D7: 50 | E7: AOM5000 | F7: 25 | G7: Energieparl Bad Lauchstädt | H7: 8 | I7: V162-6.2MW | J7: 162 | K7: 6.2 | M7: 169 | AG7: 1 | AH7: 2024 | AI7: =COUNTIF($I$158:$I$188,I7) -> 1 | AJ7: =COUNTIF($C$157:$C$180,C7) -> 1 | AK7: =COUNTIF($C$213:$C$238,C7) -> 1 | AL7: =_xlfn.DAYS(DATE(AH7,AG7*3-2,1),DATE(RIGHT(B7,4),MID(B7,4,2),LEFT(B7,2))) -> 290
B8: 30.03.2023 | C8: Brazil | D8: 1310 | E8: AOM5000 | F8: 25 | G8: Casa dos Ventos Energias Renovavies | H8: =168+123 -> 291 | I8: V150-4.5MW | J8: 150 | K8: 4.5 | AG8: 3 | AH8: 2024 | AI8: =COUNTIF($I$158:$I$188,I8) -> 1 | AJ8: =COUNTIF($C$157:$C$180,C8) -> 1 | AK8: =COUNTIF($C$213:$C$238,C8) -> 1 | AL8: =_xlfn.DAYS(DATE(AH8,AG8*3-2,1),DATE(RIGHT(B8,4),MID(B8,4,2),LEFT(B8,2))) -> 459
B9: 30.03.2023 | C9: Argentina | D9: 162 | E9: AOM5000 | F9: 25 | G9: Gebbeia | H9: 36 | I9: V150-4.5MW | J9: 150 | K9: 4.5 | AG9: 3 | AH9: 2023 | AI9: =COUNTIF($I$158:$I$188,I9) -> 1 | AJ9: =COUNTIF($C$157:$C$180,C9) -> 1 | AK9: =COUNTIF($C$213:$C$238,C9) -> 1 | AL9: =_xlfn.DAYS(DATE(AH9,AG9*3-2,1),DATE(RIGHT(B9,4),MID(B9,4,2),LEFT(B9,2))) -> 93
B10: 31.03.2023 | C10: Argentina | D10: 155 | E10: AOM5000 | F10: 25 | H10: 25 | I10: V162-6.2MW | J10: 162 | K10: 6.2 | AG10: 4 | AH10: 2023 | AI10: =COUNTIF($I$158:$I$188,I10) -> 1 | AJ10: =COUNTIF($C$157:$C$180,C10) -> 1 | AK10: =COUNTIF($C$213:$C$238,C10) -> 1 | AL10: =_xlfn.DAYS(DATE(AH10,AG10*3-2,1),DATE(RIGHT(B10,4),MID(B10,4,2),LEFT(B10,2))) -> 184
B11: 31.03.2023 | C11: Germany | D11: 63 | E11: AOM4000 | F11: 20 | G11: JUWI GmbH | H11: 5 | I11: V162-5.6MW | J11: 162 | K11: 5.6 | O11: 7 | P11: V126-3.45MW | Q11: 126 | R11: 3.45 | U11: 1 | V11: V150-5.6MW | W11: 150 | X11: 5.6 | AG11: 1 | AH11: 2024 | AI11: =COUNTIF($I$158:$I$188,I11) -> 1 | AJ11: =COUNTIF($C$157:$C$180,C11) -> 1 | AK11: =COUNTIF($C$213:$C$238,C11) -> 1 | AL11: =_xlfn.DAYS(DATE(AH11,AG11*3-2,1),DATE(RIGHT(B11,4),MID(B11,4,2),LEFT(B11,2))) -> 276
B12: 31.03.2023 | C12: Spain | D12: 140 | E12: AOM4000 | F12: 10 | G12: Estudio y Proyectos | H12: 20 | I12: V163-4.5MW | J12: 163 | K12: 4.5 | O12: 11 | P12: V150-4.5MW | Q12: 150 | R12: 4.5 | AG12: 2 | AH12: 2024 | AI12: =COUNTIF($I$158:$I$188,I12) -> 1 | AJ12: =COUNTIF($C$157:$C$180,C12) -> 1 | AK12: =COUNTIF($C$213:$C$238,C12) -> 1 | AL12: =_xlfn.DAYS(DATE(AH12,AG12*3-2,1),DATE(RIGHT(B12,4),MID(B12,4,2),LEFT(B12,2))) -> 367
B13: 31.03.2023 | C13: India | D13: 130 | G13: Vibrant Energy | H13: 36 | I13: V155-3.6MW | J13: 155 | K13: 3.6 | AG13: 4 | AH13: 2023 | AI13: =COUNTIF($I$158:$I$188,I13) -> 1 | AJ13: =COUNTIF($C$157:$C$180,C13) -> 1 | AK13: =COUNTIF($C$213:$C$238,C13) -> 1 | AL13: =_xlfn.DAYS(DATE(AH13,AG13*3-2,1),DATE(RIGHT(B13,4),MID(B13,4,2),LEFT(B13,2))) -> 184
A14: =SUM(D2:D14) -> 3022 | B14: 31.03.2023 | C14: United states | D14: 370 | G14: Xcel Energy | H14: =97+71 -> 168 | I14: V110-2.0MW | J14: 110 | K14: 2.2 | L14: opt 2.2MW | AG14: 2 | AH14: 2025 | AI14: =COUNTIF($I$158:$I$188,I14) -> 1 | AJ14: =COUNTIF($C$157:$C$180,C14) -> 1 | AK14: =COUNTIF($C$213:$C$238,C14) -> 1 | AL14: =_xlfn.DAYS(DATE(AH14,AG14*3-2,1),DATE(RIGHT(B14,4),MID(B14,4,2),LEFT(B14,2))) -> 732
B15: 25.04.2023 | C15: Japan | D15: 238 | E15: AOM5000 | G15: Hibiki Wind Energy | H15: 25 | I15: V174-9.5MW | J15: 174 | K15: 9.5 | AG15: 1 | AH15: 2025 | AI15: =COUNTIF($I$158:$I$188,I15) -> 1 | AJ15: =COUNTIF($C$157:$C$180,C15) -> 1 | AK15: =COUNTIF($C$213:$C$238,C15) -> 1 | AL15: =_xlfn.DAYS(DATE(AH15,AG15*3-2,1),DATE(RIGHT(B15,4),MID(B15,4,2),LEFT(B15,2))) -> 617
B16: 24.05.2023 | C16: Argentina | D16: 72 | E16: AOM5000 | F16: 30 | H16: 16 | I16: V150-4.5MW | J16: 150 | K16: 4.5 | AG16: 1 | AH16: 2024 | AI16: =COUNTIF($I$158:$I$188,I16) -> 1 | AJ16: =COUNTIF($C$157:$C$180,C16) -> 1 | AK16: =COUNTIF($C$213:$C$238,C16) -> 1 | AL16: =_xlfn.DAYS(DATE(AH16,AG16*3-2,1),DATE(RIGHT(B16,4),MID(B16,4,2),LEFT(B16,2))) -> 222
B17: 24.05.2023 | C17: Turkey | D17: 37 | E17: AOM4000 | F17: 10 | H17: 6 | I17: V162-6.2MW | J17: 162 | K17: 6.2 | AG17: 4 | AH17: 2023 | AI17: =COUNTIF($I$158:$I$188,I17) -> 1 | AJ17: =COUNTIF($C$157:$C$180,C17) -> 1 | AK17: =COUNTIF($C$213:$C$238,C17) -> 1 | AL17: =_xlfn.DAYS(DATE(AH17,AG17*3-2,1),DATE(RIGHT(B17,4),MID(B17,4,2),LEFT(B17,2))) -> 130
B18: 08.06.2023 | C18: Finland | D18: 161 | E18: AOM5000 | F18: 20 | G18: Neoen | H18: =17+9 -> 26 | I18: V162-6.2MW | J18: 162 | K18: 6.2 | AG18: 3 | AH18: 2024 | AI18: =COUNTIF($I$158:$I$188,I18) -> 1 | AJ18: =COUNTIF($C$157:$C$180,C18) -> 1 | AK18: =COUNTIF($C$213:$C$238,C18) -> 1 | AL18: =_xlfn.DAYS(DATE(AH18,AG18*3-2,1),DATE(RIGHT(B18,4),MID(B18,4,2),LEFT(B18,2))) -> 389
B19: 09.06.2023 | C19: UK | D19: 221 | E19: AOM5000 | F19: 30 | G19: North Kyle Wind Farm | H19: 49 | I19: V136-4.5MW | J19: 136 | K19: 4.5 | AG19: 2 | AH19: 2024 | AI19: =COUNTIF($I$158:$I$188,I19) -> 1 | AJ19: =COUNTIF($C$157:$C$180,C19) -> 1 | AK19: =COUNTIF($C$213:$C$238,C19) -> 1 | AL19: =_xlfn.DAYS(DATE(AH19,AG19*3-2,1),DATE(RIGHT(B19,4),MID(B19,4,2),LEFT(B19,2))) -> 297
B20: 16.06.2023 | C20: United states | D20: 139 | E20: AOM5000 | F20: 20 | G20: Vitol | H20: 68 | I20: V110-2.0MW | J20: 110 | K20: 2.05 | AG20: 2 | AH20: 2024 | AI20: =COUNTIF($I$158:$I$188,I20) -> 1 | AJ20: =COUNTIF($C$157:$C$180,C20) -> 1 | AK20: =COUNTIF($C$213:$C$238,C20) -> 1 | AL20: =_xlfn.DAYS(DATE(AH20,AG20*3-2,1),DATE(RIGHT(B20,4),MID(B20,4,2),LEFT(B20,2))) -> 290
B21: 28.06.2023 | C21: Italy | D21: 27 | E21: AOM5000 | F21: 35 | G21: Ox2 | H21: 6 | I21: V150-4.5MW | J21: 150 | K21: 4.5 | AG21: 2 | AH21: 2024 | AI21: =COUNTIF($I$158:$I$188,I21) -> 1 | AJ21: =COUNTIF($C$157:$C$180,C21) -> 1 | AK21: =COUNTIF($C$213:$C$238,C21) -> 1 | AL21: =_xlfn.DAYS(DATE(AH21,AG21*3-2,1),DATE(RIGHT(B21,4),MID(B21,4,2),LEFT(B21,2))) -> 278
B22: 30.06.2023 | C22: Greece | D22: 45 | E22: AOM4000 | G22: EDF | H22: 10 | I22: V136-4.5MW | J22: 136 | K22: 4.5 | AG22: 3 | AH22: 2024 | AI22: =COUNTIF($I$158:$I$188,I22) -> 1 | AJ22: =COUNTIF($C$157:$C$180,C22) -> 1 | AK22: =COUNTIF($C$213:$C$238,C22) -> 1 | AL22: =_xlfn.DAYS(DATE(AH22,AG22*3-2,1),DATE(RIGHT(B22,4),MID(B22,4,2),LEFT(B22,2))) -> 367
B23: 30.06.2023 | C23: Italy | D23: 74 | E23: AOM5000 | F23: 20 | G23: SIMIC | H23: 12 | I23: V162-6.2MW | J23: 162 | K23: 6.2 | AG23: 2 | AH23: 2024 | AI23: =COUNTIF($I$158:$I$188,I23) -> 1 | AJ23: =COUNTIF($C$157:$C$180,C23) -> 1 | AK23: =COUNTIF($C$213:$C$238,C23) -> 1 | AL23: =_xlfn.DAYS(DATE(AH23,AG23*3-2,1),DATE(RIGHT(B23,4),MID(B23,4,2),LEFT(B23,2))) -> 276
B24: 30.06.2023 | C24: Spain | D24: 151 | E24: AOM5000 | F24: 15 | H24: 26 | I24: V136-4.5MW | J24: 136 | K24: 4.5 | AG24: 3 | AH24: 2024 | AI24: =COUNTIF($I$158:$I$188,I24) -> 1 | AJ24: =COUNTIF($C$157:$C$180,C24) -> 1 | AK24: =COUNTIF($C$213:$C$238,C24) -> 1 | AL24: =_xlfn.DAYS(DATE(AH24,AG24*3-2,1),DATE(RIGHT(B24,4),MID(B24,4,2),LEFT(B24,2))) -> 367
B25: 30.06.2023 | C25: Japan | D25: 55 | E25: AOM5000 | F25: 20 | G25: Renova | H25: 13 | I25: V117-4.2MW | J25: 117 | K25: 4.2 | M25: 112 | AG25: 4 | AH25: 2024 | AI25: =COUNTIF($I$158:$I$188,I25) -> 1 | AJ25: =COUNTIF($C$157:$C$180,C25) -> 1 | AK25: =COUNTIF($C$213:$C$238,C25) -> 1 | AL25: =_xlfn.DAYS(DATE(AH25,AG25*3-2,1),DATE(RIGHT(B25,4),MID(B25,4,2),LEFT(B25,2))) -> 459
B26: 30.06.2023 | C26: Spain | D26: 100 | E26: AOM5000 | F26: 25 | H26: 20 | I26: V150-4.2MW | J26: 150 | K26: 4.2 | O26: 4 | P26: V150-4.2MW | Q26: 150 | R26: 4.2 | S26: Opt 4.0 | AG26: 2 | AH26: 2024 | AI26: =COUNTIF($I$158:$I$188,I26) -> 1 | AJ26: =COUNTIF($C$157:$C$180,C26) -> 1 | AK26: =COUNTIF($C$213:$C$238,C26) -> 1 | AL26: =_xlfn.DAYS(DATE(AH26,AG26*3-2,1),DATE(RIGHT(B26,4),MID(B26,4,2),LEFT(B26,2))) -> 276
B27: 30.06.2023 | C27: United states | D27: 423 | E27: AOM5000 | F27: 20 | H27: =D27/4 -> 105.75 | I27: 4MW | AG27: 1 | AH27: 2024 | AI27: =COUNTIF($I$158:$I$188,I27) -> 0 | AJ27: =COUNTIF($C$157:$C$180,C27) -> 1 | AK27: =COUNTIF($C$213:$C$238,C27) -> 1 | AL27: =_xlfn.DAYS(DATE(AH27,AG27*3-2,1),DATE(RIGHT(B27,4),MID(B27,4,2),LEFT(B27,2))) -> 185
A28: =SUM(D15:D28) -> 1802 | B28: 30.06.2023 | C28: United states | D28: 59 | E28: AOM5000 | G28: Greenbacker | H28: 14 | I28: V150-4.2MW | J28: 150 | K28: 4.2 | AG28: 2 | AH28: 2024 | AI28: =COUNTIF($I$158:$I$188,I28) -> 1 | AJ28: =COUNTIF($C$157:$C$180,C28) -> 1 | AK28: =COUNTIF($C$213:$C$238,C28) -> 1 | AL28: =_xlfn.DAYS(DATE(AH28,AG28*3-2,1),DATE(RIGHT(B28,4),MID(B28,4,2),LEFT(B28,2))) -> 276
B29: 03.08.2023 | C29: United states | D29: 189 | E29: AOM5000 | H29: 45 | I29: V150-4.2MW | J29: 150 | K29: 4.2 | AG29: 1 | AH29: 2024 | AI29: =COUNTIF($I$158:$I$188,I29) -> 1 | AJ29: =COUNTIF($C$157:$C$180,C29) -> 1 | AK29: =COUNTIF($C$213:$C$238,C29) -> 1 | AL29: =_xlfn.DAYS(DATE(AH29,AG29*3-2,1),DATE(RIGHT(B29,4),MID(B29,4,2),LEFT(B29,2))) -> 151
B30: 08.08.2023 | C30: Spain | D30: 50 | E30: AOM4000 | F30: 45 | G30: Sinia Renovables | H30: 11 | I30: V136-4.5MW | J30: 136 | K30: 4.5 | AG30: 2 | AH30: 2024 | AI30: =COUNTIF($I$158:$I$188,I30) -> 1 | AJ30: =COUNTIF($C$157:$C$180,C30) -> 1 | AK30: =COUNTIF($C$213:$C$238,C30) -> 1 | AL30: =_xlfn.DAYS(DATE(AH30,AG30*3-2,1),DATE(RIGHT(B30,4),MID(B30,4,2),LEFT(B30,2))) -> 237
B31: 15.08.2023 | C31: Canada | D31: 140 | E31: AOM5000 | F31: 10 | G31: Capital power | H31: 31 | I31: V150-4.5MW | J31: 150 | K31: 4.5 | AG31: 2 | AH31: 2024 | AI31: =COUNTIF($I$158:$I$188,I31) -> 1 | AJ31: =COUNTIF($C$157:$C$180,C31) -> 1 | AK31: =COUNTIF($C$213:$C$238,C31) -> 1 | AL31: =_xlfn.DAYS(DATE(AH31,AG31*3-2,1),DATE(RIGHT(B31,4),MID(B31,4,2),LEFT(B31,2))) -> 230
B32: 22.08.2023 | C32: United states | D32: 288 | E32: AOM5000 | H32: 64 | I32: V150-4.5MW | J32: 150 | K32: 4.5 | AG32: 2 | AH32: 2024 | AI32: =COUNTIF($I$158:$I$188,I32) -> 1 | AJ32: =COUNTIF($C$157:$C$180,C32) -> 1 | AK32: =COUNTIF($C$213:$C$238,C32) -> 1 | AL32: =_xlfn.DAYS(DATE(AH32,AG32*3-2,1),DATE(RIGHT(B32,4),MID(B32,4,2),LEFT(B32,2))) -> 223
B33: 23.08.2023 | C33: United states | D33: 158 | E33: AOM5000 | F33: 10 | H33: 72 | I33: V120-2.2MW | J33: 120 | K33: 2.2 | AG33: 4 | AH33: 2023 | AI33: =COUNTIF($I$158:$I$188,I33) -> 1 | AJ33: =COUNTIF($C$157:$C$180,C33) -> 1 | AK33: =COUNTIF($C$213:$C$238,C33) -> 1 | AL33: =_xlfn.DAYS(DATE(AH33,AG33*3-2,1),DATE(RIGHT(B33,4),MID(B33,4,2),LEFT(B33,2))) -> 39
B34: 01.09.2023 | C34: Germany | D34: 42 | E34: AOM4000 | F34: 20 | H34: 6 | I34: V150-6.0MW | J34: 150 | K34: 6 | O34: 1 | P34: V162-6.2MW | Q34: 162 | R34: 6 | S34: opt 6.0 | AG34: 1 | AH34: 2024 | AI34: =COUNTIF($I$158:$I$188,I34) -> 1 | AJ34: =COUNTIF($C$157:$C$180,C34) -> 1 | AK34: =COUNTIF($C$213:$C$238,C34) -> 1 | AL34: =_xlfn.DAYS(DATE(AH34,AG34*3-2,1),DATE(RIGHT(B34,4),MID(B34,4,2),LEFT(B34,2))) -> 122
B35: 01.09.2023 | C35: Germany | D35: 54 | E35: AOM5000 | F35: 25 | G35: Energiequelle | H35: 9 | I35: V162-6.2MW | J35: 162 | K35: 6 | L35: opt 6.0 | AG35: 3 | AH35: 2024 | AI35: =COUNTIF($I$158:$I$188,I35) -> 1 | AJ35: =COUNTIF($C$157:$C$180,C35) -> 1 | AK35: =COUNTIF($C$213:$C$238,C35) -> 1 | AL35: =_xlfn.DAYS(DATE(AH35,AG35*3-2,1),DATE(RIGHT(B35,4),MID(B35,4,2),LEFT(B35,2))) -> 304
B36: 13.09.2023 | C36: United states | D36: 243 | E36: AOM5000 | G36: RWE | H36: 54 | I36: V163-4.5MW | J36: 163 | K36: 4.5 | AG36: 2 | AH36: 2024 | AI36: =COUNTIF($I$158:$I$188,I36) -> 1 | AJ36: =COUNTIF($C$157:$C$180,C36) -> 1 | AK36: =COUNTIF($C$213:$C$238,C36) -> 1 | AL36: =_xlfn.DAYS(DATE(AH36,AG36*3-2,1),DATE(RIGHT(B36,4),MID(B36,4,2),LEFT(B36,2))) -> 201
B37: 19.09.2023 | C37: Denmark | D37: 27 | E37: AOM5000 | G37: HOFOR | H37: 6 | I37: V136-4.5MW | J37: 136 | K37: 4.5 | AG37: 4 | AH37: 2024 | AI37: =COUNTIF($I$158:$I$188,I37) -> 1 | AJ37: =COUNTIF($C$157:$C$180,C37) -> 1 | AK37: =COUNTIF($C$213:$C$238,C37) -> 1 | AL37: =_xlfn.DAYS(DATE(AH37,AG37*3-2,1),DATE(RIGHT(B37,4),MID(B37,4,2),LEFT(B37,2))) -> 378
B38: 20.09.2023 | C38: Austria | D38: 46 | E38: AOM4000 | F38: 25 | H38: 11 | I38: V136-4.2MW | J38: 136 | K38: 4.2 | AG38: 3 | AH38: 2024 | AI38: =COUNTIF($I$158:$I$188,I38) -> 1 | AJ38: =COUNTIF($C$157:$C$180,C38) -> 1 | AK38: =COUNTIF($C$213:$C$238,C38) -> 1 | AL38: =_xlfn.DAYS(DATE(AH38,AG38*3-2,1),DATE(RIGHT(B38,4),MID(B38,4,2),LEFT(B38,2))) -> 285
B39: 20.09.2023 | C39: United states | D39: 126 | E39: AOM5000 | G39: Apex clean Energy | H39: 30 | I39: V150-4.2MW | J39: 150 | K39: 4.2 | AG39: 2 | AH39: 2024 | AI39: =COUNTIF($I$158:$I$188,I39) -> 1 | AJ39: =COUNTIF($C$157:$C$180,C39) -> 1 | AK39: =COUNTIF($C$213:$C$238,C39) -> 1 | AL39: =_xlfn.DAYS(DATE(AH39,AG39*3-2,1),DATE(RIGHT(B39,4),MID(B39,4,2),LEFT(B39,2))) -> 194
B40: 26.09.2023 | C40: Canada | D40: 136 | E40: AOM5000 | H40: 22 | I40: V162-6.2MW | J40: 162 | K40: 6.2 | AG40: 3 | AH40: 2024 | AI40: =COUNTIF($I$158:$I$188,I40) -> 1 | AJ40: =COUNTIF($C$157:$C$180,C40) -> 1 | AK40: =COUNTIF($C$213:$C$238,C40) -> 1 | AL40: =_xlfn.DAYS(DATE(AH40,AG40*3-2,1),DATE(RIGHT(B40,4),MID(B40,4,2),LEFT(B40,2))) -> 279
B41: 28.09.2023 | C41: Sweden | D41: 147 | E41: AOM5000 | F41: 35 | G41: SR Energy | H41: 20 | I41: V162-6.2MW | J41: 162 | K41: 6.2 | O41: 5 | P41: V150-4.5MW | Q41: 150 | R41: 4.5 | AG41: 1 | AH41: 2025 | AI41: =COUNTIF($I$158:$I$188,I41) -> 1 | AJ41: =COUNTIF($C$157:$C$180,C41) -> 1 | AK41: =COUNTIF($C$213:$C$238,C41) -> 1 | AL41: =_xlfn.DAYS(DATE(AH41,AG41*3-2,1),DATE(RIGHT(B41,4),MID(B41,4,2),LEFT(B41,2))) -> 461
B42: 28.09.2023 | C42: Poland | D42: 1140 | E42: AOM5000 | F42: 15 | G42: ORLEN | H42: 76 | I42: V236-15.0MW | J42: 236 | K42: 15 | AG42: 1 | AH42: 2025 | AI42: =COUNTIF($I$158:$I$188,I42) -> 1 | AJ42: =COUNTIF($C$157:$C$180,C42) -> 1 | AK42: =COUNTIF($C$213:$C$238,C42) -> 1 | AL42: =_xlfn.DAYS(DATE(AH42,AG42*3-2,1),DATE(RIGHT(B42,4),MID(B42,4,2),LEFT(B42,2))) -> 461
B43: 29.09.2023 | C43: Japan | D43: 38 | E43: AOM5000 | F43: 20 | G43: Toda Corp | H43: 9 | I43: V117-4.2MW | J43: 117 | K43: 4.2 | AG43: 1 | AH43: 2026 | AI43: =COUNTIF($I$158:$I$188,I43) -> 1 | AJ43: =COUNTIF($C$157:$C$180,C43) -> 1 | AK43: =COUNTIF($C$213:$C$238,C43) -> 1 | AL43: =_xlfn.DAYS(DATE(AH43,AG43*3-2,1),DATE(RIGHT(B43,4),MID(B43,4,2),LEFT(B43,2))) -> 825
B44: 29.09.2023 | C44: Germany | D44: 62 | E44: AOM5000 | F44: 25 | G44: Burgerwind | H44: 10 | I44: V162-6.2MW | J44: 162 | K44: 6.2 | AG44: 2 | AH44: 2024 | AI44: =COUNTIF($I$158:$I$188,I44) -> 1 | AJ44: =COUNTIF($C$157:$C$180,C44) -> 1 | AK44: =COUNTIF($C$213:$C$238,C44) -> 1 | AL44: =_xlfn.DAYS(DATE(AH44,AG44*3-2,1),DATE(RIGHT(B44,4),MID(B44,4,2),LEFT(B44,2))) -> 185
B45: 29.09.2023 | C45: Turkey | D45: 25 | E45: AOM4000 | F45: 10 | G45: Sanko Holding | H45: 4 | I45: V162-6.2MW | J45: 162 | K45: 6.2 | AG45: 2 | AH45: 2024 | AI45: =COUNTIF($I$158:$I$188,I45) -> 1 | AJ45: =COUNTIF($C$157:$C$180,C45) -> 1 | AK45: =COUNTIF($C$213:$C$238,C45) -> 1 | AL45: =_xlfn.DAYS(DATE(AH45,AG45*3-2,1),DATE(RIGHT(B45,4),MID(B45,4,2),LEFT(B45,2))) -> 185
B46: 29.09.2023 | C46: Germany | D46: 960 | E46: AOM5000 | F46: 5 | G46: EnBW | H46: 64 | I46: V236-15.0MW | J46: 236 | K46: 15 | AG46: 2 | AH46: 2025 | AI46: =COUNTIF($I$158:$I$188,I46) -> 1 | AJ46: =COUNTIF($C$157:$C$180,C46) -> 1 | AK46: =COUNTIF($C$213:$C$238,C46) -> 1 | AL46: =_xlfn.DAYS(DATE(AH46,AG46*3-2,1),DATE(RIGHT(B46,4),MID(B46,4,2),LEFT(B46,2))) -> 550
B47: 29.09.2023 | C47: Italy | D47: 76 | E47: AOM5000 | F47: 10 | H47: 18 | I47: V150-4.2MW | J47: 150 | K47: 4.2 | AG47: 1 | AH47: 2024 | AI47: =COUNTIF($I$158:$I$188,I47) -> 1 | AJ47: =COUNTIF($C$157:$C$180,C47) -> 1 | AK47: =COUNTIF($C$213:$C$238,C47) -> 1 | AL47: =_xlfn.DAYS(DATE(AH47,AG47*3-2,1),DATE(RIGHT(B47,4),MID(B47,4,2),LEFT(B47,2))) -> 94
B48: 29.09.2023 | C48: United states | D48: 90 | E48: AOM5000 | H48: 20 | I48: V150-4.5MW | J48: 150 | K48: 4.5 | AG48: 2 | AH48: 2024 | AI48: =COUNTIF($I$158:$I$188,I48) -> 1 | AJ48: =COUNTIF($C$157:$C$180,C48) -> 1 | AK48: =COUNTIF($C$213:$C$238,C48) -> 1 | AL48: =_xlfn.DAYS(DATE(AH48,AG48*3-2,1),DATE(RIGHT(B48,4),MID(B48,4,2),LEFT(B48,2))) -> 185
A49: =SUM(D29:D49) -> 4044 | B49: 30.09.2023 | C49: Germany | D49: 7 | E49: AOM4000 | F49: 20 | H49: 1 | I49: V162-7.2MW | J49: 162 | K49: 7.2 | AG49: 1 | AH49: 2024 | AI49: =COUNTIF($I$158:$I$188,I49) -> 1 | AJ49: =COUNTIF($C$157:$C$180,C49) -> 1 | AK49: =COUNTIF($C$213:$C$238,C49) -> 1 | AL49: =_xlfn.DAYS(DATE(AH49,AG49*3-2,1),DATE(RIGHT(B49,4),MID(B49,4,2),LEFT(B49,2))) -> 93
B50: 05.10.2023 | C50: Poland | D50: 139 | E50: AOM5000 | G50: Eviva Drzezewo | H50: 23 | I50: V110-2.0MW | J50: 110 | K50: 2 | O50: 40 | P50: V100-2.0MW | Q50: 100 | R50: 2.2 | S50: opt 2.2 | AG50: 4 | AH50: 2024 | AI50: =COUNTIF($I$158:$I$188,I50) -> 1 | AJ50: =COUNTIF($C$157:$C$180,C50) -> 1 | AK50: =COUNTIF($C$213:$C$238,C50) -> 1 | AL50: =_xlfn.DAYS(DATE(AH50,AG50*3-2,1),DATE(RIGHT(B50,4),MID(B50,4,2),LEFT(B50,2))) -> 362
B51: 13.10.2023 | C51: Sweden | D51: 115 | E51: AOM5000 | F51: 35 | G51: OX2 | H51: 18 | I51: V162-6.2MW | J51: 162 | K51: 6.2 | L51: opt 6.4 | AG51: 3 | AH51: 2026 | AI51: =COUNTIF($I$158:$I$188,I51) -> 1 | AJ51: =COUNTIF($C$157:$C$180,C51) -> 1 | AK51: =COUNTIF($C$213:$C$238,C51) -> 1 | AL51: =_xlfn.DAYS(DATE(AH51,AG51*3-2,1),DATE(RIGHT(B51,4),MID(B51,4,2),LEFT(B51,2))) -> 992
B52: 31.10.2023 | C52: Germany | D52: 43 | E52: AOM5000 | F52: 25 | G52: Uhl Windkraft | H52: 6 | I52: V172-7.2MW | J52: 172 | K52: 7.2 | AG52: 2 | AH52: 2025 | AI52: =COUNTIF($I$158:$I$188,I52) -> 1 | AJ52: =COUNTIF($C$157:$C$180,C52) -> 1 | AK52: =COUNTIF($C$213:$C$238,C52) -> 1 | AL52: =_xlfn.DAYS(DATE(AH52,AG52*3-2,1),DATE(RIGHT(B52,4),MID(B52,4,2),LEFT(B52,2))) -> 518
B53: 03.11.2023 | C53: Germany | D53: 42 | E53: AOM5000 | F53: 20 | G53: Strom 2020 | H53: 7 | I53: V150-6.0MW | J53: 150 | K53: 6 | AG53: 1 | AH53: 2025 | AI53: =COUNTIF($I$158:$I$188,I53) -> 1 | AJ53: =COUNTIF($C$157:$C$180,C53) -> 1 | AK53: =COUNTIF($C$213:$C$238,C53) -> 1 | AL53: =_xlfn.DAYS(DATE(AH53,AG53*3-2,1),DATE(RIGHT(B53,4),MID(B53,4,2),LEFT(B53,2))) -> 425
B54: 14.11.2023 | C54: Sweden | D54: 67 | E54: AOM5000 | G54: Vattenfall | H54: 12 | I54: V150-6.0MW | J54: 150 | K54: 6 | AG54: 2 | AH54: 2025 | AI54: =COUNTIF($I$158:$I$188,I54) -> 1 | AJ54: =COUNTIF($C$157:$C$180,C54) -> 1 | AK54: =COUNTIF($C$213:$C$238,C54) -> 1 | AL54: =_xlfn.DAYS(DATE(AH54,AG54*3-2,1),DATE(RIGHT(B54,4),MID(B54,4,2),LEFT(B54,2))) -> 504
B55: 21.11.2023 | C55: United states | D55: 239 | E55: AOM5000 | H55: 53 | I55: V163-4.5MW | J55: 163 | K55: 4.5 | AG55: 4 | AH55: 2024 | AI55: =COUNTIF($I$158:$I$188,I55) -> 1 | AJ55: =COUNTIF($C$157:$C$180,C55) -> 1 | AK55: =COUNTIF($C$213:$C$238,C55) -> 1 | AL55: =_xlfn.DAYS(DATE(AH55,AG55*3-2,1),DATE(RIGHT(B55,4),MID(B55,4,2),LEFT(B55,2))) -> 315
B56: 23.11.2023 | C56: United states | D56: 270 | E56: AOM5000 | F56: 20 | H56: 60 | I56: V163-4.5MW | J56: 163 | K56: 4.5 | AG56: 3 | AH56: 2024 | AI56: =COUNTIF($I$158:$I$188,I56) -> 1 | AJ56: =COUNTIF($C$157:$C$180,C56) -> 1 | AK56: =COUNTIF($C$213:$C$238,C56) -> 1 | AL56: =_xlfn.DAYS(DATE(AH56,AG56*3-2,1),DATE(RIGHT(B56,4),MID(B56,4,2),LEFT(B56,2))) -> 221
B57: 27.11.2023 | C57: Germany | D57: 43 | E57: AOM5000 | F57: 25 | G57: SAB WindTeam | H57: 7 | I57: V162-6.2MW | J57: 162 | K57: 6.2 | AG57: 3 | AH57: 2024 | AI57: =COUNTIF($I$158:$I$188,I57) -> 1 | AJ57: =COUNTIF($C$157:$C$180,C57) -> 1 | AK57: =COUNTIF($C$213:$C$238,C57) -> 1 | AL57: =_xlfn.DAYS(DATE(AH57,AG57*3-2,1),DATE(RIGHT(B57,4),MID(B57,4,2),LEFT(B57,2))) -> 217
B58: 30.11.2023 | C58: United states | D58: 203 | E58: AOM5000 | H58: 45 | I58: V163-4.5MW | J58: 163 | K58: 4.5 | AG58: 4 | AH58: 2024 | AI58: =COUNTIF($I$158:$I$188,I58) -> 1 | AJ58: =COUNTIF($C$157:$C$180,C58) -> 1 | AK58: =COUNTIF($C$213:$C$238,C58) -> 1 | AL58: =_xlfn.DAYS(DATE(AH58,AG58*3-2,1),DATE(RIGHT(B58,4),MID(B58,4,2),LEFT(B58,2))) -> 306
B59: 01.12.2023 | C59: Japan | D59: 46 | E59: AOM4000 | G59: Eurus Energy | H59: 11 | I59: V117-4.2MW | J59: 117 | K59: 4.2 | AG59: 1 | AH59: 2025 | AI59: =COUNTIF($I$158:$I$188,I59) -> 1 | AJ59: =COUNTIF($C$157:$C$180,C59) -> 1 | AK59: =COUNTIF($C$213:$C$238,C59) -> 1 | AL59: =_xlfn.DAYS(DATE(AH59,AG59*3-2,1),DATE(RIGHT(B59,4),MID(B59,4,2),LEFT(B59,2))) -> 397
B60: 14.12.2023 | C60: Spain | D60: 31 | H60: 5 | I60: V162-6.2MW | J60: 162 | K60: 6.2 | AG60: 2 | AH60: 2024 | AI60: =COUNTIF($I$158:$I$188,I60) -> 1 | AJ60: =COUNTIF($C$157:$C$180,C60) -> 1 | AK60: =COUNTIF($C$213:$C$238,C60) -> 1 | AL60: =_xlfn.DAYS(DATE(AH60,AG60*3-2,1),DATE(RIGHT(B60,4),MID(B60,4,2),LEFT(B60,2))) -> 109
B61: 14.12.2023 | C61: Finland | D61: 186 | E61: AOM5000 | F61: 30 | G61: Ilmatar | H61: 30 | I61: V162-6.2MW | J61: 162 | K61: 6.2 | AG61: 3 | AH61: 2024 | AI61: =COUNTIF($I$158:$I$188,I61) -> 1 | AJ61: =COUNTIF($C$157:$C$180,C61) -> 1 | AK61: =COUNTIF($C$213:$C$238,C61) -> 1 | AL61: =_xlfn.DAYS(DATE(AH61,AG61*3-2,1),DATE(RIGHT(B61,4),MID(B61,4,2),LEFT(B61,2))) -> 200
B62: 20.12.2023 | C62: South Africa | D62: 108 | E62: AOM5000 | F62: 15 | G62: Red Rocket | H62: 24 | I62: V136-4.5MW | J62: 136 | K62: 4.5 | AG62: 3 | AH62: 2024 | AI62: =COUNTIF($I$158:$I$188,I62) -> 1 | AJ62: =COUNTIF($C$157:$C$180,C62) -> 1 | AK62: =COUNTIF($C$213:$C$238,C62) -> 1 | AL62: =_xlfn.DAYS(DATE(AH62,AG62*3-2,1),DATE(RIGHT(B62,4),MID(B62,4,2),LEFT(B62,2))) -> 194
B63: 21.12.2023 | C63: Lithuania | D63: 87 | E63: AOM5000 | F63: 35 | G63: UAB | H63: 14 | I63: V162-6.2MW | J63: 162 | K63: 6.2 | AG63: 1 | AH63: 2025 | AI63: =COUNTIF($I$158:$I$188,I63) -> 1 | AJ63: =COUNTIF($C$157:$C$180,C63) -> 1 | AK63: =COUNTIF($C$213:$C$238,C63) -> 1 | AL63: =_xlfn.DAYS(DATE(AH63,AG63*3-2,1),DATE(RIGHT(B63,4),MID(B63,4,2),LEFT(B63,2))) -> 377
B64: 21.12.2023 | C64: Germany | D64: 45 | E64: AOM4000 | F64: 20 | G64: BayWa | H64: 8 | I64: V162-5.6MW | J64: 162 | K64: 5.6 | AG64: 2 | AH64: 2025 | AI64: =COUNTIF($I$158:$I$188,I64) -> 1 | AJ64: =COUNTIF($C$157:$C$180,C64) -> 1 | AK64: =COUNTIF($C$213:$C$238,C64) -> 1 | AL64: =_xlfn.DAYS(DATE(AH64,AG64*3-2,1),DATE(RIGHT(B64,4),MID(B64,4,2),LEFT(B64,2))) -> 467
B65: 22.12.2023 | C65: United states | D65: 143 | E65: AOM5000 | H65: 34 | I65: V150-4.2MW | J65: 150 | K65: 4.2 | AG65: 3 | AH65: 2025 | AI65: =COUNTIF($I$158:$I$188,I65) -> 1 | AJ65: =COUNTIF($C$157:$C$180,C65) -> 1 | AK65: =COUNTIF($C$213:$C$238,C65) -> 1 | AL65: =_xlfn.DAYS(DATE(AH65,AG65*3-2,1),DATE(RIGHT(B65,4),MID(B65,4,2),LEFT(B65,2))) -> 557
B66: 22.12.2023 | C66: United states | D66: 401 | E66: AOM5000 | H66: 89 | I66: V150-4.5MW | J66: 150 | K66: 4.5 | AG66: 4 | AH66: 2024 | AI66: =COUNTIF($I$158:$I$188,I66) -> 1 | AJ66: =COUNTIF($C$157:$C$180,C66) -> 1 | AK66: =COUNTIF($C$213:$C$238,C66) -> 1 | AL66: =_xlfn.DAYS(DATE(AH66,AG66*3-2,1),DATE(RIGHT(B66,4),MID(B66,4,2),LEFT(B66,2))) -> 284
B67: 22.12.2023 | C67: Netherlands | D67: 780 | E67: AOM5000 | F67: 15 | G67: Ecowende | H67: 52 | I67: V236-15.0MW | J67: 236 | K67: 15 | AG67: 2 | AH67: 2026 | AI67: =COUNTIF($I$158:$I$188,I67) -> 1 | AJ67: =COUNTIF($C$157:$C$180,C67) -> 1 | AK67: =COUNTIF($C$213:$C$238,C67) -> 1 | AL67: =_xlfn.DAYS(DATE(AH67,AG67*3-2,1),DATE(RIGHT(B67,4),MID(B67,4,2),LEFT(B67,2))) -> 831
B68: 22.12.2023 | C68: United states | D68: 450 | E68: AOM5000 | F68: 10 | H68: 100 | I68: V163-4.5MW | J68: 163 | K68: 4.5 | AG68: 2 | AH68: 2025 | AI68: =COUNTIF($I$158:$I$188,I68) -> 1 | AJ68: =COUNTIF($C$157:$C$180,C68) -> 1 | AK68: =COUNTIF($C$213:$C$238,C68) -> 1 | AL68: =_xlfn.DAYS(DATE(AH68,AG68*3-2,1),DATE(RIGHT(B68,4),MID(B68,4,2),LEFT(B68,2))) -> 466
B69: 22.12.2023 | C69: United states | D69: 603 | E69: AOM5000 | F69: 10 | H69: 134 | I69: V163-4.5MW | J69: 163 | K69: 4.5 | AG69: 4 | AH69: 2025 | AI69: =COUNTIF($I$158:$I$188,I69) -> 1 | AJ69: =COUNTIF($C$157:$C$180,C69) -> 1 | AK69: =COUNTIF($C$213:$C$238,C69) -> 1 | AL69: =_xlfn.DAYS(DATE(AH69,AG69*3-2,1),DATE(RIGHT(B69,4),MID(B69,4,2),LEFT(B69,2))) -> 649
B70: 23.12.2023 | C70: United states | D70: 945 | E70: AOM5000 | F70: 10 | H70: 210 | I70: V163-4.5MW | J70: 163 | K70: 4.5 | AG70: 4 | AH70: 2026 | AI70: =COUNTIF($I$158:$I$188,I70) -> 1 | AJ70: =COUNTIF($C$157:$C$180,C70) -> 1 | AK70: =COUNTIF($C$213:$C$238,C70) -> 1 | AL70: =_xlfn.DAYS(DATE(AH70,AG70*3-2,1),DATE(RIGHT(B70,4),MID(B70,4,2),LEFT(B70,2))) -> 1013
B71: 26.12.2023 | C71: Australia | D71: 254 | E71: AOM5000 | F71: 30 | H71: 41 | I71: V162-6.2MW | J71: 162 | K71: 6.2 | AG71: 4 | AH71: 2024 | AI71: =COUNTIF($I$158:$I$188,I71) -> 1 | AJ71: =COUNTIF($C$157:$C$180,C71) -> 1 | AK71: =COUNTIF($C$213:$C$238,C71) -> 1 | AL71: =_xlfn.DAYS(DATE(AH71,AG71*3-2,1),DATE(RIGHT(B71,4),MID(B71,4,2),LEFT(B71,2))) -> 280
B72: 27.12.2023 | C72: United states | D72: 1089 | E72: AOM5000 | F72: 10 | H72: 242 | I72: V163-4.5MW | J72: 163 | K72: 4.5 | AG72: 1 | AH72: 2025 | AI72: =COUNTIF($I$158:$I$188,I72) -> 1 | AJ72: =COUNTIF($C$157:$C$180,C72) -> 1 | AK72: =COUNTIF($C$213:$C$238,C72) -> 1 | AL72: =_xlfn.DAYS(DATE(AH72,AG72*3-2,1),DATE(RIGHT(B72,4),MID(B72,4,2),LEFT(B72,2))) -> 371
B73: 29.12.2023 | C73: UK | D73: 47 | E73: AOM5000 | F73: 25 | G73: ERG | H73: 11 | I73: V117-4.2MW | J73: 117 | K73: 4.3 | L73: opt 4.3MW | AG73: 2 | AH73: 2025 | AI73: =COUNTIF($I$158:$I$188,I73) -> 1 | AJ73: =COUNTIF($C$157:$C$180,C73) -> 1 | AK73: =COUNTIF($C$213:$C$238,C73) -> 1 | AL73: =_xlfn.DAYS(DATE(AH73,AG73*3-2,1),DATE(RIGHT(B73,4),MID(B73,4,2),LEFT(B73,2))) -> 459
B74: 29.12.2023 | C74: South Africa | D74: 63 | E74: AOM4000 | F74: 20 | H74: 14 | I74: V150-4.5MW | J74: 150 | K74: 4.5 | AG74: 1 | AH74: 2024 | AI74: =COUNTIF($I$158:$I$188,I74) -> 1 | AJ74: =COUNTIF($C$157:$C$180,C74) -> 1 | AK74: =COUNTIF($C$213:$C$238,C74) -> 1 | AL74: =_xlfn.DAYS(DATE(AH74,AG74*3-2,1),DATE(RIGHT(B74,4),MID(B74,4,2),LEFT(B74,2))) -> 3
B75: 29.12.2023 | C75: Spain | D75: 37 | E75: AOM5000 | F75: 20 | H75: 6 | I75: V162-6.2MW | J75: 162 | K75: 6.2 | AG75: 3 | AH75: 2024 | AI75: =COUNTIF($I$158:$I$188,I75) -> 1 | AJ75: =COUNTIF($C$157:$C$180,C75) -> 1 | AK75: =COUNTIF($C$213:$C$238,C75) -> 1 | AL75: =_xlfn.DAYS(DATE(AH75,AG75*3-2,1),DATE(RIGHT(B75,4),MID(B75,4,2),LEFT(B75,2))) -> 185
B76: 29.12.2023 | C76: Germany | D76: 42 | E76: AOM4000 | F76: 20 | G76: WindStrom | H76: 4 | I76: V162-6.2MW | J76: 162 | K76: 6.2 | O76: 3 | P76: V162-5.6MW | Q76: 162 | R76: 5.6 | AG76: 1 | AH76: 2025 | AI76: =COUNTIF($I$158:$I$188,I76) -> 1 | AJ76: =COUNTIF($C$157:$C$180,C76) -> 1 | AK76: =COUNTIF($C$213:$C$238,C76) -> 1 | AL76: =_xlfn.DAYS(DATE(AH76,AG76*3-2,1),DATE(RIGHT(B76,4),MID(B76,4,2),LEFT(B76,2))) -> 369
B77: 29.12.2023 | C77: Italy | D77: 125 | E77: AOM4000 | H77: 19 | I77: V136-4.2MW | J77: 136 | K77: 4.2 | O77: 10 | P77: V136-4.5MW | Q77: 136 | R77: 4.5 | AG77: 1 | AH77: 2025 | AI77: =COUNTIF($I$158:$I$188,I77) -> 1 | AJ77: =COUNTIF($C$157:$C$180,C77) -> 1 | AK77: =COUNTIF($C$213:$C$238,C77) -> 1 | AL77: =_xlfn.DAYS(DATE(AH77,AG77*3-2,1),DATE(RIGHT(B77,4),MID(B77,4,2),LEFT(B77,2))) -> 369
B78: 29.12.2023 | C78: United states | D78: 167 | E78: AOM5000 | H78: 45 | I78: V150-4.2MW | J78: 150 | K78: 4.2 | AG78: 2 | AH78: 2025 | AI78: =COUNTIF($I$158:$I$188,I78) -> 1 | AJ78: =COUNTIF($C$157:$C$180,C78) -> 1 | AK78: =COUNTIF($C$213:$C$238,C78) -> 1 | AL78: =_xlfn.DAYS(DATE(AH78,AG78*3-2,1),DATE(RIGHT(B78,4),MID(B78,4,2),LEFT(B78,2))) -> 459
A79: =SUM(D50:D79) -> 6945 | B79: 30.12.2023 | C79: United states | D79: 135 | E79: AOM5000 | F79: 20 | H79: 30 | I79: V163-4.5MW | J79: 163 | K79: 4.5 | AG79: 3 | AH79: 2024 | AI79: =COUNTIF($I$158:$I$188,I79) -> 1 | AJ79: =COUNTIF($C$157:$C$180,C79) -> 1 | AK79: =COUNTIF($C$213:$C$238,C79) -> 1 | AL79: =_xlfn.DAYS(DATE(AH79,AG79*3-2,1),DATE(RIGHT(B79,4),MID(B79,4,2),LEFT(B79,2))) -> 184
AI80: =COUNTIF($I$158:$I$188,I80) -> 0 | AJ80: =COUNTIF($C$157:$C$180,C80) -> 0
AI81: =COUNTIF($I$158:$I$188,I81) -> 0 | AJ81: =COUNTIF($C$157:$C$180,C81) -> 0
AK82: average | AL82: =AVERAGE(AL2:AL79) -> 331.88462 | AM82: days
B92: Unannounced
B93: Q1 | D93: 281
B94: Q2 | D94: 531
B95: Q3 | D95: 458
B96: Q4 | D96: 1303
B97: Total | D97: =SUM(D2:D96) -> 18386
B98: Unannounced total | D98: =SUM(D93:D96) -> 2573 | E98: =D98/D97 -> 0.13994344
D127: =SUM(D93:D96) -> 2573 | E127: =D127/D97 -> 0.13994344
C148: Services Counters | D148: # | E148: MW | G148: Average | I148: Counters | L148: # sites | M148: # turbines | N148: MW
C149: # MW | D149: =SUM(M149:M151,T149:T151) -> 2490 | E149: =SUM(D2:D96) -> 18386 | G149: =E149/D149 -> 7.3839357 | I149: 2MW PL | L149: =COUNTIF(K2:K146,"<3")+COUNTIF(X2:X146,"<3")+COUNTIF(R2:R146,"<3") -> 5 | M149: =SUMIF(K2:K146,"<3",H2:H146)+SUMIF(R2:R146,"<3",O2:O146)+SUMIF(X2:X146,"<3",U2:U146) -> 371 | N149: =SUMIF(K2:K146,"<3",D2:D146) -> 806
C150: # of sites | D150: =COUNT(D2:D146) -> 85 | I150: 3MW PL | L150: =COUNTIF(K2:K146,"<4")+COUNTIF(X2:X146,"<4")+COUNTIF(R2:R146,"<4")-L149 -> 2 | M150: =SUMIF(K2:K146,"<4",H2:H146)+SUMIF(R2:R146,"<4",O2:O146)+SUMIF(X2:X146,"<4",U2:U146)-M149 -> 43 | N150: =SUMIF(K2:K146,"<4",D2:D146)-N149 -> 130
C151: # AOM5000 Energy based yield | D151: =COUNTIF(E2:E146,"AOM5000") -> 61 | E151: =SUMIF(E2:E90,"AOM5000",D2:D90) -> 14506 | F151: av.length AOM5000 | G151: =AVERAGEIF(E2:E146,"AOM5000",F2:F146) -> 20.666667 | I151: 4MW PL | L151: =COUNTIF(K2:K146,"<5")+COUNTIF(X2:X146,"<5")+COUNTIF(R2:R146,"<5")-L150-L149 -> 47 | M151: =SUMIF(K2:K146,"<5",H2:H146)+SUMIF(R2:R146,"<5",O2:O146)+SUMIF(X2:X146,"<5",U2:U146)-M150-M149 -> 2076 | N151: =SUMIF(K2:K146,"<5",D2:D146)-N150-N149 -> 9281
C152: # AOM4000 Time based yield | D152: =COUNTIF(E2:E146,"AOM4000") -> 14 | E152: =SUMIF(E2:E89,"AOM4000",D2:D89) -> 776 | F152: av.length AOM4000 | G152: =AVERAGEIF(E2:E146,"AOM4000",F2:F146) -> 20 | I152: 6MW PL | L152: =COUNTIF(K2:K146,"<7")+COUNTIF(X2:X146,"<7")+COUNTIF(R2:R146,"<7")-L151-L150-L149 -> 28 | M152: =SUMIF(K3:K147,"<7",H3:H147)+SUMIF(R3:R147,"<7",O3:O147)+SUMIF(X3:X147,"<7",U3:U147)-M151-M150-M149 -> 308 | N152: =SUMIF(K3:K147,"<7",D3:D147)-N151-N150-N149 -> 1937
C153: % AOM5000 of confirmed | D153: =D151/(D152+D151)*100 -> 81.333333 | E153: =E151/(E152+E151)*100 -> 94.922131 | I153: 7+ | L153: =COUNTIF(K2:K146,"<17")+COUNTIF(X2:X146,"<17")+COUNTIF(R2:R146,"<17")-L151-L150-L149-L152 -> 6 | M153: =SUMIF(K3:K147,"<17",H3:H147)+SUMIF(R3:R147,"<17",O3:O147)+SUMIF(X3:X147,"<17",U3:U147)-M151-M150-M149-M152 -> 224 | N153: =SUMIF(K3:K147,"<17",D3:D147)-N151-N150-N149-N152 -> 3168
C154: % of confirmed Energy yield SC | D154: =D151/D150*100 -> 71.764706 | E154: =E151/E149*100 -> 78.896987 | I154: # Power optimized sites | L154: =COUNTA(L2:L146) -> 5
F155: Confirmed service contracts
B156: Market share | C156: Country | D156: # sites | E156: MW | F156: AOM4000 | G156: AOM5000
A157: =COUNTIF($C$157:$C$180,C157) -> 1 | B157: =E157/$E$149*100 -> 36.908517 | C157: United states | D157: =COUNTIF(C$2:C$146,C157) -> 22 | E157: =SUMIF(C$2:C$88,C157,D$2:D$88) -> 6786 | F157: =SUMIFS($D$2:$D$146,$C$2:$C$146,C157,$E$2:$E$146,$F$156) -> 0 | G157: =SUMIFS($D$2:$D$146,$C$2:$C$146,C157,$E$2:$E$146,$G$156) -> 6416 | I157: Turbine Models | J157: # sold | K157: delivery days | M157: Turbine Models | N157: # sold
...

Sheet OI 2022
B1: date | C1: country | D1: size [MW] | E1: Service scheme | F1: Service time [years] | G1: customer | H1: # | I1: platform | J1: Rotor | K1: MW | L1: special mode | M1: Tower height | N1: Multi towerH | O1: # | P1: Multi platform | Q1: Rotor | R1: MW | S1: special mode | T1: Tower height | U1: # | V1: Multi platform | W1: Rotor | X1: MW | Y1: Tower height | Z1: Note | AA1: # | AB1: Multi platform | AC1: Rotor | AD1: MW | AE1: Tower height | AF1: Note | AG1: delivery q | AH1: delivery y | AI1: platform check | AJ1: country check | AL1: Delivery days
B2: 03.03.2022 | C2: Estonia | D2: 21 | E2: AOM5000 | F2: 30 | G2: Enefit Green | H2: 5 | I2: V136-4.2MW | J2: 136 | K2: 4.2 | M2: 82 | AG2: 1 | AH2: 2023 | AI2: =COUNTIF($I$158:$I$188,I2) -> 1 | AJ2: =COUNTIF($C$157:$C$188,C2) -> 1 | AK2: =COUNTIF($C$213:$C$246,C2) -> 1 | AL2: =_xlfn.DAYS(DATE(AH2,AG2*3-2,1),DATE(RIGHT(B2,4),MID(B2,4,2),LEFT(B2,2))) -> 304
B3: 03.03.2022 | C3: United states | D3: 171 | E3: AOM5000 | F3: 20 | G3: Cordelio Power | H3: 38 | I3: V150-4.5MW | J3: 150 | K3: 4.5 | AG3: 4 | AH3: 2022 | AI3: =COUNTIF($I$158:$I$188,I3) -> 1 | AJ3: =COUNTIF($C$157:$C$188,C3) -> 1 | AK3: =COUNTIF($C$213:$C$246,C3) -> 1 | AL3: =_xlfn.DAYS(DATE(AH3,AG3*3-2,1),DATE(RIGHT(B3,4),MID(B3,4,2),LEFT(B3,2))) -> 212
B4: 08.03.2022 | C4: Portugal | D4: 42 | E4: AOM5000 | F4: 15 | H4: 2 | I4: V162-6.2MW | J4: 117 | K4: 4.2 | O4: 6 | P4: V126-3.45MW | Q4: 126 | R4: 3.6 | S4: Opt 3.6MW | U4: 2 | V4: V117-4.2MW | W4: 117 | X4: 4.2 | AG4: 4 | AH4: 2022 | AI4: =COUNTIF($I$158:$I$188,I4) -> 1 | AJ4: =COUNTIF($C$157:$C$188,C4) -> 1 | AK4: =COUNTIF($C$213:$C$246,C4) -> 1 | AL4: =_xlfn.DAYS(DATE(AH4,AG4*3-2,1),DATE(RIGHT(B4,4),MID(B4,4,2),LEFT(B4,2))) -> 207
B5: 08.03.2022 | C5: Brazil | D5: 194 | E5: AOM5000 | F5: 5 | H5: 43 | I5: V150-4.5MW | J5: 150 | K5: 4.5 | AH5: 2024 | AI5: =COUNTIF($I$158:$I$188,I5) -> 1 | AJ5: =COUNTIF($C$157:$C$188,C5) -> 1 | AK5: =COUNTIF($C$213:$C$246,C5) -> 1 | AL5: =_xlfn.DAYS(DATE(AH5,AG5*3-2,1),DATE(RIGHT(B5,4),MID(B5,4,2),LEFT(B5,2))) -> 572
B6: 11.03.2022 | C6: Sweden | D6: 32 | E6: AOM5000 | F6: long-term | G6: Octopus Renewables | H6: 7 | I6: V150-4.5MW | J6: 150 | K6: 4.5 | AG6: 2 | AH6: 2023 | AI6: =COUNTIF($I$158:$I$188,I6) -> 1 | AJ6: =COUNTIF($C$157:$C$188,C6) -> 1 | AK6: =COUNTIF($C$213:$C$246,C6) -> 1 | AL6: =_xlfn.DAYS(DATE(AH6,AG6*3-2,1),DATE(RIGHT(B6,4),MID(B6,4,2),LEFT(B6,2))) -> 386
B7: 15.03.2022 | C7: Argentina | D7: 86 | E7: AOM5000 | F7: 30 | G7: PCR | H7: 19 | I7: V150-4.5MW | J7: 150 | K7: 4.5 | AG7: 1 | AH7: 2023 | AI7: =COUNTIF($I$158:$I$188,I7) -> 1 | AJ7: =COUNTIF($C$157:$C$188,C7) -> 1 | AK7: =COUNTIF($C$213:$C$246,C7) -> 1 | AL7: =_xlfn.DAYS(DATE(AH7,AG7*3-2,1),DATE(RIGHT(B7,4),MID(B7,4,2),LEFT(B7,2))) -> 292
B8: 18.03.2022 | C8: Italy | D8: 30 | E8: AOM5000 | F8: 15 | H8: 7 | I8: V150-4.2MW | J8: 150 | K8: 4.3 | L8: opt 4.3MW | AG8: 3 | AH8: 2023 | AI8: =COUNTIF($I$158:$I$188,I8) -> 1 | AJ8: =COUNTIF($C$157:$C$188,C8) -> 1 | AK8: =COUNTIF($C$213:$C$246,C8) -> 1 | AL8: =_xlfn.DAYS(DATE(AH8,AG8*3-2,1),DATE(RIGHT(B8,4),MID(B8,4,2),LEFT(B8,2))) -> 470
B9: 25.03.2022 | C9: India | D9: 51 | E9: nan | G9: O2 | H9: 23 | I9: V120-2.2MW | J9: 120 | K9: 2.2 | AG9: 3 | AH9: 2022 | AI9: =COUNTIF($I$158:$I$188,I9) -> 1 | AJ9: =COUNTIF($C$157:$C$188,C9) -> 1 | AK9: =COUNTIF($C$213:$C$246,C9) -> 1 | AL9: =_xlfn.DAYS(DATE(AH9,AG9*3-2,1),DATE(RIGHT(B9,4),MID(B9,4,2),LEFT(B9,2))) -> 98 | AP9: 2023 | AS9: 2024
B10: 25.03.2022 | C10: UK | D10: 36 | G10: Muirhall Energy | H10: 8 | I10: V136-4.5MW | J10: 136 | K10: 4.5 | AG10: 4 | AH10: 2022 | AI10: =COUNTIF($I$158:$I$188,I10) -> 1 | AJ10: =COUNTIF($C$157:$C$188,C10) -> 1 | AK10: =COUNTIF($C$213:$C$246,C10) -> 1 | AL10: =_xlfn.DAYS(DATE(AH10,AG10*3-2,1),DATE(RIGHT(B10,4),MID(B10,4,2),LEFT(B10,2))) -> 190 | AP10: 5 | AQ10: V136-4.2MW | AS10: 43 | AT10: V150-4.5MW
B11: 29.03.2022 | C11: Argentina | D11: 103 | E11: AOM5000 | F11: 20 | G11: Tenaris | H11: 24 | I11: V150-4.2MW | J11: 150 | K11: 4.2 | L11: opt 4.3MW | AG11: 3 | AH11: 2022 | AI11: =COUNTIF($I$158:$I$188,I11) -> 1 | AJ11: =COUNTIF($C$157:$C$188,C11) -> 1 | AK11: =COUNTIF($C$213:$C$246,C11) -> 1 | AL11: =_xlfn.DAYS(DATE(AH11,AG11*3-2,1),DATE(RIGHT(B11,4),MID(B11,4,2),LEFT(B11,2))) -> 94 | AP11: 7 | AQ11: V150-4.5MW | AS11: 31 | AT11: V174-9.5MW
B12: 29.03.2022 | C12: Vietnam | D12: 100 | E12: AOM4000 | F12: 15 | H12: 24 | I12: V150-4.2MW | J12: 150 | K12: 4.2 | L12: opt 4.0MW | AG12: 4 | AH12: 2022 | AI12: =COUNTIF($I$158:$I$188,I12) -> 1 | AJ12: =COUNTIF($C$157:$C$188,C12) -> 1 | AK12: =COUNTIF($C$213:$C$246,C12) -> 1 | AL12: =_xlfn.DAYS(DATE(AH12,AG12*3-2,1),DATE(RIGHT(B12,4),MID(B12,4,2),LEFT(B12,2))) -> 186 | AP12: 19 | AQ12: V150-4.5MW | AS12: 94 | AT12: V150-4.5MW
B13: 31.03.2022 | C13: Italy | D13: 97 | E13: AOM5000 | F13: multi-year | G13: ERG | H13: 12 | I13: V117-4.2MW | J13: 117 | K13: 4.2 | O13: 13 | P13: V117-3.45MW | Q13: 117 | R13: 3.45 | S13: opt 3.6MW | AG13: 1 | AH13: 2023 | AI13: =COUNTIF($I$158:$I$188,I13) -> 1 | AJ13: =COUNTIF($C$157:$C$188,C13) -> 1 | AK13: =COUNTIF($C$213:$C$246,C13) -> 1 | AL13: =_xlfn.DAYS(DATE(AH13,AG13*3-2,1),DATE(RIGHT(B13,4),MID(B13,4,2),LEFT(B13,2))) -> 276 | AP13: 7 | AQ13: V150-4.2MW | AS13: 3 | AT13: V164-10.0MW
B14: 31.03.2022 | C14: Australia | D14: 76 | H14: 18 | I14: V150-4.2MW | J14: 150 | K14: 4.2 | AG14: 1 | AH14: 2023 | AI14: =COUNTIF($I$158:$I$188,I14) -> 1 | AJ14: =COUNTIF($C$157:$C$188,C14) -> 1 | AK14: =COUNTIF($C$213:$C$246,C14) -> 1 | AL14: =_xlfn.DAYS(DATE(AH14,AG14*3-2,1),DATE(RIGHT(B14,4),MID(B14,4,2),LEFT(B14,2))) -> 276 | AP14: 12 | AQ14: V117-4.2MW | AS14: 19 | AT14: V150-4.5MW
B15: 31.03.2022 | C15: Finland | D15: 93 | E15: AOM5000 | F15: 30 | H15: 15 | I15: V162-6.2MW | J15: 162 | K15: 6.2 | AG15: 2 | AH15: 2023 | AI15: =COUNTIF($I$158:$I$188,I15) -> 1 | AJ15: =COUNTIF($C$157:$C$188,C15) -> 1 | AK15: =COUNTIF($C$213:$C$246,C15) -> 1 | AL15: =_xlfn.DAYS(DATE(AH15,AG15*3-2,1),DATE(RIGHT(B15,4),MID(B15,4,2),LEFT(B15,2))) -> 366 | AP15: 18 | AQ15: V150-4.2MW | AS15: 120 | AT15: V150-4.5MW
B16: 31.03.2022 | C16: Greece | D16: 36 | E16: AOM5000 | F16: 20 | H16: 8 | I16: V136-4.5MW | J16: 136 | K16: 4.5 | AG16: 2 | AH16: 2023 | AI16: =COUNTIF($I$158:$I$188,I16) -> 1 | AJ16: =COUNTIF($C$157:$C$188,C16) -> 1 | AK16: =COUNTIF($C$213:$C$246,C16) -> 1 | AL16: =_xlfn.DAYS(DATE(AH16,AG16*3-2,1),DATE(RIGHT(B16,4),MID(B16,4,2),LEFT(B16,2))) -> 366 | AP16: 15 | AQ16: V162-6.2MW | AS16: 12 | AT16: V117-4.2MW
B17: 31.03.2022 | C17: Italy | D17: 30 | E17: AOM4000 | F17: 10 | G17: A2A | H17: 3 | I17: V136-4.2MW | J17: 136 | K17: 4.2 | L17: opt 4.0MW | O17: 5 | P17: V136-3.45MW | Q17: 136 | R17: 3.6 | S17: Opt 3.6MW | AG17: 1 | AH17: 2023 | AI17: =COUNTIF($I$158:$I$188,I17) -> 1 | AJ17: =COUNTIF($C$157:$C$188,C17) -> 1 | AK17: =COUNTIF($C$213:$C$246,C17) -> 1 | AL17: =_xlfn.DAYS(DATE(AH17,AG17*3-2,1),DATE(RIGHT(B17,4),MID(B17,4,2),LEFT(B17,2))) -> 276 | AP17: 8 | AQ17: V136-4.5MW | AS17: 12 | AT17: V162-6.2MW
B18: 31.03.2022 | C18: France | D18: 31 | E18: AOM5000 | F18: 20 | G18: H2Air | H18: 3 | I18: V136-4.2MW | J18: 136 | K18: 4.2 | O18: 2 | P18: V126-3.45MW | Q18: 126 | R18: 3.45 | U18: 2 | V18: V112-3.45MW | W18: 112 | X18: 3.45 | AA18: 1 | AB18: V117-4.2MW | AC18: 117 | AD18: 4.2 | AG18: 4 | AH18: 2022 | AI18: =COUNTIF($I$158:$I$188,I18) -> 1 | AJ18: =COUNTIF($C$157:$C$188,C18) -> 1 | AK18: =COUNTIF($C$213:$C$246,C18) -> 1 | AL18: =_xlfn.DAYS(DATE(AH18,AG18*3-2,1),DATE(RIGHT(B18,4),MID(B18,4,2),LEFT(B18,2))) -> 184 | AP18: 3 | AQ18: V136-4.2MW
B19: 31.03.2022 | C19: Italy | D19: 25 | E19: AOM4000 | F19: 14 | G19: Inergia Spa | H19: 6 | I19: V136-4.2MW | J19: 136 | K19: 4.2 | AG19: 4 | AH19: 2022 | AI19: =COUNTIF($I$158:$I$188,I19) -> 1 | AJ19: =COUNTIF($C$157:$C$188,C19) -> 1 | AK19: =COUNTIF($C$213:$C$246,C19) -> 1 | AL19: =_xlfn.DAYS(DATE(AH19,AG19*3-2,1),DATE(RIGHT(B19,4),MID(B19,4,2),LEFT(B19,2))) -> 184 | AP19: 31 | AQ19: V174-9.5MW
B20: 31.03.2022 | C20: Taiwan | D20: 295 | E20: offshore | F20: 14 | G20: Foxwell Energy Corp | H20: 31 | I20: V174-9.5MW | J20: 174 | K20: 9.5 | AG20: 1 | AH20: 2023 | AI20: =COUNTIF($I$158:$I$188,I20) -> 1 | AJ20: =COUNTIF($C$157:$C$188,C20) -> 1 | AK20: =COUNTIF($C$213:$C$246,C20) -> 1 | AL20: =_xlfn.DAYS(DATE(AH20,AG20*3-2,1),DATE(RIGHT(B20,4),MID(B20,4,2),LEFT(B20,2))) -> 276 | AP20: 24 | AQ20: V136-4.2MW
B21: 31.03.2022 | C21: Taiwan | D21: 295 | E21: AOM5000 | F21: 15 | G21: CIP | H21: 31 | I21: V174-9.5MW | J21: 174 | K21: 9.5 | AG21: 1 | AH21: 2024 | AI21: =COUNTIF($I$158:$I$188,I21) -> 1 | AJ21: =COUNTIF($C$157:$C$188,C21) -> 1 | AK21: =COUNTIF($C$213:$C$246,C21) -> 1 | AL21: =_xlfn.DAYS(DATE(AH21,AG21*3-2,1),DATE(RIGHT(B21,4),MID(B21,4,2),LEFT(B21,2))) -> 641 | AP21: 33 | AQ21: V110-2.2MW
B22: 31.03.2022 | C22: India | D22: 54 | H22: 15 | I22: V155-3.6MW | J22: 155 | K22: 3.6 | AG22: 3 | AH22: 2022 | AI22: =COUNTIF($I$158:$I$188,I22) -> 1 | AJ22: =COUNTIF($C$157:$C$188,C22) -> 1 | AK22: =COUNTIF($C$213:$C$246,C22) -> 1 | AL22: =_xlfn.DAYS(DATE(AH22,AG22*3-2,1),DATE(RIGHT(B22,4),MID(B22,4,2),LEFT(B22,2))) -> 92 | AP22: 19 | AQ22: V150-4.5MW
B23: 31.03.2022 | C23: Portugal | D23: 50 | E23: AOM5000 | F23: 15 | H23: 11 | I23: V150-4.5MW | J23: 150 | K23: 4.5 | AG23: 4 | AH23: 2022 | AI23: =COUNTIF($I$158:$I$188,I23) -> 1 | AJ23: =COUNTIF($C$157:$C$188,C23) -> 1 | AK23: =COUNTIF($C$213:$C$246,C23) -> 1 | AL23: =_xlfn.DAYS(DATE(AH23,AG23*3-2,1),DATE(RIGHT(B23,4),MID(B23,4,2),LEFT(B23,2))) -> 184 | AP23: 9 | AQ23: V150-4.2MW
B24: 31.03.2022 | C24: United states | D24: 201 | E24: AOM5000 | F24: 15 | H24: 33 | I24: V162-6.2MW | J24: 162 | K24: 6 | L24: opt 6.0MW | O24: 1 | P24: V136-3.45MW | Q24: 136 | R24: 3.45 | AG24: 4 | AH24: 2022 | AI24: =COUNTIF($I$158:$I$188,I24) -> 1 | AJ24: =COUNTIF($C$157:$C$188,C24) -> 1 | AK24: =COUNTIF($C$213:$C$246,C24) -> 1 | AL24: =_xlfn.DAYS(DATE(AH24,AG24*3-2,1),DATE(RIGHT(B24,4),MID(B24,4,2),LEFT(B24,2))) -> 184 | AP24: 15 | AQ24: V162-6.2MW
A25: =SUM(D2:D25) -> 2179 | B25: 31.03.2022 | C25: France | D25: 30 | E25: AOM5000 | F25: 18 | G25: EDPR | H25: 3 | I25: V164-10.0MW | J25: 164 | K25: 10 | AI25: =COUNTIF($I$158:$I$188,I25) -> 1 | AJ25: =COUNTIF($C$157:$C$188,C25) -> 1 | AK25: =COUNTIF($C$213:$C$246,C25) -> 1 | AP25: 11 | AQ25: V126-3.45MW
B26: 05.05.2022 | C26: Brazil | D26: 423 | E26: AOM5000 | F26: 20 | G26: Pan American Energy Energias Renováveis | H26: 94 | I26: V150-4.5MW | J26: 150 | K26: 4.5 | AH26: 2024 | AI26: =COUNTIF($I$158:$I$188,I26) -> 1 | AJ26: =COUNTIF($C$157:$C$188,C26) -> 1 | AK26: =COUNTIF($C$213:$C$246,C26) -> 1 | AL26: =_xlfn.DAYS(DATE(AH26,AG26*3-2,1),DATE(RIGHT(B26,4),MID(B26,4,2),LEFT(B26,2))) -> 514 | AP26: 7 | AQ26: V136-4.2MW
B27: 05.05.2022 | C27: Argentina | D27: 81 | E27: AOM5000 | F27: 20 | G27: Aluar Aluminio Argentino S.A.I.C | H27: 18 | I27: V150-4.5MW | J27: 150 | K27: 4.5 | AG27: 4 | AH27: 2022 | AI27: =COUNTIF($I$158:$I$188,I27) -> 1 | AJ27: =COUNTIF($C$157:$C$188,C27) -> 1 | AK27: =COUNTIF($C$213:$C$246,C27) -> 1 | AL27: =_xlfn.DAYS(DATE(AH27,AG27*3-2,1),DATE(RIGHT(B27,4),MID(B27,4,2),LEFT(B27,2))) -> 149 | AP27: 2 | AQ27: V100-2.0MW
B28: 08.06.2022 | C28: Italy | D28: 101 | E28: AOM5000 | G28: ERG | H28: 24 | I28: V136-4.2MW | J28: 136 | K28: 4.2 | AG28: 2 | AH28: 2023 | AI28: =COUNTIF($I$158:$I$188,I28) -> 1 | AJ28: =COUNTIF($C$157:$C$188,C28) -> 1 | AK28: =COUNTIF($C$213:$C$246,C28) -> 1 | AL28: =_xlfn.DAYS(DATE(AH28,AG28*3-2,1),DATE(RIGHT(B28,4),MID(B28,4,2),LEFT(B28,2))) -> 297 | AP28: 59 | AQ28: V136-4.5MW
B29: 27.06.2022 | C29: France | D29: 30 | E29: AOM5000 | F29: 15 | G29: Qair, TotalEnergies, BW Ideol | H29: 3 | I29: V164-10.0MW | J29: 164 | K29: 10 | AF29: 18 km offshore | AG29: 3 | AH29: 2024 | AI29: =COUNTIF($I$158:$I$188,I29) -> 1 | AJ29: =COUNTIF($C$157:$C$188,C29) -> 1 | AK29: =COUNTIF($C$213:$C$246,C29) -> 1 | AL29: =_xlfn.DAYS(DATE(AH29,AG29*3-2,1),DATE(RIGHT(B29,4),MID(B29,4,2),LEFT(B29,2))) -> 735 | AP29: 10 | AQ29: V136-4.2MW
B30: 28.06.2022 | C30: Poland | D30: 73 | E30: AOM5000 | F30: 15 | G30: PAK-Polska Czysta Energia | H30: 33 | I30: V110-2.2MW | J30: 110 | K30: 2.2 | M30: 120 | AG30: 3 | AH30: 2023 | AI30: =COUNTIF($I$158:$I$188,I30) -> 1 | AJ30: =COUNTIF($C$157:$C$188,C30) -> 1 | AK30: =COUNTIF($C$213:$C$246,C30) -> 1 | AL30: =_xlfn.DAYS(DATE(AH30,AG30*3-2,1),DATE(RIGHT(B30,4),MID(B30,4,2),LEFT(B30,2))) -> 368 | AP30: 23 | AQ30: V150-4.5MW
B31: 29.06.2022 | C31: United states | D31: 86 | E31: AOM5000 | F31: 10 | G31: Sacramento Municipal Unitility District | H31: 19 | I31: V150-4.5MW | J31: 150 | K31: 4.5 | AG31: 4 | AH31: 2023 | AI31: =COUNTIF($I$158:$I$188,I31) -> 1 | AJ31: =COUNTIF($C$157:$C$188,C31) -> 1 | AK31: =COUNTIF($C$213:$C$246,C31) -> 1 | AL31: =_xlfn.DAYS(DATE(AH31,AG31*3-2,1),DATE(RIGHT(B31,4),MID(B31,4,2),LEFT(B31,2))) -> 459 | AP31: 23 | AQ31: V150-4.5MW
B32: 29.06.2022 | C32: Estonia | D32: 39 | E32: AOM5000 | F32: 30 | G32: Utilitas | H32: 9 | I32: V150-4.2MW | J32: 150 | K32: 4.3 | L32: opt 4.3MW | AG32: 2 | AH32: 2023 | AI32: =COUNTIF($I$158:$I$188,I32) -> 1 | AJ32: =COUNTIF($C$157:$C$188,C32) -> 1 | AK32: =COUNTIF($C$213:$C$246,C32) -> 1 | AL32: =_xlfn.DAYS(DATE(AH32,AG32*3-2,1),DATE(RIGHT(B32,4),MID(B32,4,2),LEFT(B32,2))) -> 276 | AP32: 11 | AQ32: V162-6.2MW
